Workbook

Sheet Transaction
A1: Emp Code | B1: Employee Name | C1: Date Of Joining | D1: Date Of Leaving | E1: Level | F1: Department | G1: Employment_Type | H1: Status | I1: Status Reason | J1: Location | K1: Date Of Confirmation | L1: Prior Experience | M1: Current Company Experience | N1: Total Experience | O1: Project Name | P1: Date Of Birth | Q1: Gender | R1: Reason Category | S1: Reason for Resignation | T1: Attrition | U1: Source | V1: Age | W1: Blood Group | X1: Marital Status | Y1: Address | Z1: Phone No | AA1: Rating | AB1: Education | AC1: region | AD1: Skills
A2: E7 | B2: GAYLE NEWENHAM | C2: 42725 | E2: L8 | F2: BI | G2: Employees | H2: Active | I2: Confirmed | J2: Gurugram | K2: 40408 | L2: 10 | M2: =IF(H2<>"03 Exit",(TODAY()-C2)/365,DATEDIF(C2,D2,"Y")) -> 6.7808219 | N2: =L2+M2 -> 16.780822 | O2: DHFL | P2: 27432 | Q2: Male | T2: =IF(D2="","No","Yes") -> No | U2: Referrals | V2: 44 | W2: AB+ | X2: Married | Y2: Address | Z2: 1539228581 | AA2: 3 | AB2: Master's | AC2: region_15 | AD2: Control Assessment
A3: E12 | B3: CHRISTIAN MCWHIRTER | C3: 42726 | E3: L8 | F3: BI | G3: Employees | H3: Active | I3: Confirmed | J3: Gurugram | K3: 40408 | L3: 10 | M3: =IF(H3<>"03 Exit",(TODAY()-C3)/365,DATEDIF(C3,D3,"Y")) -> 6.7780822 | N3: =L3+M3 -> 16.778082 | O3: UST India | P3: 31393 | Q3: Male | T3: =IF(D3="","No","Yes") -> No | U3: Social media | V3: 37 | W3: B+ | X3: Married | Y3: Address | Z3: 4049812195 | AA3: 4 | AB3: Master's | AC3: region_2 | AD3: Control Assessment
A4: E14 | B4: CORY BLISSETT | C4: 42727 | E4: L8 | F4: BI | G4: Employees | H4: Active | I4: Confirmed | J4: Pune | K4: 40408 | L4: 10 | M4: =IF(H4<>"03 Exit",(TODAY()-C4)/365,DATEDIF(C4,D4,"Y")) -> 6.7753425 | N4: =L4+M4 -> 16.775342 | O4: Adobe | P4: 31815 | Q4: Male | T4: =IF(D4="","No","Yes") -> No | U4: Career Fairs | V4: 22 | W4: B- | X4: Unmarried | Y4: Address | Z4: 4325856210 | AA4: 3 | AB4: MBA | AC4: region_15 | AD4: Control Assessment
A5: E15 | B5: BRETT DIERCKS | C5: 42728 | E5: L8 | F5: BI | G5: Employees | H5: Active | I5: Confirmed | J5: Pune | K5: 40408 | L5: 10 | M5: =IF(H5<>"03 Exit",(TODAY()-C5)/365,DATEDIF(C5,D5,"Y")) -> 6.7726027 | N5: =L5+M5 -> 16.772603 | O5: DHFL | P5: 26888 | Q5: Male | T5: =IF(D5="","No","Yes") -> No | U5: job boards | V5: 26 | W5: B+ | X5: Unmarried | Y5: Address | Z5: 1855805439 | AA5: 3 | AB5: Master's | AC5: region_13 | AD5: Control Assessment
A6: E24 | B6: JACOB DETERS | C6: 42767 | E6: L5 | F6: BI | G6: Employees | H6: Active | I6: Confirmed | J6: Pune | K6: 40510 | L6: 0 | M6: =IF(H6<>"03 Exit",(TODAY()-C6)/365,DATEDIF(C6,D6,"Y")) -> 6.6657534 | N6: =L6+M6 -> 6.6657534 | O6: UST India | P6: 32285 | Q6: Male | T6: =IF(D6="","No","Yes") -> No | U6: Referrals | V6: 26 | W6: AB- | X6: Unmarried | Y6: Address | Z6: 1607018686 | AA6: 3 | AB6: MBA | AC6: region_15 | AD6: VAPT
A7: E27 | B7: KELLEY CLAUSING | C7: 40406 | E7: L8 | F7: BI | G7: Employees | H7: Active | I7: Confirmed | J7: Pune | K7: 40496 | L7: 10 | M7: =IF(H7<>"03 Exit",(TODAY()-C7)/365,DATEDIF(C7,D7,"Y")) -> 13.134247 | N7: =L7+M7 -> 23.134247 | O7: DHFL | P7: 30372 | Q7: Male | T7: =IF(D7="","No","Yes") -> No | U7: Referrals | V7: 37 | W7: AB+ | X7: Married | Y7: Address | Z7: 2904261610 | AA7: 3 | AB7: MBA | AC7: region_15 | AD7: Control Assessment
A8: E36 | B8: LISA BARRY | C8: 40742 | E8: L4 | F8: Cloud | G8: Employees | H8: Active | I8: Confirmed | J8: Gurugram | K8: 40922 | L8: 0 | M8: =IF(H8<>"03 Exit",(TODAY()-C8)/365,DATEDIF(C8,D8,"Y")) -> 12.213699 | N8: =L8+M8 -> 12.213699 | O8: Reliance | P8: 31718 | Q8: Male | T8: =IF(D8="","No","Yes") -> No | U8: Referrals | V8: 41 | W8: B- | X8: Married | Y8: Address | Z8: 3856685469 | AA8: 4 | AB8: Bachelor's | AC8: region_15 | AD8: .net Developer / C Sharp
A9: E38 | B9: RANDALL SKALICKY | C9: 40777 | E9: L5 | F9: BI | G9: Employees | H9: Active | I9: Confirmed | J9: Pune | K9: 40957 | L9: 2 | M9: =IF(H9<>"03 Exit",(TODAY()-C9)/365,DATEDIF(C9,D9,"Y")) -> 12.117808 | N9: =L9+M9 -> 14.117808 | O9: UST India | P9: 32080 | Q9: Male | T9: =IF(D9="","No","Yes") -> No | U9: Referrals | V9: 33 | W9: A- | X9: Married | Y9: Address | Z9: 1080440734 | AA9: 4 | AB9: MBA | AC9: region_22 | AD9: VAPT
A10: E53 | B10: REGINALD GUYTON | C10: 41180 | E10: L4 | F10: BI | G10: Employees | H10: Active | I10: Confirmed | J10: Pune | K10: 41360 | L10: 10 | M10: =IF(H10<>"03 Exit",(TODAY()-C10)/365,DATEDIF(C10,D10,"Y")) -> 11.013699 | N10: =L10+M10 -> 21.013699 | O10: Eureka Forbes | P10: 24685 | Q10: Male | T10: =IF(D10="","No","Yes") -> No | U10: Referrals | V10: 36 | W10: AB+ | X10: Unmarried | Y10: Address | Z10: 2757754001 | AA10: 4 | AB10: Bachelor's | AC10: region_2 | AD10: TPA
A11: E56 | B11: TED KEYLON | C11: 41302 | E11: L4 | F11: BI | G11: Employees | H11: Active | I11: Confirmed | J11: Pune | K11: 41395 | L11: 0 | M11: =IF(H11<>"03 Exit",(TODAY()-C11)/365,DATEDIF(C11,D11,"Y")) -> 10.679452 | N11: =L11+M11 -> 10.679452 | P11: 33318 | Q11: Male | T11: =IF(D11="","No","Yes") -> No | U11: Referrals | V11: 38 | W11: AB- | X11: Unmarried | Y11: Address | Z11: 7150875917 | AA11: 3 | AB11: MBA | AC11: region_13 | AD11: TPA
A12: E62 | B12: THOMAS WHALEN | C12: 41365 | E12: L4 | F12: BI | G12: Employees | H12: Active | I12: Confirmed | J12: Pune | K12: 41487 | L12: 0 | M12: =IF(H12<>"03 Exit",(TODAY()-C12)/365,DATEDIF(C12,D12,"Y")) -> 10.506849 | N12: =L12+M12 -> 10.506849 | O12: UST India | P12: 32670 | Q12: Female | T12: =IF(D12="","No","Yes") -> No | U12: Referrals | V12: 28 | W12: A+ | X12: Unmarried | Y12: Address | Z12: 5894904547 | AA12: 3 | AB12: Bachelor's | AC12: region_15 | AD12: TPA
A13: E63 | B13: ZAXXSON NATION | C13: 41365 | E13: L5 | F13: BI | G13: Employees | H13: Active | I13: Confirmed | J13: Pune | K13: 41487 | L13: 3.4 | M13: =IF(H13<>"03 Exit",(TODAY()-C13)/365,DATEDIF(C13,D13,"Y")) -> 10.506849 | N13: =L13+M13 -> 13.906849 | O13: EFL | P13: 31565 | Q13: Male | T13: =IF(D13="","No","Yes") -> No | U13: Referrals | V13: 36 | W13: AB- | X13: Married | Y13: Address | Z13: 3597082916 | AA13: 3 | AB13: MBA | AC13: region_22 | AD13: VAPT
A14: E64 | B14: ABIGAIL CLINE | C14: 41372 | E14: L4 | F14: BI | G14: Employees | H14: Active | I14: Confirmed | J14: Mumbai | K14: 41487 | L14: 3.5 | M14: =IF(H14<>"03 Exit",(TODAY()-C14)/365,DATEDIF(C14,D14,"Y")) -> 10.487671 | N14: =L14+M14 -> 13.987671 | O14: UST India | P14: 30519 | Q14: Male | T14: =IF(D14="","No","Yes") -> No | U14: Referrals | V14: 26 | W14: B- | X14: Unmarried | Y14: Address | Z14: 7723611545 | AA14: 3 | AB14: Master's | AC14: region_22 | AD14: TPA
A15: E76 | B15: ADAM CURRAN | C15: 41507 | E15: L6 | F15: BI | G15: Employees | H15: Active | I15: Confirmed | J15: Mumbai | K15: 41597 | L15: 12 | M15: =IF(H15<>"03 Exit",(TODAY()-C15)/365,DATEDIF(C15,D15,"Y")) -> 10.117808 | N15: =L15+M15 -> 22.117808 | O15: DHFL | P15: 29411 | Q15: Male | T15: =IF(D15="","No","Yes") -> No | U15: Referrals | V15: 36 | W15: AB+ | X15: Unmarried | Y15: Address | Z15: 2447602721 | AA15: 3 | AB15: Bachelor's | AC15: region_2 | AD15: VAPT
A16: E85 | B16: MALIK WHEATLEY | C16: 41813 | D16: 44335 | E16: L2 | F16: BI | G16: Employees | H16: 03 Exit | J16: PUNE | M16: =IF(H16<>"03 Exit",(TODAY()-C16)/365,DATEDIF(C16,D16,"Y")) -> 6 | Q16: Female | R16: Voluntary | S16: Family Reasons | T16: =IF(D16="","No","Yes") -> Yes | U16: Social media | V16: 28 | W16: A- | X16: Unmarried | Y16: Address | Z16: 9562177743 | AA16: 3 | AB16: MBA | AC16: region_15 | AD16: Python Engineer, Data science and ETL
A17: E89 | B17: ALAN LOWE | C17: 41834 | E17: L4 | F17: BI | G17: Employees | H17: Active | I17: Confirmed | J17: Pune | K17: 41927 | L17: 4 | M17: =IF(H17<>"03 Exit",(TODAY()-C17)/365,DATEDIF(C17,D17,"Y")) -> 9.2219178 | N17: =L17+M17 -> 13.221918 | O17: Eureka Forbes | P17: 32074 | Q17: Female | T17: =IF(D17="","No","Yes") -> No | U17: Referrals | V17: 48 | W17: O+ | X17: Unmarried | Y17: Address | Z17: 5053084886 | AA17: 3 | AB17: Master's | AC17: region_15 | AD17: TPA
A18: E98 | B18: AMANDA HELM | C18: 41911 | E18: L4 | F18: BI | G18: Employees | H18: Active | I18: Confirmed | J18: Pune | K18: 41944 | L18: 0.7 | M18: =IF(H18<>"03 Exit",(TODAY()-C18)/365,DATEDIF(C18,D18,"Y")) -> 9.0109589 | N18: =L18+M18 -> 9.7109589 | O18: UST India | P18: 33069 | Q18: Male | T18: =IF(D18="","No","Yes") -> No | U18: Referrals | V18: 36 | W18: B- | X18: Unmarried | Y18: Address | Z18: 7568347648 | AA18: 3 | AB18: MBA | AC18: region_15 | AD18: TPA
A19: E99 | B19: ANGELA BLACKMAN | C19: 41913 | E19: L5 | F19: BI | G19: On Contract | H19: Active | I19: Confirmed | J19: Gurugram | K19: =C19+89 -> 42002 | L19: 14 | M19: =IF(H19<>"03 Exit",(TODAY()-C19)/365,DATEDIF(C19,D19,"Y")) -> 9.0054795 | N19: =L19+M19 -> 23.005479 | O19: UST India | P19: 27729 | Q19: Male | T19: =IF(D19="","No","Yes") -> No | U19: Referrals | V19: 30 | W19: A+ | X19: Married | Y19: Address | Z19: 2993619626 | AA19: 3 | AB19: Master's | AC19: region_2 | AD19: VAPT
A20: E100 | B20: ARTHUR CAREY | C20: 42691 | E20: L6 | F20: BI | G20: Employees | H20: Active | I20: Confirmed | J20: Pune | K20: 42051 | L20: 20 | M20: =IF(H20<>"03 Exit",(TODAY()-C20)/365,DATEDIF(C20,D20,"Y")) -> 6.8739726 | N20: =L20+M20 -> 26.873973 | O20: DHFL | P20: 26138 | Q20: Male | T20: =IF(D20="","No","Yes") -> No | U20: Referrals | V20: 48 | W20: O- | X20: Unmarried | Y20: Address | Z20: 3398419796 | AA20: 3 | AB20: MBA | AC20: region_2 | AD20: VAPT
A21: E115 | B21: BONNIE PARR | C21: 42135 | E21: L4 | F21: Support | G21: Employees | H21: Active | I21: Confirmed | J21: Pune | K21: 42217 | L21: 7 | M21: =IF(H21<>"03 Exit",(TODAY()-C21)/365,DATEDIF(C21,D21,"Y")) -> 8.3972603 | N21: =L21+M21 -> 15.39726 | P21: 30817 | Q21: Male | T21: =IF(D21="","No","Yes") -> No | U21: Referrals | V21: 38 | W21: A+ | X21: Unmarried | Y21: Address | Z21: 3605137329 | AA21: 3 | AB21: Master's | AC21: region_15 | AD21: TPA
A22: E116 | B22: BRITTA BRACKNEY | C22: 42149 | E22: L4 | F22: BI | G22: Employees | H22: Active | I22: Confirmed | J22: Pune | K22: 42248 | L22: 0 | M22: =IF(H22<>"03 Exit",(TODAY()-C22)/365,DATEDIF(C22,D22,"Y")) -> 8.3589041 | N22: =L22+M22 -> 8.3589041 | O22: Cigna | P22: 33449 | Q22: Male | T22: =IF(D22="","No","Yes") -> No | U22: Referrals | V22: 35 | W22: A+ | X22: Unmarried | Y22: Address | Z22: 4034138457 | AA22: 3 | AB22: Bachelor's | AC22: region_15 | AD22: TPA
A23: E127 | B23: CARLA SMITH | C23: 42219 | E23: L5 | F23: BI | G23: Employees | H23: Active | I23: Confirmed | J23: Pune | K23: 42309 | L23: 13 | M23: =IF(H23<>"03 Exit",(TODAY()-C23)/365,DATEDIF(C23,D23,"Y")) -> 8.1671233 | N23: =L23+M23 -> 21.167123 | O23: OTIS | P23: 28766 | Q23: Male | T23: =IF(D23="","No","Yes") -> No | U23: Referrals | V23: 22 | W23: AB+ | X23: Unmarried | Y23: Address | Z23: 9557167069 | AA23: 4 | AB23: MBA | AC23: region_15 | AD23: VAPT
A24: E131 | B24: CHAD BETTIS | C24: 42226 | E24: L4 | F24: BI | G24: Employees | H24: Active | I24: Confirmed | J24: Gurugram | K24: 42318 | L24: 7 | M24: =IF(H24<>"03 Exit",(TODAY()-C24)/365,DATEDIF(C24,D24,"Y")) -> 8.1479452 | N24: =L24+M24 -> 15.147945 | O24: Adobe | P24: 30772 | Q24: Male | T24: =IF(D24="","No","Yes") -> No | U24: Referrals | V24: 36 | W24: O+ | X24: Unmarried | Y24: Address | Z24: 5473777717 | AA24: 3 | AB24: Bachelor's | AC24: region_13 | AD24: TPA
A25: E135 | B25: JILL BRUINGTON | C25: 42240 | E25: L4 | F25: QA & QC | G25: Employees | H25: Active | I25: Confirmed | J25: Pune | K25: 42339 | L25: 4.5 | M25: =IF(H25<>"03 Exit",(TODAY()-C25)/365,DATEDIF(C25,D25,"Y")) -> 8.109589 | N25: =L25+M25 -> 12.609589 | O25: IT | P25: 30281 | Q25: Female | T25: =IF(D25="","No","Yes") -> No | U25: Referrals | V25: 40 | W25: AB+ | X25: Married | Y25: Address | Z25: 7744269401 | AA25: 3 | AB25: Bachelor's | AC25: region_7 | AD25: ITGC
A26: E138 | B26: CHRISTOPHER SCHNELL | C26: 42263 | E26: L5 | F26: BI | G26: Employees | H26: Active | I26: Confirmed | J26: Gurugram | K26: 42262 | L26: 7 | M26: =IF(H26<>"03 Exit",(TODAY()-C26)/365,DATEDIF(C26,D26,"Y")) -> 8.0465753 | N26: =L26+M26 -> 15.046575 | O26: IT | P26: 31145 | Q26: Male | T26: =IF(D26="","No","Yes") -> No | U26: Referrals | V26: 44 | W26: AB- | X26: Unmarried | Y26: Address | Z26: 3553282486 | AA26: 3 | AB26: Master's | AC26: region_13 | AD26: IAM - Multiple Product
A27: E141 | B27: JORDAN JACKSON | C27: 42282 | D27: 44316 | E27: L3 | F27: BI | G27: Employees | H27: 03 Exit | J27: Pune | M27: =IF(H27<>"03 Exit",(TODAY()-C27)/365,DATEDIF(C27,D27,"Y")) -> 5 | Q27: Female | R27: Voluntary | S27: Growth Opportunities | T27: =IF(D27="","No","Yes") -> Yes | U27: Social media | V27: 33 | W27: A+ | X27: Married | Y27: Address | Z27: 3536341879 | AA27: 3 | AB27: Master's | AC27: region_7 | AD27: Python Engineer, Data science and ETL
A28: E145 | B28: CHRISTOPHER WILLS | C28: 42282 | E28: L3 | F28: BI | G28: Employees | H28: Active | I28: Confirmed | J28: Pune | K28: 42374 | L28: 0 | M28: =IF(H28<>"03 Exit",(TODAY()-C28)/365,DATEDIF(C28,D28,"Y")) -> 7.9945205 | N28: =L28+M28 -> 7.9945205 | O28: IT | P28: 33833 | Q28: Male | T28: =IF(D28="","No","Yes") -> No | U28: Referrals | V28: 28 | W28: A- | X28: Unmarried | Y28: Address | Z28: 6953753869 | AA28: 4 | AB28: Master's | AC28: region_7 | AD28: Python Engineer, Data science and ETL
A29: E150 | B29: CLARA THORPE | C29: 42324 | E29: L3 | F29: QA & QC | G29: Employees | H29: Active | I29: Confirmed | J29: Pune | K29: 42416 | L29: 2.11 | M29: =IF(H29<>"03 Exit",(TODAY()-C29)/365,DATEDIF(C29,D29,"Y")) -> 7.8794521 | N29: =L29+M29 -> 9.9894521 | O29: IT | P29: 31274 | Q29: Male | T29: =IF(D29="","No","Yes") -> No | U29: Referrals | V29: 39 | W29: B- | X29: Unmarried | Y29: Address | Z29: 9576493121 | AA29: 3 | AB29: Bachelor's | AC29: region_7 | AD29: SAP Controls Transformation
A30: E156 | B30: COLBY MARS | C30: 42370 | E30: L1 | F30: Support | G30: Employees | H30: Active | I30: Confirmed | J30: Pune | K30: 42461 | L30: 2 | M30: =IF(H30<>"03 Exit",(TODAY()-C30)/365,DATEDIF(C30,D30,"Y")) -> 7.7534247 | N30: =L30+M30 -> 9.7534247 | O30: Admin | P30: 34206 | Q30: Male | T30: =IF(D30="","No","Yes") -> No | U30: Referrals | V30: 44 | W30: B+ | X30: Married | Y30: Address | Z30: 5132664546 | AA30: 3 | AB30: MBA | AC30: region_7 | AD30: SAP Controls Transformation
A31: E158 | B31: CYNTHIA HAMOR | C31: 42394 | E31: L4 | F31: BI | G31: Employees | H31: Active | I31: Confirmed | J31: Pune | K31: 42461 | L31: 2.8 | M31: =IF(H31<>"03 Exit",(TODAY()-C31)/365,DATEDIF(C31,D31,"Y")) -> 7.6876712 | N31: =L31+M31 -> 10.487671 | O31: IT | P31: 32910 | Q31: Male | T31: =IF(D31="","No","Yes") -> No | U31: Referrals | V31: 30 | W31: AB+ | X31: Married | Y31: Address | Z31: 6183121500 | AA31: 3 | AB31: MBA | AC31: region_13 | AD31: TPA
A32: E181 | B32: DALE VANDEVENTER | C32: 42522 | E32: L3 | F32: BI | G32: Employees | H32: Active | I32: Confirmed | J32: Pune | K32: 42614 | L32: 2.5 | M32: =IF(H32<>"03 Exit",(TODAY()-C32)/365,DATEDIF(C32,D32,"Y")) -> 7.3369863 | N32: =L32+M32 -> 9.8369863 | P32: 32172 | Q32: Female | T32: =IF(D32="","No","Yes") -> No | U32: Referrals | V32: 27 | W32: A+ | X32: Married | Y32: Address | Z32: 5360230333 | AA32: 3 | AB32: Bachelor's | AC32: region_15 | AD32: Python Engineer, Data science and ETL
A33: E192 | B33: DANIEL WORTHINGTON | C33: 42552 | E33: L3 | F33: BI | G33: Employees | H33: Active | I33: Confirmed | J33: Pune | K33: 42644 | L33: 0 | M33: =IF(H33<>"03 Exit",(TODAY()-C33)/365,DATEDIF(C33,D33,"Y")) -> 7.2547945 | N33: =L33+M33 -> 7.2547945 | O33: VFS Project | P33: 34222 | Q33: Male | T33: =IF(D33="","No","Yes") -> No | U33: job boards | V33: 34 | W33: B- | X33: Unmarried | Y33: Address | Z33: 4525787344 | AA33: 3 | AB33: MBA | AC33: region_13 | AD33: Python Engineer, Data science and ETL
A34: E196 | B34: MARIA JONES | C34: 42552 | D34: 44320 | E34: L2 | F34: Cloud | G34: Employees | H34: 03 Exit | J34: PUNE | M34: =IF(H34<>"03 Exit",(TODAY()-C34)/365,DATEDIF(C34,D34,"Y")) -> 4 | Q34: Female | R34: Voluntary | S34: Growth Opportunities | T34: =IF(D34="","No","Yes") -> Yes | U34: Social media | V34: 44 | W34: O+ | X34: Married | Y34: Address | Z34: 1117655842 | AA34: 3 | AB34: Bachelor's | AC34: region_22 | AD34: Cloud Computing
A35: E198 | B35: DANNY WILLIAMS | C35: 42552 | E35: L3 | F35: BI | G35: Employees | H35: Active | I35: Confirmed | J35: Pune | K35: 42644 | L35: 0 | M35: =IF(H35<>"03 Exit",(TODAY()-C35)/365,DATEDIF(C35,D35,"Y")) -> 7.2547945 | N35: =L35+M35 -> 7.2547945 | O35: IT | P35: 34458 | Q35: Male | T35: =IF(D35="","No","Yes") -> No | U35: job boards | V35: 44 | W35: B+ | X35: Unmarried | Y35: Address | Z35: 9289938852 | AA35: 3 | AB35: Master's | AC35: region_15 | AD35: Python Engineer, Data science and ETL
A36: E201 | B36: SHAWN PETTIT | C36: 42555 | D36: 44417 | E36: L2 | F36: BI | G36: Employees | H36: 03 Exit | J36: PUNE | M36: =IF(H36<>"03 Exit",(TODAY()-C36)/365,DATEDIF(C36,D36,"Y")) -> 5 | Q36: Female | R36: Voluntary | S36: Growth Opportunities | T36: =IF(D36="","No","Yes") -> Yes | U36: Social media | V36: 36 | W36: O- | X36: Married | Y36: Address | Z36: 1924725075 | AA36: 3 | AB36: Master's | AC36: region_13 | AD36: Python Engineer, Data science and ETL
A37: E208 | B37: DARCI DURBIN | C37: 42569 | E37: L3 | F37: BI | G37: Employees | H37: Active | I37: Confirmed | J37: Pune | K37: 42675 | L37: 1 | M37: =IF(H37<>"03 Exit",(TODAY()-C37)/365,DATEDIF(C37,D37,"Y")) -> 7.2082192 | N37: =L37+M37 -> 8.2082192 | O37: GS Labs | P37: 32916 | Q37: Male | T37: =IF(D37="","No","Yes") -> No | U37: job boards | V37: 48 | W37: A+ | X37: Married | Y37: Address | Z37: 9346886405 | AA37: 3 | AB37: Bachelor's | AC37: region_7 | AD37: Python Engineer, Data science and ETL
A38: E210 | B38: DAVID KELM | C38: 42569 | E38: L5 | F38: BI | G38: Employees | H38: Active | I38: Confirmed | J38: Bengaluru | K38: 42675 | L38: 13 | M38: =IF(H38<>"03 Exit",(TODAY()-C38)/365,DATEDIF(C38,D38,"Y")) -> 7.2082192 | N38: =L38+M38 -> 20.208219 | O38: IT | P38: 29602 | Q38: Male | T38: =IF(D38="","No","Yes") -> No | U38: job boards | V38: 23 | W38: A+ | X38: Married | Y38: Address | Z38: 5041342834 | AA38: 3 | AB38: Master's | AC38: region_2 | AD38: IAM - Multiple Product
A39: E214 | B39: DAVID PAINE | C39: 42583 | E39: L4 | F39: BI | G39: Employees | H39: Active | I39: Confirmed | J39: Pune | K39: 42705 | L39: 1 | M39: =IF(H39<>"03 Exit",(TODAY()-C39)/365,DATEDIF(C39,D39,"Y")) -> 7.169863 | N39: =L39+M39 -> 8.169863 | O39: Eureka Forbes | P39: 34048 | Q39: Male | T39: =IF(D39="","No","Yes") -> No | U39: job boards | V39: 43 | W39: AB- | X39: Unmarried | Y39: Address | Z39: 6362281905 | AA39: 3 | AB39: Master's | AC39: region_7 | AD39: TPA
A40: E230 | B40: DEBBIE HAMM | C40: 42625 | E40: L4 | F40: BI | G40: Employees | H40: Active | I40: Confirmed | J40: Pune | K40: 42767 | L40: 3 | M40: =IF(H40<>"03 Exit",(TODAY()-C40)/365,DATEDIF(C40,D40,"Y")) -> 7.0547945 | N40: =L40+M40 -> 10.054795 | P40: 33096 | Q40: Male | T40: =IF(D40="","No","Yes") -> No | U40: Referrals | V40: 37 | W40: A+ | X40: Unmarried | Y40: Address | Z40: 4445160441 | AA40: 3 | AB40: Bachelor's | AC40: region_7 | AD40: TPA
A41: E236 | B41: DEBBIE ROSS | C41: 42646 | E41: L5 | F41: BI | G41: Employees | H41: Active | I41: Confirmed | J41: Pune | K41: 42736 | L41: 8.1 | M41: =IF(H41<>"03 Exit",(TODAY()-C41)/365,DATEDIF(C41,D41,"Y")) -> 6.9972603 | N41: =L41+M41 -> 15.09726 | O41: IT | P41: 30847 | Q41: Male | T41: =IF(D41="","No","Yes") -> No | U41: Referrals | V41: 39 | W41: B- | X41: Unmarried | Y41: Address | Z41: 8240406926 | AA41: 3 | AB41: Master's | AC41: region_7 | AD41: IAM - Multiple Product
A42: E243 | B42: DEBRA SALISBURY | C42: 42660 | E42: L5 | F42: BI | G42: Employees | H42: Active | I42: Confirmed | J42: Bengaluru | K42: 42750 | L42: 15 | M42: =IF(H42<>"03 Exit",(TODAY()-C42)/365,DATEDIF(C42,D42,"Y")) -> 6.9589041 | N42: =L42+M42 -> 21.958904 | O42: EFL | P42: 26375 | Q42: Male | T42: =IF(D42="","No","Yes") -> No | U42: Referrals | V42: 26 | W42: O+ | X42: Married | Y42: Address | Z42: 2098190421 | AA42: 3 | AB42: Bachelor's | AC42: region_15 | AD42: IAM - Multiple Product
A43: E247 | B43: DENNIS HOLLOWAY | C43: 42677 | E43: L4 | F43: BI | G43: Employees | H43: Active | I43: Confirmed | J43: Bengaluru | K43: 42826 | L43: 2.1 | M43: =IF(H43<>"03 Exit",(TODAY()-C43)/365,DATEDIF(C43,D43,"Y")) -> 6.9123288 | N43: =L43+M43 -> 9.0123288 | O43: RBS | P43: 33634 | Q43: Male | T43: =IF(D43="","No","Yes") -> No | U43: Referrals | V43: 34 | W43: AB+ | X43: Married | Y43: Address | Z43: 5146331962 | AA43: 3 | AB43: Master's | AC43: region_7 | AD43: TPA
A44: E251 | B44: EDWARD HARMEYER | C44: 42695 | E44: L2 | F44: BI | G44: Employees | H44: Active | I44: Confirmed | J44: Pune | K44: 42826 | L44: 0 | M44: =IF(H44<>"03 Exit",(TODAY()-C44)/365,DATEDIF(C44,D44,"Y")) -> 6.8630137 | N44: =L44+M44 -> 6.8630137 | P44: 33890 | Q44: Male | T44: =IF(D44="","No","Yes") -> No | U44: Referrals | V44: 39 | W44: A- | X44: Married | Y44: Address | Z44: 1282855230 | AA44: 3 | AB44: Master's | AC44: region_2 | AD44: Python Engineer, Data science and ETL
A45: E259 | B45: EDWARD MACMURDO | C45: 42695 | E45: L3 | F45: BI | G45: Employees | H45: Active | I45: Confirmed | J45: Pune | K45: 42826 | L45: 0 | M45: =IF(H45<>"03 Exit",(TODAY()-C45)/365,DATEDIF(C45,D45,"Y")) -> 6.8630137 | N45: =L45+M45 -> 6.8630137 | P45: 33872 | Q45: Female | T45: =IF(D45="","No","Yes") -> No | U45: Referrals | V45: 22 | W45: AB+ | X45: Unmarried | Y45: Address | Z45: 8726535354 | AA45: 3 | AB45: Master's | AC45: region_13 | AD45: Python Engineer, Data science and ETL
A46: E262 | B46: GARRETT WEST | C46: 42711 | E46: L2 | F46: Cloud | G46: Employees | H46: Active | I46: Confirmed | J46: Pune | K46: 42917 | L46: 2 | M46: =IF(H46<>"03 Exit",(TODAY()-C46)/365,DATEDIF(C46,D46,"Y")) -> 6.8191781 | N46: =L46+M46 -> 8.8191781 | O46: HSBC | P46: 31313 | Q46: Female | T46: =IF(D46="","No","Yes") -> No | U46: Referrals | V46: 39 | W46: B- | X46: Married | Y46: Address | Z46: 8356027589 | AA46: 4 | AB46: MBA | AC46: region_15 | AD46: Cloud Computing
A47: E266 | B47: GENEVIEVE KAPLAN | C47: 42744 | E47: L4 | F47: BI | G47: Employees | H47: Active | I47: Confirmed | J47: Pune | K47: 42856 | L47: 2 | M47: =IF(H47<>"03 Exit",(TODAY()-C47)/365,DATEDIF(C47,D47,"Y")) -> 6.7287671 | N47: =L47+M47 -> 8.7287671 | O47: IT | P47: 33805 | Q47: Male | T47: =IF(D47="","No","Yes") -> No | U47: Referrals | V47: 38 | W47: O+ | X47: Married | Y47: Address | Z47: 5269092678 | AA47: 3 | AB47: Master's | AC47: region_2 | AD47: TPA
A48: E272 | B48: HANNAH ROSS | C48: 42758 | E48: L1 | F48: Support | G48: Employees | H48: Active | I48: Confirmed | J48: Gurugram | K48: 42917 | L48: 1 | M48: =IF(H48<>"03 Exit",(TODAY()-C48)/365,DATEDIF(C48,D48,"Y")) -> 6.690411 | N48: =L48+M48 -> 7.690411 | O48: Admin | P48: 33805 | Q48: Male | T48: =IF(D48="","No","Yes") -> No | U48: Referrals | V48: 44 | W48: AB+ | X48: Married | Y48: Address | Z48: 6574809840 | AA48: 4 | AB48: MBA | AC48: region_13 | AD48: SAP Controls Transformation
A49: E278 | B49: HAROLD STURM | C49: 42767 | E49: L3 | F49: BI | G49: Employees | H49: Active | I49: Confirmed | J49: Pune | K49: 43009 | L49: 0 | M49: =IF(H49<>"03 Exit",(TODAY()-C49)/365,DATEDIF(C49,D49,"Y")) -> 6.6657534 | N49: =L49+M49 -> 6.6657534 | O49: IT | P49: 33806 | Q49: Male | T49: =IF(D49="","No","Yes") -> No | U49: Referrals | V49: 25 | W49: A+ | X49: Married | Y49: Address | Z49: 8955792637 | AA49: 4 | AB49: MBA | AC49: region_7 | AD49: Python Engineer, Data science and ETL
A50: E279 | B50: MARJORIE DALE | C50: 44228 | D50: 44344 | E50: L2 | F50: BI | G50: Employees | H50: 03 Exit | J50: PUNE | M50: =IF(H50<>"03 Exit",(TODAY()-C50)/365,DATEDIF(C50,D50,"Y")) -> 0 | Q50: Female | R50: Voluntary | S50: Growth Opportunities | T50: =IF(D50="","No","Yes") -> Yes | U50: Referrals | V50: 48 | W50: A- | X50: Married | Y50: Address | Z50: 4520405338 | AA50: 4 | AB50: Master's | AC50: region_15 | AD50: Python Engineer, Data science and ETL
A51: E282 | B51: ROBERT SCHNEIDER | C51: 42767 | D51: 44547 | E51: L2 | F51: BI | G51: Employees | H51: 03 Exit | J51: Pune | M51: =IF(H51<>"03 Exit",(TODAY()-C51)/365,DATEDIF(C51,D51,"Y")) -> 4 | Q51: Female | R51: Voluntary | S51: Further Studies | T51: =IF(D51="","No","Yes") -> Yes | U51: Referrals | V51: 49 | W51: O+ | X51: Unmarried | Y51: Address | Z51: 9021736633 | AA51: 3 | AB51: Master's | AC51: region_7 | AD51: Python Engineer, Data science and ETL
A52: E283 | B52: IAN HUNT | C52: 42767 | E52: L3 | F52: BI | G52: Employees | H52: Active | I52: Confirmed | J52: Pune | K52: 43009 | L52: 0 | M52: =IF(H52<>"03 Exit",(TODAY()-C52)/365,DATEDIF(C52,D52,"Y")) -> 6.6657534 | N52: =L52+M52 -> 6.6657534 | O52: IT | P52: 34488 | Q52: Female | T52: =IF(D52="","No","Yes") -> No | U52: Referrals | V52: 33 | W52: AB- | X52: Unmarried | Y52: Address | Z52: 4835829528 | AA52: 3 | AB52: Bachelor's | AC52: region_13 | AD52: Python Engineer, Data science and ETL
A53: E292 | B53: TYRE WRIGHT | C53: 42795 | D53: 44455 | E53: L3 | F53: BI | G53: Employees | H53: 03 Exit | J53: PUNE | M53: =IF(H53<>"03 Exit",(TODAY()-C53)/365,DATEDIF(C53,D53,"Y")) -> 4 | Q53: Female | R53: Voluntary | S53: Growth Opportunities | T53: =IF(D53="","No","Yes") -> Yes | U53: Referrals | V53: 27 | W53: AB+ | X53: Married | Y53: Address | Z53: 7546214914 | AA53: 3 | AB53: Master's | AC53: region_22 | AD53: Python Engineer, Data science and ETL
A54: E298 | B54: JAMES CORNELIUS | C54: 42795 | E54: L3 | F54: BI | G54: Employees | H54: Active | I54: Confirmed | J54: Gurugram | K54: 43009 | L54: 0 | M54: =IF(H54<>"03 Exit",(TODAY()-C54)/365,DATEDIF(C54,D54,"Y")) -> 6.5890411 | N54: =L54+M54 -> 6.5890411 | O54: DHFL | P54: 33598 | Q54: Male | T54: =IF(D54="","No","Yes") -> No | U54: Referrals | V54: 32 | W54: A- | X54: Married | Y54: Address | Z54: 3073839701 | AA54: 4 | AB54: MBA | AC54: region_13 | AD54: Python Engineer, Data science and ETL
A55: E307 | B55: JEFFREY NEVINS | C55: 42816 | E55: L3 | F55: QA & QC | G55: Employees | H55: Active | I55: Confirmed | J55: Pune | K55: 42917 | L55: 1.6 | M55: =IF(H55<>"03 Exit",(TODAY()-C55)/365,DATEDIF(C55,D55,"Y")) -> 6.5315068 | N55: =L55+M55 -> 8.1315068 | O55: OTIS | P55: 34192 | Q55: Male | T55: =IF(D55="","No","Yes") -> No | U55: Referrals | V55: 31 | W55: O- | X55: Married | Y55: Address | Z55: 6260848284 | AA55: 3 | AB55: Bachelor's | AC55: region_22 | AD55: SAP Controls Transformation
A56: E308 | B56: JENIFER BROWNELL | C56: 42828 | E56: L2 | F56: BI | G56: Employees | H56: Active | I56: Confirmed | J56: Pune | K56: 43009 | L56: 1 | M56: =IF(H56<>"03 Exit",(TODAY()-C56)/365,DATEDIF(C56,D56,"Y")) -> 6.4986301 | N56: =L56+M56 -> 7.4986301 | P56: 33901 | Q56: Female | T56: =IF(D56="","No","Yes") -> No | U56: Referrals | V56: 37 | W56: A- | X56: Married | Y56: Address | Z56: 2508353510 | AA56: 3 | AB56: Bachelor's | AC56: region_7 | AD56: Python Engineer, Data science and ETL
A57: E309 | B57: SHERRY REYNOLDS | C57: 42828 | D57: 44432 | E57: L3 | F57: QA & QC | G57: Employees | H57: 03 Exit | J57: PUNE | M57: =IF(H57<>"03 Exit",(TODAY()-C57)/365,DATEDIF(C57,D57,"Y")) -> 4 | Q57: Female | R57: Voluntary | S57: Growth Opportunities | T57: =IF(D57="","No","Yes") -> Yes | U57: Referrals | V57: 31 | W57: O- | X57: Unmarried | Y57: Address | Z57: 4604339786 | AA57: 3 | AB57: Bachelor's | AC57: region_15 | AD57: SAP Controls Transformation
A58: E312 | B58: JOSEPH CLOUD | C58: 42828 | D58: 44301 | E58: L1 | F58: Cloud | G58: Employees | H58: 03 Exit | J58: Pune | M58: =IF(H58<>"03 Exit",(TODAY()-C58)/365,DATEDIF(C58,D58,"Y")) -> 4 | Q58: Female | R58: Voluntary | S58: Growth Opportunities | T58: =IF(D58="","No","Yes") -> Yes | U58: Referrals | V58: 40 | W58: B- | X58: Unmarried | Y58: Address | Z58: 9646972362 | AA58: 4 | AB58: Bachelor's | AC58: region_2 | AD58: Cloud Computing
A59: E315 | B59: JERAMY TEDROW | C59: 42857 | E59: L1 | F59: Support | G59: Employees | H59: Active | I59: Confirmed | J59: Pune | K59: 43191 | L59: 2 | M59: =IF(H59<>"03 Exit",(TODAY()-C59)/365,DATEDIF(C59,D59,"Y")) -> 6.4191781 | N59: =L59+M59 -> 8.4191781 | P59: 28491 | Q59: Male | T59: =IF(D59="","No","Yes") -> No | U59: Referrals | V59: 37 | W59: O- | X59: Married | Y59: Address | Z59: 9013827899 | AA59: 3 | AB59: MBA | AC59: region_2 | AD59: SAP Controls Transformation
A60: E320 | B60: GERALD LINDBERG | C60: 42887 | D60: 44546 | E60: L2 | F60: QA & QC | G60: Employees | H60: 03 Exit | J60: Pune | M60: =IF(H60<>"03 Exit",(TODAY()-C60)/365,DATEDIF(C60,D60,"Y")) -> 4 | Q60: Female | R60: Voluntary | S60: Growth Opportunities | T60: =IF(D60="","No","Yes") -> Yes | U60: Social media | V60: 35 | W60: AB- | X60: Married | Y60: Address | Z60: 8051731349 | AA60: 4 | AB60: Bachelor's | AC60: region_2 | AD60: SAP Controls Transformation
A61: E323 | B61: JEREMY CARRELL | C61: 42919 | E61: L3 | F61: BI | G61: Employees | H61: Active | I61: Confirmed | J61: Pune | K61: 43040 | L61: 0 | M61: =IF(H61<>"03 Exit",(TODAY()-C61)/365,DATEDIF(C61,D61,"Y")) -> 6.2493151 | N61: =L61+M61 -> 6.2493151 | P61: 34779 | Q61: Female | T61: =IF(D61="","No","Yes") -> No | U61: Referrals | V61: 45 | W61: A+ | X61: Unmarried | Y61: Address | Z61: 6348645813 | AA61: 3 | AB61: MBA | AC61: region_7 | AD61: Python Engineer, Data science and ETL
A62: E324 | B62: KATHLEEN MUDD | C62: 42919 | E62: L3 | F62: BI | G62: Employees | H62: Active | I62: Confirmed | J62: Pune | K62: 43101 | L62: 0 | M62: =IF(H62<>"03 Exit",(TODAY()-C62)/365,DATEDIF(C62,D62,"Y")) -> 6.2493151 | N62: =L62+M62 -> 6.2493151 | O62: HSBC | P62: 35052 | Q62: Female | T62: =IF(D62="","No","Yes") -> No | U62: Referrals | V62: 34 | W62: AB- | X62: Unmarried | Y62: Address | Z62: 2738776591 | AA62: 4 | AB62: Master's | AC62: region_7 | AD62: Python Engineer, Data science and ETL
A63: E329 | B63: KREGG ARGENTA | C63: 42929 | E63: L5 | F63: BI | G63: Employees | H63: Active | I63: Confirmed | J63: Gurugram | K63: 43009 | L63: 13 | M63: =IF(H63<>"03 Exit",(TODAY()-C63)/365,DATEDIF(C63,D63,"Y")) -> 6.2219178 | N63: =L63+M63 -> 19.221918 | O63: HSBC | P63: 29724 | Q63: Male | T63: =IF(D63="","No","Yes") -> No | U63: Referrals | V63: 46 | W63: B+ | X63: Married | Y63: Address | Z63: 8137635944 | AA63: 3 | AB63: Bachelor's | AC63: region_13 | AD63: IAM - Multiple Product
A64: E333 | B64: KURT WILLIAMS | C64: 43006 | E64: L4 | F64: BI | G64: Employees | H64: Active | I64: Confirmed | J64: Mumbai | K64: 43101 | L64: 7.9 | M64: =IF(H64<>"03 Exit",(TODAY()-C64)/365,DATEDIF(C64,D64,"Y")) -> 6.0109589 | N64: =L64+M64 -> 13.910959 | O64: HSBC | P64: 32333 | Q64: Male | T64: =IF(D64="","No","Yes") -> No | U64: Referrals | V64: 38 | W64: AB- | X64: Unmarried | Y64: Address | Z64: 2881052979 | AA64: 3 | AB64: Bachelor's | AC64: region_15 | AD64: TPA
A65: E334 | B65: KEITH LITZ | C65: 43017 | D65: 44291 | E65: L3 | F65: BI | G65: Employees | H65: 03 Exit | J65: Pune | M65: =IF(H65<>"03 Exit",(TODAY()-C65)/365,DATEDIF(C65,D65,"Y")) -> 3 | Q65: Female | R65: Voluntary | S65: Growth Opportunities | T65: =IF(D65="","No","Yes") -> Yes | U65: Referrals | V65: 47 | W65: B+ | X65: Unmarried | Y65: Address | Z65: 4856242669 | AA65: 3 | AB65: Master's | AC65: region_7 | AD65: Python Engineer, Data science and ETL
A66: E335 | B66: LARRY BUMGARDNER | C66: 43070 | E66: L2 | F66: Support | G66: Employees | H66: Active | I66: Confirmed | J66: Gurugram | K66: 43191 | L66: 2 | M66: =IF(H66<>"03 Exit",(TODAY()-C66)/365,DATEDIF(C66,D66,"Y")) -> 5.8356164 | N66: =L66+M66 -> 7.8356164 | O66: IT | P66: 33954 | Q66: Male | T66: =IF(D66="","No","Yes") -> No | U66: Referrals | V66: 45 | W66: O- | X66: Married | Y66: Address | Z66: 7037271109 | AA66: 3 | AB66: Bachelor's | AC66: region_22 | AD66: SAP Controls Transformation
A67: E337 | B67: LAWRA VANDERHOOF | C67: 43080 | E67: L3 | F67: BI | G67: Employees | H67: Active | I67: Confirmed | J67: Pune | K67: 43191 | L67: 3.6 | M67: =IF(H67<>"03 Exit",(TODAY()-C67)/365,DATEDIF(C67,D67,"Y")) -> 5.8082192 | N67: =L67+M67 -> 9.4082192 | O67: IT | P67: 33499 | Q67: Male | T67: =IF(D67="","No","Yes") -> No | U67: Referrals | V67: 25 | W67: A+ | X67: Married | Y67: Address | Z67: 1642708474 | AA67: 3 | AB67: Bachelor's | AC67: region_15 | AD67: Python Engineer, Data science and ETL
A68: E339 | B68: REONA WILLIAMS | C68: 43108 | D68: 44406 | E68: L2 | F68: BI | G68: Employees | H68: 03 Exit | J68: PUNE | M68: =IF(H68<>"03 Exit",(TODAY()-C68)/365,DATEDIF(C68,D68,"Y")) -> 3 | Q68: Female | R68: Voluntary | S68: Growth Opportunities | T68: =IF(D68="","No","Yes") -> Yes | U68: Referrals | V68: 30 | W68: B+ | X68: Unmarried | Y68: Address | Z68: 5348469542 | AA68: 3 | AB68: Master's | AC68: region_7 | AD68: Python Engineer, Data science and ETL
A69: E344 | B69: KEITH PHILLIPS | C69: 43115 | D69: 44302 | E69: L4 | F69: BI | G69: Employees | H69: 03 Exit | J69: Pune | M69: =IF(H69<>"03 Exit",(TODAY()-C69)/365,DATEDIF(C69,D69,"Y")) -> 3 | Q69: Female | R69: Voluntary | S69: Growth Opportunities | T69: =IF(D69="","No","Yes") -> Yes | U69: Referrals | V69: 32 | W69: O- | X69: Married | Y69: Address | Z69: 7613965598 | AA69: 3 | AB69: Master's | AC69: region_7 | AD69: TPA
A70: E348 | B70: MARVIN CASSENS | C70: 43136 | D70: 44330 | E70: L1 | F70: BI | G70: Employees | H70: 03 Exit | J70: PUNE | M70: =IF(H70<>"03 Exit",(TODAY()-C70)/365,DATEDIF(C70,D70,"Y")) -> 3 | Q70: Female | R70: Voluntary | S70: Growth Opportunities | T70: =IF(D70="","No","Yes") -> Yes | U70: Referrals | V70: 23 | W70: O- | X70: Unmarried | Y70: Address | Z70: 4154424498 | AA70: 3 | AB70: Master's | AC70: region_13 | AD70: Python Engineer, Data science and ETL
A71: E349 | B71: MATT SARVER | C71: 43136 | D71: 44343 | E71: L1 | F71: Cloud | G71: Employees | H71: 03 Exit | J71: PUNE | M71: =IF(H71<>"03 Exit",(TODAY()-C71)/365,DATEDIF(C71,D71,"Y")) -> 3 | Q71: Female | R71: Voluntary | S71: Growth Opportunities | T71: =IF(D71="","No","Yes") -> Yes | U71: Referrals | V71: 43 | W71: B+ | X71: Married | Y71: Address | Z71: 9891305535 | AA71: 3 | AB71: Bachelor's | AC71: region_13 | AD71: Cloud Computing
A72: E350 | B72: LISA HORSLEY | C72: 43136 | E72: L3 | F72: BI | G72: Employees | H72: Active | I72: Confirmed | J72: Gurugram | K72: 43221 | L72: 1.5 | M72: =IF(H72<>"03 Exit",(TODAY()-C72)/365,DATEDIF(C72,D72,"Y")) -> 5.6547945 | N72: =L72+M72 -> 7.1547945 | P72: 33636 | Q72: Female | T72: =IF(D72="","No","Yes") -> No | U72: Referrals | V72: 35 | W72: A- | X72: Married | Y72: Address | Z72: 4636236141 | AA72: 3 | AB72: Bachelor's | AC72: region_13 | AD72: Python Engineer, Data science and ETL
A73: E351 | B73: KELBY BRUSS | C73: 43143 | D73: 44316 | E73: L3 | F73: BI | G73: Employees | H73: 03 Exit | J73: Mumbai | M73: =IF(H73<>"03 Exit",(TODAY()-C73)/365,DATEDIF(C73,D73,"Y")) -> 3 | Q73: Female | R73: Voluntary | S73: Growth Opportunities | T73: =IF(D73="","No","Yes") -> Yes | U73: Referrals | V73: 42 | W73: B- | X73: Married | Y73: Address | Z73: 9235002893 | AA73: 4 | AB73: MBA | AC73: region_22 | AD73: Python Engineer, Data science and ETL
A74: E355 | B74: MARK DEPUE | C74: 43150 | E74: L2 | F74: Cloud | G74: Employees | H74: Active | I74: Confirmed | J74: Pune | K74: 43252 | L74: 3.5 | M74: =IF(H74<>"03 Exit",(TODAY()-C74)/365,DATEDIF(C74,D74,"Y")) -> 5.6164384 | N74: =L74+M74 -> 9.1164384 | O74: IT | P74: 32250 | Q74: Female | T74: =IF(D74="","No","Yes") -> No | U74: Referrals | V74: 49 | W74: A+ | X74: Married | Y74: Address | Z74: 6315625077 | AA74: 3 | AB74: Master's | AC74: region_7 | AD74: Python Engineer, Data science and ETL
A75: E362 | B75: MARY BASKA | C75: 43164 | E75: L6 | F75: BI | G75: Employees | H75: Active | I75: Confirmed | J75: Pune | K75: 43252 | L75: 20 | M75: =IF(H75<>"03 Exit",(TODAY()-C75)/365,DATEDIF(C75,D75,"Y")) -> 5.5780822 | N75: =L75+M75 -> 25.578082 | O75: EFL | P75: 26667 | Q75: Male | T75: =IF(D75="","No","Yes") -> No | U75: Referrals | V75: 40 | W75: A- | X75: Unmarried | Y75: Address | Z75: 9482251956 | AA75: 3 | AB75: Master's | AC75: region_13 | AD75: IAM - Multiple Product
A76: E366 | B76: MATTHEW BAKER | C76: 43185 | E76: L2 | F76: QA & QC | G76: Employees | H76: Active | I76: Confirmed | J76: Pune | K76: 43282 | L76: 0.8 | M76: =IF(H76<>"03 Exit",(TODAY()-C76)/365,DATEDIF(C76,D76,"Y")) -> 5.5205479 | N76: =L76+M76 -> 6.3205479 | O76: IT | P76: 33801 | Q76: Male | T76: =IF(D76="","No","Yes") -> No | U76: Referrals | V76: 36 | W76: AB- | X76: Married | Y76: Address | Z76: 9178885027 | AA76: 3 | AB76: Master's | AC76: region_7 | AD76: SAP Controls Transformation
A77: E367 | B77: SHYILA LEEVE | C77: 43192 | D77: 44414 | E77: L3 | F77: BI | G77: Employees | H77: 03 Exit | J77: PUNE | M77: =IF(H77<>"03 Exit",(TODAY()-C77)/365,DATEDIF(C77,D77,"Y")) -> 3 | Q77: Male | R77: Voluntary | S77: Growth Opportunities | T77: =IF(D77="","No","Yes") -> Yes | U77: Referrals | V77: 45 | W77: A- | X77: Unmarried | Y77: Address | Z77: 7667111501 | AA77: 4 | AB77: Bachelor's | AC77: region_7 | AD77: Python Engineer, Data science and ETL
A78: E369 | B78: MICHAEL JONES | C78: 43206 | D78: 44343 | E78: L3 | F78: QA & QC | G78: Employees | H78: 03 Exit | J78: GURUGRAM | M78: =IF(H78<>"03 Exit",(TODAY()-C78)/365,DATEDIF(C78,D78,"Y")) -> 3 | Q78: Male | R78: Voluntary | S78: Growth Opportunities | T78: =IF(D78="","No","Yes") -> Yes | U78: Referrals | V78: 26 | W78: O- | X78: Unmarried | Y78: Address | Z78: 9320203902 | AA78: 3 | AB78: MBA | AC78: region_22 | AD78: SAP Controls Transformation
A79: E371 | B79: MATTHEW REUKER | C79: 43220 | E79: L5 | F79: BI | G79: Employees | H79: Active | I79: Confirmed | J79: Gurugram | K79: 43278 | L79: 8 | M79: =IF(H79<>"03 Exit",(TODAY()-C79)/365,DATEDIF(C79,D79,"Y")) -> 5.4246575 | N79: =L79+M79 -> 13.424658 | O79: IT | P79: 32118 | Q79: Male | T79: =IF(D79="","No","Yes") -> No | U79: Referrals | V79: 29 | W79: B- | X79: Unmarried | Y79: Address | Z79: 1866110290 | AA79: 3 | AB79: Master's | AC79: region_13 | AD79: IAM - Multiple Product
A80: E375 | B80: KENT BLOOM | C80: 43223 | D80: 44561 | E80: L3 | F80: BI | G80: Employees | H80: 03 Exit | J80: Pune | M80: =IF(H80<>"03 Exit",(TODAY()-C80)/365,DATEDIF(C80,D80,"Y")) -> 3 | Q80: Male | R80: Voluntary | S80: Growth Opportunities | T80: =IF(D80="","No","Yes") -> Yes | U80: Referrals | V80: 23 | W80: AB+ | X80: Unmarried | Y80: Address | Z80: 5202365720 | AA80: 3 | AB80: MBA | AC80: region_13 | AD80: Python Engineer, Data science and ETL
A81: E377 | B81: MYKEYLA WHEELER | C81: 43227 | D81: 44340 | E81: L2 | F81: BI | G81: Employees | H81: 03 Exit | J81: PUNE | M81: =IF(H81<>"03 Exit",(TODAY()-C81)/365,DATEDIF(C81,D81,"Y")) -> 3 | Q81: Male | R81: Voluntary | S81: Growth Opportunities | T81: =IF(D81="","No","Yes") -> Yes | U81: Social media | V81: 50 | W81: AB- | X81: Unmarried | Y81: Address | Z81: 7671170396 | AA81: 4 | AB81: MBA | AC81: region_22 | AD81: Python Engineer, Data science and ETL
A82: E378 | B82: MEGAN KLINTWORTH | C82: 43241 | E82: L3 | F82: BI | G82: Employees | H82: Active | I82: Confirmed | J82: Gurugram | K82: 43344 | L82: 2 | M82: =IF(H82<>"03 Exit",(TODAY()-C82)/365,DATEDIF(C82,D82,"Y")) -> 5.3671233 | N82: =L82+M82 -> 7.3671233 | O82: IT | P82: 34366 | Q82: Female | T82: =IF(D82="","No","Yes") -> No | U82: Referrals | V82: 27 | W82: A- | X82: Unmarried | Y82: Address | Z82: 4704355323 | AA82: 3 | AB82: Bachelor's | AC82: region_7 | AD82: Python Engineer, Data science and ETL
A83: E381 | B83: MEGHAN HARMON | C83: 43255 | E83: L5 | F83: QA & QC | G83: Employees | H83: Active | I83: Confirmed | J83: Pune | K83: 43327 | L83: 20 | M83: =IF(H83<>"03 Exit",(TODAY()-C83)/365,DATEDIF(C83,D83,"Y")) -> 5.3287671 | N83: =L83+M83 -> 25.328767 | O83: IT | P83: 25848 | Q83: Male | T83: =IF(D83="","No","Yes") -> No | U83: Referrals | V83: 50 | W83: AB- | X83: Unmarried | Y83: Address | Z83: 4450722395 | AA83: 3 | AB83: Bachelor's | AC83: region_13 | AD83: IAM - Multiple Product
A84: E382 | B84: VALERY ROBINSON | C84: 43255 | D84: 44442 | E84: L3 | F84: QA & QC | G84: Employees | H84: 03 Exit | J84: PUNE | M84: =IF(H84<>"03 Exit",(TODAY()-C84)/365,DATEDIF(C84,D84,"Y")) -> 3 | Q84: Male | R84: Voluntary | S84: Growth Opportunities | T84: =IF(D84="","No","Yes") -> Yes | U84: Referrals | V84: 35 | W84: B+ | X84: Unmarried | Y84: Address | Z84: 7962614481 | AA84: 3 | AB84: Master's | AC84: region_22 | AD84: SAP Controls Transformation
A85: E386 | B85: MICHAEL LAURENZANA | C85: 43262 | D85: 44494 | E85: L3 | F85: BI | G85: Employees | H85: 03 Exit | J85: Pune | M85: =IF(H85<>"03 Exit",(TODAY()-C85)/365,DATEDIF(C85,D85,"Y")) -> 3 | Q85: Male | R85: Voluntary | S85: Growth Opportunities | T85: =IF(D85="","No","Yes") -> Yes | U85: Referrals | V85: 49 | W85: AB+ | X85: Married | Y85: Address | Z85: 1043688554 | AA85: 3 | AB85: Master's | AC85: region_7 | AD85: Python Engineer, Data science and ETL
A86: E387 | B86: KENNETH LUTTRELL | C86: 43262 | D86: 44315 | E86: L2 | F86: Cloud | G86: Employees | H86: 03 Exit | J86: Pune | M86: =IF(H86<>"03 Exit",(TODAY()-C86)/365,DATEDIF(C86,D86,"Y")) -> 2 | Q86: Male | R86: Voluntary | S86: Growth Opportunities | T86: =IF(D86="","No","Yes") -> Yes | U86: Referrals | V86: 23 | W86: O- | X86: Unmarried | Y86: Address | Z86: 4756317135 | AA86: 3 | AB86: MBA | AC86: region_13 | AD86: Cloud Computing
A87: E391 | B87: PATRICK HUNTER | C87: 43269 | D87: 44370 | E87: L3 | F87: BI | G87: Employees | H87: 03 Exit | J87: GURUGRAM | M87: =IF(H87<>"03 Exit",(TODAY()-C87)/365,DATEDIF(C87,D87,"Y")) -> 3 | Q87: Male | R87: Voluntary | S87: Growth Opportunities | T87: =IF(D87="","No","Yes") -> Yes | U87: Referrals | V87: 24 | W87: AB+ | X87: Married | Y87: Address | Z87: 2796280142 | AA87: 3 | AB87: MBA | AC87: region_7 | AD87: Python Engineer, Data science and ETL
A88: E393 | B88: MELISSA SCHAEFER | C88: 43269 | E88: L3 | F88: BI | G88: Employees | H88: Active | I88: Confirmed | J88: Pune | K88: 43374 | L88: 2 | M88: =IF(H88<>"03 Exit",(TODAY()-C88)/365,DATEDIF(C88,D88,"Y")) -> 5.290411 | N88: =L88+M88 -> 7.290411 | O88: IT | P88: 34018 | Q88: Male | T88: =IF(D88="","No","Yes") -> No | U88: Referrals | V88: 50 | W88: B- | X88: Unmarried | Y88: Address | Z88: 5559519805 | AA88: 3 | AB88: Bachelor's | AC88: region_2 | AD88: Python Engineer, Data science and ETL
A89: E398 | B89: VEONTRE HAYES | C89: 43276 | D89: 44459 | E89: L3 | F89: BI | G89: Employees | H89: 03 Exit | J89: PUNE | M89: =IF(H89<>"03 Exit",(TODAY()-C89)/365,DATEDIF(C89,D89,"Y")) -> 3 | Q89: Male | R89: Voluntary | S89: Growth Opportunities | T89: =IF(D89="","No","Yes") -> Yes | U89: Referrals | V89: 44 | W89: O- | X89: Married | Y89: Address | Z89: 8641218075 | AA89: 4 | AB89: Master's | AC89: region_2 | AD89: Python Engineer, Data science and ETL
A90: E399 | B90: KEVIN COTTON | C90: 43278 | D90: 44300 | E90: L3 | F90: QA & QC | G90: Employees | H90: 03 Exit | J90: RBS Bangalore | M90: =IF(H90<>"03 Exit",(TODAY()-C90)/365,DATEDIF(C90,D90,"Y")) -> 2 | Q90: Male | R90: Voluntary | S90: Growth Opportunities | T90: =IF(D90="","No","Yes") -> Yes | U90: Referrals | V90: 34 | W90: O- | X90: Unmarried | Y90: Address | Z90: 6618369732 | AA90: 3 | AB90: Master's | AC90: region_7 | AD90: ITGC
A91: E401 | B91: MICHAEL SAUNDERS | C91: 43283 | D91: 44519 | E91: L3 | F91: QA & QC | G91: Employees | H91: 03 Exit | J91: Pune | M91: =IF(H91<>"03 Exit",(TODAY()-C91)/365,DATEDIF(C91,D91,"Y")) -> 3 | Q91: Male | R91: Voluntary | S91: Growth Opportunities | T91: =IF(D91="","No","Yes") -> Yes | U91: Referrals | V91: 27 | W91: AB+ | X91: Married | Y91: Address | Z91: 7381213813 | AA91: 3 | AB91: Master's | AC91: region_15 | AD91: ITGC
A92: E403 | B92: MICHAEL CASEY | C92: 43286 | E92: L5 | F92: Cloud | G92: Employees | H92: Active | I92: Confirmed | J92: Pune | K92: 43388 | L92: 14.6 | M92: =IF(H92<>"03 Exit",(TODAY()-C92)/365,DATEDIF(C92,D92,"Y")) -> 5.2438356 | N92: =L92+M92 -> 19.843836 | O92: Shopper Stop | P92: 27574 | Q92: Male | T92: =IF(D92="","No","Yes") -> No | U92: Referrals | V92: 48 | W92: B- | X92: Unmarried | Y92: Address | Z92: 6128901581 | AA92: 4 | AB92: Master's | AC92: region_15 | AD92: IAM - Multiple Product
A93: E404 | B93: MICHAEL HARMONY | C93: 43290 | E93: L3 | F93: BI | G93: Employees | H93: Active | I93: Confirmed | J93: Pune | K93: 43374 | L93: 5.5 | M93: =IF(H93<>"03 Exit",(TODAY()-C93)/365,DATEDIF(C93,D93,"Y")) -> 5.2328767 | N93: =L93+M93 -> 10.732877 | O93: OTIS | P93: 32166 | Q93: Male | T93: =IF(D93="","No","Yes") -> No | U93: Referrals | V93: 40 | W93: O+ | X93: Married | Y93: Address | Z93: 2273480246 | AA93: 4 | AB93: MBA | AC93: region_2 | AD93: Python Engineer, Data science and ETL
A94: E408 | B94: MICHAEL LITTLE | C94: 43304 | E94: L3 | F94: BI | G94: Employees | H94: Active | I94: Confirmed | J94: Pune | K94: 43374 | L94: 3 | M94: =IF(H94<>"03 Exit",(TODAY()-C94)/365,DATEDIF(C94,D94,"Y")) -> 5.1945205 | N94: =L94+M94 -> 8.1945205 | O94: Shopper Stop | P94: 32941 | Q94: Male | T94: =IF(D94="","No","Yes") -> No | U94: Referrals | V94: 43 | W94: O- | X94: Unmarried | Y94: Address | Z94: 2431809365 | AA94: 3 | AB94: Bachelor's | AC94: region_15 | AD94: Python Engineer, Data science and ETL
A95: E414 | B95: MILES JOHNSTON | C95: 43314 | E95: L4 | F95: BI | G95: Employees | H95: Active | I95: Confirmed | J95: Gurugram | K95: 43405 | L95: 7 | M95: =IF(H95<>"03 Exit",(TODAY()-C95)/365,DATEDIF(C95,D95,"Y")) -> 5.1671233 | N95: =L95+M95 -> 12.167123 | O95: Shopper Stop | P95: 31913 | Q95: Male | T95: =IF(D95="","No","Yes") -> No | U95: Referrals | V95: 43 | W95: AB- | X95: Unmarried | Y95: Address | Z95: 9609122245 | AA95: 3 | AB95: Bachelor's | AC95: region_7 | AD95: TPA
A96: E415 | B96: NADINE OLEARY | C96: 43321 | E96: L2 | F96: BI | G96: Employees | H96: Active | I96: Confirmed | J96: Pune | K96: 43480 | L96: 2.9 | M96: =IF(H96<>"03 Exit",(TODAY()-C96)/365,DATEDIF(C96,D96,"Y")) -> 5.1479452 | N96: =L96+M96 -> 8.0479452 | O96: Reliance | P96: 33588 | Q96: Male | T96: =IF(D96="","No","Yes") -> No | U96: Referrals | V96: 27 | W96: AB+ | X96: Unmarried | Y96: Address | Z96: 2879748956 | AA96: 3 | AB96: Master's | AC96: region_7 | AD96: Python Engineer, Data science and ETL
A97: E418 | B97: NICOLE HILDEBRAND | C97: 43328 | E97: L3 | F97: QA & QC | G97: Employees | H97: Active | I97: Confirmed | J97: Pune | K97: 43419 | L97: 3 | M97: =IF(H97<>"03 Exit",(TODAY()-C97)/365,DATEDIF(C97,D97,"Y")) -> 5.1287671 | N97: =L97+M97 -> 8.1287671 | O97: Shopper Stop | P97: 33544 | Q97: Female | T97: =IF(D97="","No","Yes") -> No | U97: Referrals | V97: 31 | W97: AB+ | X97: Married | Y97: Address | Z97: 9935632287 | AA97: 3 | AB97: Bachelor's | AC97: region_22 | AD97: ITGC
A98: E421 | B98: PATRICIA KNEPLER | C98: 43333 | E98: L4 | F98: BI | G98: Employees | H98: Active | I98: Confirmed | J98: Bengaluru | K98: 43435 | L98: 13 | M98: =IF(H98<>"03 Exit",(TODAY()-C98)/365,DATEDIF(C98,D98,"Y")) -> 5.1150685 | N98: =L98+M98 -> 18.115068 | O98: RBS | P98: 29177 | Q98: Male | T98: =IF(D98="","No","Yes") -> No | U98: Referrals | V98: 28 | W98: O- | X98: Unmarried | Y98: Address | Z98: 3799865625 | AA98: 4 | AB98: Bachelor's | AC98: region_2 | AD98: TPA
A99: E422 | B99: RICHARD THOMAS | C99: 43332 | D99: 44383 | E99: L3 | F99: Cloud | G99: Employees | H99: 03 Exit | J99: PUNE | M99: =IF(H99<>"03 Exit",(TODAY()-C99)/365,DATEDIF(C99,D99,"Y")) -> 2 | Q99: Male | R99: Voluntary | S99: Growth Opportunities | T99: =IF(D99="","No","Yes") -> Yes | U99: Referrals | V99: 28 | W99: B+ | X99: Married | Y99: Address | Z99: 3544540412 | AA99: 3 | AB99: Master's | AC99: region_13 | AD99: SAP S4 HANA PP-QM
A100: E423 | B100: WALLACE HALL | C100: 43334 | D100: 44456 | E100: L2 | F100: BI | G100: Employees | H100: 03 Exit | J100: PUNE | M100: =IF(H100<>"03 Exit",(TODAY()-C100)/365,DATEDIF(C100,D100,"Y")) -> 3 | Q100: Male | R100: Voluntary | S100: Growth Opportunities | T100: =IF(D100="","No","Yes") -> Yes | U100: Referrals | V100: 47 | W100: AB+ | X100: Unmarried | Y100: Address | Z100: 5758532528 | AA100: 3 | AB100: MBA | AC100: region_22 | AD100: Python Engineer, Data science and ETL
...

Sheet Employee Rating
A1: EMP ID | B1: Date | C1: Employee Satisfaction | D1: PerformanceRating | E1: NPS | F1: Annual Increment
A2: E7 | B2: 44280 | C2: 3 | D2: 3 | E2: 7 | F2: =_xlfn.SWITCH(D2,5,20,4,16,3,13,2,10,1,7) -> 13
A3: E12 | B3: 44280 | C3: 4 | D3: 4 | E3: 7 | F3: =_xlfn.SWITCH(D3,5,20,4,16,3,13,2,10,1,7) -> 16
A4: E14 | B4: 44280 | C4: 2 | D4: 3 | E4: 7 | F4: =_xlfn.SWITCH(D4,5,20,4,16,3,13,2,10,1,7) -> 13
A5: E15 | B5: 44280 | C5: 3 | D5: 3 | E5: 4 | F5: =_xlfn.SWITCH(D5,5,20,4,16,3,13,2,10,1,7) -> 13
A6: E24 | B6: 44280 | C6: 2 | D6: 3 | E6: 8 | F6: =_xlfn.SWITCH(D6,5,20,4,16,3,13,2,10,1,7) -> 13
A7: E27 | B7: 44280 | C7: 4 | D7: 3 | E7: 6 | F7: =_xlfn.SWITCH(D7,5,20,4,16,3,13,2,10,1,7) -> 13
A8: E36 | B8: 44280 | C8: 5 | D8: 4 | E8: 8 | F8: =_xlfn.SWITCH(D8,5,20,4,16,3,13,2,10,1,7) -> 16
A9: E38 | B9: 44280 | C9: 3 | D9: 4 | E9: 8 | F9: =_xlfn.SWITCH(D9,5,20,4,16,3,13,2,10,1,7) -> 16
A10: E53 | B10: 44280 | C10: 3 | D10: 4 | E10: 3 | F10: =_xlfn.SWITCH(D10,5,20,4,16,3,13,2,10,1,7) -> 16
A11: E56 | B11: 44280 | C11: 3 | D11: 3 | E11: 9 | F11: =_xlfn.SWITCH(D11,5,20,4,16,3,13,2,10,1,7) -> 13
A12: E62 | B12: 44280 | C12: 2 | D12: 3 | E12: 8 | F12: =_xlfn.SWITCH(D12,5,20,4,16,3,13,2,10,1,7) -> 13
A13: E63 | B13: 44280 | C13: 3 | D13: 3 | E13: 6 | F13: =_xlfn.SWITCH(D13,5,20,4,16,3,13,2,10,1,7) -> 13
... A829: E2001 | B829: 44640 | C829: 4 | D829: 4 | E829: 10 | F829: =_xlfn.SWITCH(D829,5,20,4,16,3,13,2,10,1,7) -> 16

Sheet Requesition Details
A1: S.No | B1: Skills | C1: Date | D1: Department | E1: Project Name | F1: Experience range | G1: Level | H1: Location | I1: No. of Openings
A2: 1 | B2: Senior Technical Consultant | C2: 44801 | D2: Support | E2: DHFL | F2: 3 to 6 yrs | G2: L2 | H2: Pune/Mumbai | I2: 5
A3: 2 | B3: Python | C3: 44806 | D3: BI | E3: Cigna | F3: 1 to 3 yrs | G3: L2 | H3: Pune/Mumbai | I3: 3
A4: 3 | B4: Python | C4: 44806 | D4: BI | E4: DHFL | F4: 1 to 3 yrs | G4: L2 | H4: Pune/Mumbai | I4: 3
A5: 4 | B5: Python | C5: 44806 | D5: BI | E5: Adobe | F5: 1 to 3 yrs | G5: L1 | H5: Pune/Mumbai | I5: 1
A6: 5 | B6: Python | C6: 44819 | D6: BI | E6: Maruti Suzuki | F6: 1 to 4 yrs | G6: L2 | H6: Pune | I6: 8
A7: 6 | B7: Senior Technical Consultant | C7: 44819 | D7: Support | E7: Accounts | F7: 3 to 6 yrs | G7: L2 | H7: Bengaluru | I7: 5
A8: 7 | B8: Test Lead | C8: 44788 | D8: QA & QC | E8: DHFL | F8: 8+yrs | G8: L3/ L4 | H8: Pune | I8: 2
A9: 8 | B9: Senior Technical Consultant | C9: 44812 | D9: Support | E9: Admin | F9: 4 to 6 yrs | G9: L2 | H9: Chennai | I9: 5
A10: 9 | B10: Technical Lead | C10: 44783 | D10: Support | E10: HR | F10: 8 + yrs | G10: L3/ L4 | H10: Pune/Mumbai | I10: 2
A11: 10 | B11: Senior Associate | C11: 44767 | D11: Sales | E11: DHFL | F11: 3-7 yrs | G11: L3 | H11: Chennai | I11: 2
A12: 11 | B12: Senior Associate | C12: 44802 | D12: Sales | E12: Shopper Stop | F12: 3-7 yrs | G12: L3 | H12: Pune | I12: 1
A13: 12 | B13: Technical Lead | C13: 44783 | D13: BI | E13: Shopper Stop | F13: 2 to 5 yrs | G13: L1 | H13: Chennai | I13: 15
... A26: 25 | B26: Technical Lead | C26: 44828 | D26: Support | E26: Shopper Stop | F26: 8 + yrs | G26: L3/ L4 | H26: Chennai | I26: 2

Sheet Training
A1: Emp Id | B1: Level | C1: Date | D1: Training Course Name | E1: Training Status | F1: Dept | G1: Start Date Time | H1: End Date Time | I1: Training Budget | J1: Actual Cost | K1: Training Hours Target | L1: Training Hours
A2: E24 | B2: L5 | C2: 44347 | D2: Management Training | E2: Completed | F2: BI | G2: 44508.498 | H2: =G2+K2/12 -> 44522.665 | I2: 10000 | J2: 8500 | K2: 170 | L2: 96
A3: E36 | B3: L4 | C3: 44355 | D3: Team Management | E3: Not started | F3: Cloud | G3: 44770.658 | H3: =G3+K3/12 -> 44785.658 | I3: 3999 | K3: 180
A4: E38 | B4: L5 | C4: 44442 | D4: Management Training | E4: Not started | F4: BI | G4: 44815.346 | H4: =G4+K4/12 -> 44829.512 | I4: 10000 | K4: 170
A5: E53 | B5: L4 | C5: 44442 | D5: Management Training | E5: Completed | F5: BI | G5: 44508.498 | H5: =G5+K5/12 -> 44522.665 | I5: 10000 | J5: 9000 | K5: 170 | L5: 126
A6: E56 | B6: L4 | C6: 44397 | D6: Management Training | E6: Unfinished | F6: BI | G6: 44675.414 | H6: =G6+K6/12 -> 44689.581 | I6: 10000 | J6: 4000 | K6: 170 | L6: 115
A7: E62 | B7: L4 | C7: 44426 | D7: Management Training | E7: Unfinished | F7: BI | G7: 44675.414 | H7: =G7+K7/12 -> 44689.581 | I7: 10000 | J7: 4000 | K7: 170 | L7: 85
A8: E63 | B8: L5 | C8: 44187 | D8: Management Training | E8: Not started | F8: BI | G8: 44815.346 | H8: =G8+K8/12 -> 44829.512 | I8: 10000 | K8: 170
A9: E64 | B9: L4 | C9: 44177 | D9: Management Training | E9: Completed | F9: BI | G9: 44508.498 | H9: =G9+K9/12 -> 44522.665 | I9: 10000 | J9: 9000 | K9: 170 | L9: 156
A10: E76 | B10: L6 | C10: 44360 | D10: Management Training | E10: Completed | F10: BI | G10: 44508.498 | H10: =G10+K10/12 -> 44522.665 | I10: 10000 | J10: 9000 | K10: 170 | L10: 138
A11: E89 | B11: L4 | C11: 44469 | D11: Management Training | E11: Not started | F11: BI | G11: 44815.346 | H11: =G11+K11/12 -> 44829.512 | I11: 10000 | J11: 7600 | K11: 170
A12: E98 | B12: L4 | C12: 44259 | D12: Management Training | E12: Completed | F12: BI | G12: 44508.498 | H12: =G12+K12/12 -> 44522.665 | I12: 10000 | J12: 9080 | K12: 170 | L12: 137
A13: E99 | B13: L5 | C13: 44366 | D13: Synapse | E13: Not started | F13: BI | G13: 44770.658 | H13: =G13+K13/12 -> 44790.242 | I13: 8000 | K13: 235
A14: E100 | B14: L6 | C14: 44311 | D14: Synapse | E14: Completed | F14: BI | G14: 44563.664 | H14: =G14+K14/12 -> 44583.247 | I14: 8000 | J14: 7000 | K14: 235 | L14: 196
A15: E115 | B15: L4 | C15: 44324 | D15: Customer Services | E15: Completed | F15: Support | G15: 44508.498 | H15: =G15+K15/12 -> 44526.832 | I15: 7900 | J15: 6800 | K15: 220 | L15: 170
A16: E116 | B16: L4 | C16: 44273 | D16: Synapse | E16: Not started | F16: BI | G16: 44770.658 | H16: =G16+K16/12 -> 44790.242 | I16: 8000 | K16: 235
A17: E127 | B17: L5 | C17: 44241 | D17: Synapse | E17: Not started | F17: BI | G17: 44770.658 | H17: =G17+K17/12 -> 44790.242 | I17: 8000 | K17: 235
A18: E131 | B18: L4 | C18: 44408 | D18: Synapse | E18: Not started | F18: BI | G18: 44770.658 | H18: =G18+K18/12 -> 44790.242 | I18: 8000 | K18: 235
A19: E135 | B19: L4 | C19: 44507 | D19: Project Management | E19: Unfinished | F19: QA & QC | G19: 44709.426 | H19: =G19+K19/12 -> 44719.426 | I19: 9000 | J19: 5999 | K19: 120 | L19: 112
A20: E138 | B20: L5 | C20: 44509 | D20: Synapse | E20: Completed | F20: BI | G20: 44563.664 | H20: =G20+K20/12 -> 44583.247 | I20: 8000 | J20: 7600 | K20: 235 | L20: 125
A21: E145 | B21: L3 | C21: 44430 | D21: Python | E21: Unfinished | F21: BI | G21: 44709.426 | H21: =G21+K21/12 -> 44728.593 | I21: 5000 | J21: 300 | K21: 230 | L21: 191
A22: E150 | B22: L3 | C22: 44388 | D22: Testing | E22: Completed | F22: QA & QC | G22: 44563.664 | H22: =G22+K22/12 -> 44583.58 | I22: 13000 | J22: 12000 | K22: 239 | L22: 175
A23: E156 | B23: L1 | C23: 44339 | D23: CRM D365 | E23: Not started | F23: Support | G23: 44824.623 | H23: =G23+K23/12 -> 44843.789 | I23: 7888 | K23: 230
A24: E158 | B24: L4 | C24: 44297 | D24: Synapse | E24: Unfinished | F24: BI | G24: 44658.643 | H24: =G24+K24/12 -> 44678.226 | I24: 8000 | J24: 6000 | K24: 235 | L24: 159
A25: E181 | B25: L3 | C25: 44428 | D25: Python | E25: Completed | F25: BI | G25: 44417.438 | H25: =G25+K25/12 -> 44436.604 | I25: 5000 | J25: 6000 | K25: 230 | L25: 134
A26: E192 | B26: L3 | C26: 44230 | D26: Python | E26: Not started | F26: BI | G26: 44767.487 | H26: =G26+K26/12 -> 44786.653 | I26: 5000 | K26: 230
A27: E198 | B27: L3 | C27: 44283 | D27: Python | E27: Not started | F27: BI | G27: 44767.487 | H27: =G27+K27/12 -> 44786.653 | I27: 5000 | K27: 230
A28: E208 | B28: L3 | C28: 44414 | D28: Python | E28: Not started | F28: BI | G28: 44767.487 | H28: =G28+K28/12 -> 44786.653 | I28: 5000 | K28: 230
A29: E210 | B29: L5 | C29: 44208 | D29: Synapse | E29: Completed | F29: BI | G29: 44563.664 | H29: =G29+K29/12 -> 44583.247 | I29: 8000 | J29: 8000 | K29: 235 | L29: 154
A30: E214 | B30: L4 | C30: 44468 | D30: Synapse | E30: Unfinished | F30: BI | G30: 44658.643 | H30: =G30+K30/12 -> 44678.226 | I30: 8000 | J30: 5000 | K30: 235 | L30: 148
A31: E230 | B31: L4 | C31: 44246 | D31: Synapse | E31: Unfinished | F31: BI | G31: 44658.643 | H31: =G31+K31/12 -> 44678.226 | I31: 8000 | J31: 5000 | K31: 235 | L31: 111
A32: E236 | B32: L5 | C32: 44206 | D32: Synapse | E32: Unfinished | F32: BI | G32: 44658.643 | H32: =G32+K32/12 -> 44678.226 | I32: 8000 | J32: 5000 | K32: 235 | L32: 93
A33: E243 | B33: L5 | C33: 44343 | D33: Synapse | E33: Not started | F33: BI | G33: 44770.658 | H33: =G33+K33/12 -> 44790.242 | I33: 8000 | K33: 235
A34: E247 | B34: L4 | C34: 44517 | D34: SQL | E34: Not started | F34: BI | G34: 44777.688 | H34: =G34+K34/12 -> 44796.021 | I34: 4500 | K34: 220
A35: E251 | B35: L2 | C35: 44456 | D35: Python | E35: Not started | F35: BI | G35: 44767.487 | H35: =G35+K35/12 -> 44786.653 | I35: 5000 | K35: 230
A36: E259 | B36: L3 | C36: 44375 | D36: Python | E36: Unfinished | F36: BI | G36: 44709.426 | H36: =G36+K36/12 -> 44728.593 | I36: 5000 | J36: 500 | K36: 230 | L36: 193
A37: E262 | B37: L2 | C37: 44408 | D37: Cloud Fundamentals | E37: Unfinished | F37: Cloud | G37: 44675.414 | H37: =G37+K37/12 -> 44686.247 | I37: 5999 | J37: 3999 | K37: 130 | L37: 188
A38: E266 | B38: L4 | C38: 44396 | D38: SQL | E38: Completed | F38: BI | G38: 44417.438 | H38: =G38+K38/12 -> 44435.771 | I38: 4500 | J38: 4300 | K38: 220 | L38: 200
A39: E272 | B39: L1 | C39: 44411 | D39: CRM D365 | E39: Unfinished | F39: Support | G39: 44675.414 | H39: =G39+K39/12 -> 44694.581 | I39: 7888 | J39: 6890 | K39: 230 | L39: 196
A40: E278 | B40: L3 | C40: 44406 | D40: Python | E40: Unfinished | F40: BI | G40: 44709.426 | H40: =G40+K40/12 -> 44728.593 | I40: 5000 | J40: 3600 | K40: 230 | L40: 198
A41: E283 | B41: L3 | C41: 44353 | D41: Python | E41: Completed | F41: BI | G41: 44417.438 | H41: =G41+K41/12 -> 44436.604 | I41: 5000 | J41: 4000 | K41: 230 | L41: 125
A42: E298 | B42: L3 | C42: 44254 | D42: Python | E42: Unfinished | F42: BI | G42: 44709.426 | H42: =G42+K42/12 -> 44728.593 | I42: 5000 | J42: 2500 | K42: 230 | L42: 146
A43: E307 | B43: L3 | C43: 44207 | D43: Testing | E43: Completed | F43: QA & QC | G43: 44563.664 | H43: =G43+K43/12 -> 44583.58 | I43: 13000 | J43: 12000 | K43: 239 | L43: 135
A44: E308 | B44: L2 | C44: 44443 | D44: Python | E44: Not started | F44: BI | G44: 44767.487 | H44: =G44+K44/12 -> 44786.653 | I44: 5000 | K44: 230
A45: E315 | B45: L1 | C45: 44432 | D45: CRM D365 | E45: Unfinished | F45: Support | G45: 44675.414 | H45: =G45+K45/12 -> 44694.581 | I45: 7888 | J45: 6890 | K45: 230 | L45: 127
A46: E323 | B46: L3 | C46: 44343 | D46: Python | E46: Completed | F46: BI | G46: 44417.438 | H46: =G46+K46/12 -> 44436.604 | I46: 5000 | J46: 4000 | K46: 230 | L46: 194
A47: E324 | B47: L3 | C47: 44179 | D47: Python | E47: Completed | F47: BI | G47: 44417.438 | H47: =G47+K47/12 -> 44436.604 | I47: 5000 | J47: 4000 | K47: 230 | L47: 112
A48: E329 | B48: L5 | C48: 44509 | D48: SQL | E48: Completed | F48: BI | G48: 44417.438 | H48: =G48+K48/12 -> 44435.771 | I48: 4500 | J48: 4300 | K48: 220 | L48: 133
A49: E333 | B49: L4 | C49: 44286 | D49: SQL | E49: Unfinished | F49: BI | G49: 44658.643 | H49: =G49+K49/12 -> 44676.976 | I49: 4500 | J49: 3000 | K49: 220 | L49: 148
A50: E335 | B50: L2 | C50: 44422 | D50: CRM D365 | E50: Unfinished | F50: Support | G50: 44675.414 | H50: =G50+K50/12 -> 44694.581 | I50: 7888 | J50: 6890 | K50: 230 | L50: 136
A51: E337 | B51: L3 | C51: 44294 | D51: Python | E51: Not started | F51: BI | G51: 44767.487 | H51: =G51+K51/12 -> 44786.653 | I51: 5000 | K51: 230
A52: E350 | B52: L3 | C52: 44266 | D52: Python | E52: Unfinished | F52: BI | G52: 44709.426 | H52: =G52+K52/12 -> 44728.593 | I52: 5000 | J52: 3000 | K52: 230 | L52: 140
A53: E355 | B53: L2 | C53: 44456 | D53: Python | E53: Unfinished | F53: BI | G53: 44709.426 | H53: =G53+K53/12 -> 44728.593 | I53: 5000 | J53: 2000 | K53: 230 | L53: 159
A54: E362 | B54: L6 | C54: 44323 | D54: SQL | E54: Completed | F54: BI | G54: 44417.438 | H54: =G54+K54/12 -> 44435.771 | I54: 4500 | J54: 4000 | K54: 220 | L54: 135
A55: E366 | B55: L2 | C55: 44276 | D55: Testing | E55: Completed | F55: QA & QC | G55: 44563.664 | H55: =G55+K55/12 -> 44583.58 | I55: 13000 | J55: 12000 | K55: 239 | L55: 143
A56: E371 | B56: L5 | C56: 44201 | D56: SQL | E56: Completed | F56: BI | G56: 44417.438 | H56: =G56+K56/12 -> 44435.771 | I56: 4500 | J56: 4000 | K56: 220 | L56: 149
A57: E378 | B57: L3 | C57: 44250 | D57: Python | E57: Unfinished | F57: BI | G57: 44709.426 | H57: =G57+K57/12 -> 44728.593 | I57: 5000 | J57: 2000 | K57: 230 | L57: 186
A58: E381 | B58: L5 | C58: 44190 | D58: Project Management | E58: Not started | F58: QA & QC | G58: 44899.531 | H58: =G58+K58/12 -> 44909.531 | I58: 9000 | K58: 120
A59: E393 | B59: L3 | C59: 44268 | D59: Python | E59: Not started | F59: BI | G59: 44767.487 | H59: =G59+K59/12 -> 44786.653 | I59: 5000 | K59: 230
A60: E403 | B60: L5 | C60: 44286 | D60: Team Management | E60: Completed | F60: Cloud | G60: 44563.664 | H60: =G60+K60/12 -> 44578.664 | I60: 3999 | J60: 3999 | K60: 180 | L60: 171
A61: E404 | B61: L3 | C61: 44390 | D61: Python | E61: Not started | F61: BI | G61: 44767.487 | H61: =G61+K61/12 -> 44786.653 | I61: 5000 | K61: 230
A62: E408 | B62: L3 | C62: 44213 | D62: Python | E62: Unfinished | F62: BI | G62: 44709.426 | H62: =G62+K62/12 -> 44728.593 | I62: 5000 | J62: 2000 | K62: 230 | L62: 160
A63: E414 | B63: L4 | C63: 44170 | D63: SQL | E63: Completed | F63: BI | G63: 44417.438 | H63: =G63+K63/12 -> 44435.771 | I63: 4500 | J63: 4500 | K63: 220 | L63: 169
A64: E415 | B64: L2 | C64: 44398 | D64: Python | E64: Unfinished | F64: BI | G64: 44709.426 | H64: =G64+K64/12 -> 44728.593 | I64: 5000 | J64: 2000 | K64: 230 | L64: 143
A65: E418 | B65: L3 | C65: 44289 | D65: Testing | E65: Unfinished | F65: QA & QC | G65: 44658.643 | H65: =G65+K65/12 -> 44678.56 | I65: 13000 | J65: 10000 | K65: 239 | L65: 174
A66: E421 | B66: L4 | C66: 44408 | D66: SQL | E66: Completed | F66: BI | G66: 44417.438 | H66: =G66+K66/12 -> 44435.771 | I66: 4500 | J66: 4400 | K66: 220 | L66: 155
A67: E426 | B67: L2 | C67: 44516 | D67: Python | E67: Unfinished | F67: BI | G67: 44709.426 | H67: =G67+K67/12 -> 44728.593 | I67: 5000 | J67: 2000 | K67: 230 | L67: 81
A68: E427 | B68: L2 | C68: 44418 | D68: Python | E68: Unfinished | F68: BI | G68: 44709.426 | H68: =G68+K68/12 -> 44728.593 | I68: 5000 | J68: 2000 | K68: 230 | L68: 123
A69: E429 | B69: L2 | C69: 44425 | D69: Python | E69: Not started | F69: BI | G69: 44767.487 | H69: =G69+K69/12 -> 44786.653 | I69: 5000 | K69: 230
A70: E430 | B70: L2 | C70: 44300 | D70: Python | E70: Unfinished | F70: BI | G70: 44709.426 | H70: =G70+K70/12 -> 44728.593 | I70: 5000 | J70: 2000 | K70: 230 | L70: 152
A71: E438 | B71: L2 | C71: 44441 | D71: Python | E71: Completed | F71: BI | G71: 44417.438 | H71: =G71+K71/12 -> 44436.604 | I71: 5000 | J71: 4500 | K71: 230 | L71: 155
A72: E442 | B72: L3 | C72: 44165 | D72: Python | E72: Not started | F72: BI | G72: 44767.487 | H72: =G72+K72/12 -> 44786.653 | I72: 5000 | K72: 230
A73: E448 | B73: L2 | C73: 44434 | D73: Python | E73: Not started | F73: BI | G73: 44767.487 | H73: =G73+K73/12 -> 44786.653 | I73: 5000 | K73: 230
A74: E454 | B74: L3 | C74: 44407 | D74: Python | E74: Unfinished | F74: BI | G74: 44709.426 | H74: =G74+K74/12 -> 44728.593 | I74: 5000 | J74: 2000 | K74: 230 | L74: 165
A75: E456 | B75: L2 | C75: 44232 | D75: Python | E75: Not started | F75: BI | G75: 44767.487 | H75: =G75+K75/12 -> 44786.653 | I75: 5000 | K75: 230
A76: E457 | B76: L3 | C76: 44173 | D76: CRM D365 | E76: Unfinished | F76: Support | G76: 44675.414 | H76: =G76+K76/12 -> 44694.581 | I76: 7888 | J76: 6890 | K76: 230 | L76: 195
A77: E462 | B77: L5 | C77: 44511 | D77: Data Factory | E77: Not started | F77: BI | G77: 44771.427 | H77: =G77+K77/12 -> 44787.26 | I77: 9000 | K77: 190
A78: E465 | B78: L3 | C78: 44365 | D78: Python | E78: Completed | F78: BI | G78: 44417.438 | H78: =G78+K78/12 -> 44436.604 | I78: 5000 | J78: 4000 | K78: 230 | L78: 160
A79: E467 | B79: L3 | C79: 44505 | D79: Python | E79: Not started | F79: BI | G79: 44767.487 | H79: =G79+K79/12 -> 44786.653 | I79: 5000 | K79: 230
A80: E481 | B80: L5 | C80: 44361 | D80: Team Management | E80: Not started | F80: Sales | G80: 44770.658 | H80: =G80+K80/12 -> 44785.658 | I80: 9000 | K80: 180
A81: E493 | B81: L2 | C81: 44423 | D81: Cloud Fundamentals | E81: Completed | F81: Cloud | G81: 44508.498 | H81: =G81+K81/12 -> 44526.832 | I81: 5999 | J81: 5000 | K81: 220 | L81: 80
A82: E495 | B82: L2 | C82: 44199 | D82: Testing | E82: Unfinished | F82: QA & QC | G82: 44658.643 | H82: =G82+K82/12 -> 44678.56 | I82: 13000 | J82: 10000 | K82: 239 | L82: 171
A83: E497 | B83: L3 | C83: 44512 | D83: Testing | E83: Completed | F83: QA & QC | G83: 44563.664 | H83: =G83+K83/12 -> 44583.58 | I83: 13000 | J83: 12000 | K83: 239 | L83: 197
A84: E499 | B84: L4 | C84: 44261 | D84: Team Management | E84: Unfinished | F84: Sales | G84: 44658.643 | H84: =G84+K84/12 -> 44673.643 | I84: 9000 | J84: 8000 | K84: 180 | L84: 136
A85: E500 | B85: L4 | C85: 44253 | D85: Data Factory | E85: Completed | F85: BI | G85: 44508.498 | H85: =G85+K85/12 -> 44524.332 | I85: 9000 | J85: 9000 | K85: 190 | L85: 141
A86: E505 | B86: L2 | C86: 44481 | D86: Sales Management | E86: Completed | F86: Sales | G86: 44417.438 | H86: =G86+K86/12 -> 44432.021 | I86: 8700 | J86: 8200 | K86: 175 | L86: 93
A87: E508 | B87: L2 | C87: 44241 | D87: Python | E87: Unfinished | F87: BI | G87: 44709.426 | H87: =G87+K87/12 -> 44728.593 | I87: 5000 | J87: 2000 | K87: 230 | L87: 180
A88: E509 | B88: L3 | C88: 44410 | D88: Sales Management | E88: Completed | F88: Sales | G88: 44417.438 | H88: =G88+K88/12 -> 44432.021 | I88: 8700 | J88: 8200 | K88: 175 | L88: 140
A89: E510 | B89: L2 | C89: 44184 | D89: Python | E89: Completed | F89: BI | G89: 44417.438 | H89: =G89+K89/12 -> 44436.604 | I89: 5000 | J89: 4500 | K89: 230 | L89: 117
A90: E511 | B90: L2 | C90: 44172 | D90: Python | E90: Not started | F90: BI | G90: 44767.487 | H90: =G90+K90/12 -> 44786.653 | I90: 5000 | K90: 230
A91: E512 | B91: L1 | C91: 44426 | D91: Power BI | E91: Completed | F91: BI | G91: 44265.531 | H91: =G91+K91/12 -> 44283.865 | I91: 10000 | J91: 8000 | K91: 220 | L91: 120
A92: E514 | B92: L3 | C92: 44267 | D92: Python | E92: Unfinished | F92: BI | G92: 44709.426 | H92: =G92+K92/12 -> 44728.593 | I92: 5000 | J92: 2000 | K92: 230 | L92: 91
A93: E515 | B93: L2 | C93: 44380 | D93: Python | E93: Unfinished | F93: BI | G93: 44709.426 | H93: =G93+K93/12 -> 44728.593 | I93: 5000 | J93: 2000 | K93: 230 | L93: 110
A94: E518 | B94: L2 | C94: 44300 | D94: CRM D365 | E94: Not started | F94: Support | G94: 44824.623 | H94: =G94+K94/12 -> 44843.789 | I94: 7888 | K94: 230
A95: E521 | B95: L3 | C95: 44515 | D95: Testing | E95: Not started | F95: QA & QC | G95: 44770.658 | H95: =G95+K95/12 -> 44790.575 | I95: 13000 | K95: 239
A96: E523 | B96: L3 | C96: 44499 | D96: Python | E96: Not started | F96: BI | G96: 44767.487 | H96: =G96+K96/12 -> 44786.653 | I96: 5000 | K96: 230
A97: E525 | B97: L3 | C97: 44243 | D97: Python | E97: Unfinished | F97: BI | G97: 44709.426 | H97: =G97+K97/12 -> 44728.593 | I97: 5000 | J97: 2000 | K97: 230 | L97: 116
A98: E526 | B98: L2 | C98: 44349 | D98: CRM D365 | E98: Unfinished | F98: Support | G98: 44675.414 | H98: =G98+K98/12 -> 44694.581 | I98: 7888 | J98: 6890 | K98: 230 | L98: 109
A99: E527 | B99: L2 | C99: 44221 | D99: Cloud Fundamentals | E99: Not started | F99: Cloud | G99: 44753.522 | H99: =G99+K99/12 -> 44771.856 | I99: 5999 | K99: 220
A100: E529 | B100: L3 | C100: 44338 | D100: Testing | E100: Unfinished | F100: QA & QC | G100: 44658.643 | H100: =G100+K100/12 -> 44678.56 | I100: 13000 | J100: 10000 | K100: 239 | L100: 82
...

Sheet Joining Details
A1: Sr No | B1: Offer No | C1: Status | D1: Total Exp (in ) | E1: Relevant (in ) | F1: Skill | G1: Function | H1: Qualification | I1: D O O | J1: DOJ | K1: Job Location
B2: 700 | C2: YTJ | D2: 1 | E2: 1 | F2: MS CRM | G2: D365 CRM | H2: BE | I2: 44406 | J2: 44621 | K2: Pune
B3: 785 | C3: YTJ | D3: 2.7 | E3: 2.7 | F3: Dotnet | G3: D365 CRM | H3: BE IT | I3: 44477 | J3: 44562 | K3: Pune
B4: 795 | C4: Joined | D4: 4 | E4: 4 | F4: Application Support | G4: AMS | H4: MCA | I4: 44512 | J4: 44562 | K4: Pune
B5: 808 | C5: YTJ | D5: 2.5 | E5: 2.5 | F5: QA Automation | G5: QA & QC | H5: Bsc | I5: 44524 | J5: 44562 | K5: Pune
B6: 811 | C6: YTJ | D6: 7 | E6: 7 | F6: BA | G6: QA & QC | H6: B-Tech | I6: 44525 | J6: 44562 | K6: Bengaluru
B7: 829 | C7: YTJ | D7: 1.2 | E7: 1.2 | F7: Dotnet | G7: D365 CRM | H7: BTech | I7: 44544 | J7: 44562 | K7: Pune
B8: 871 | C8: YTJ | D8: 7 | E8: 5 | F8: Application Support | G8: AMS | H8: BTech | I8: 44558 | J8: 44562 | K8: Gurugram
B9: 873 | C9: YTJ | D9: 1 | E9: 1 | F9: Recuritment | G9: Recruitment | H9: MBA | I9: 44201 | J9: 44562 | K9: Chennai
B10: 874 | C10: YTJ | D10: 5 | E10: 5 | F10: QA Manual | G10: QA & QC | H10: BE | I10: 44566 | J10: 44562 | K10: Pune
B11: 875 | C11: Joined | D11: 3.11 | E11: 3.5 | F11: Application Support | G11: AMS | H11: BE | I11: 44567 | J11: 44562 | K11: Pune
B12: 876 | C12: Joined | D12: 1.3 | E12: 1.3 | F12: Dotnet | G12: D365 CRM | H12: BE | I12: 44567 | J12: 44562 | K12: Pune
B13: 877 | C13: YTJ | D13: 3.8 | E13: 3.8 | F13: Application Support | G13: AMS | H13: BE | I13: 44568 | J13: 44562 | K13: Pune
... B18: 836 | C18: YTJ | D18: 3 | E18: 3 | F18: Dotnet | G18: D365 CRM | H18: BE | I18: 44544 | J18: 44621 | K18: Pune
B19: 838 | C19: YTJ | D19: 1.5 | E19: 1.5 | F19: Dotnet | G19: D365 CRM | I19: 44544 | J19: 44621 | K19: Pune
B20: 851 | C20: YTJ | D20: 6.4 | E20: 6.4 | F20: Dotnet | G20: D365 CRM | H20: MCA | I20: 44550 | J20: 44593 | K20: Pune
B21: 869 | C21: YTJ | D21: 3.7 | E21: 3.2 | F21: Application Support | G21: AMS | H21: BE | I21: 44554 | J21: 44621 | K21: Chennai

Sheet Salary
A1: Emp_Id | B1: Level | C1: Basic Salary | D1: DA | E1: HRA | F1: PF | G1: Gross Salary | H1: EPF | I1: LIC | J1: Total Deduction | K1: Net Salary | L1: CTC | M1: Bonus | N1: Overtime
A2: E7 | B2: L8 | C2: 90000 | D2: =C2*10/100 -> 9000 | E2: =C2*7.5/100 -> 6750 | F2: =C2*15/100 -> 13500 | G2: =SUM(C2:F2) -> 119250 | H2: =F2/2 -> 6750 | I2: =H2/2 -> 3375 | J2: =SUM(H2:I2) -> 10125 | K2: =G2-J2 -> 109125 | L2: =G2*12 -> 1431000 | M2: 30000 | N2: 33521
A3: E12 | B3: L8 | C3: 77000 | D3: =C3*10/100 -> 7700 | E3: =C3*7.5/100 -> 5775 | F3: =C3*15/100 -> 11550 | G3: =SUM(C3:F3) -> 102025 | H3: =F3/2 -> 5775 | I3: =H3/2 -> 2887.5 | J3: =SUM(H3:I3) -> 8662.5 | K3: =G3-J3 -> 93362.5 | L3: =G3*12 -> 1224300 | M3: 30000 | N3: 42421
A4: E14 | B4: L8 | C4: 95000 | D4: =C4*10/100 -> 9500 | E4: =C4*7.5/100 -> 7125 | F4: =C4*15/100 -> 14250 | G4: =SUM(C4:F4) -> 125875 | H4: =F4/2 -> 7125 | I4: =H4/2 -> 3562.5 | J4: =SUM(H4:I4) -> 10687.5 | K4: =G4-J4 -> 115187.5 | L4: =G4*12 -> 1510500 | M4: 30000 | N4: 34507
A5: E15 | B5: L8 | C5: 80000 | D5: =C5*10/100 -> 8000 | E5: =C5*7.5/100 -> 6000 | F5: =C5*15/100 -> 12000 | G5: =SUM(C5:F5) -> 106000 | H5: =F5/2 -> 6000 | I5: =H5/2 -> 3000 | J5: =SUM(H5:I5) -> 9000 | K5: =G5-J5 -> 97000 | L5: =G5*12 -> 1272000 | M5: 30000 | N5: 42828
A6: E24 | B6: L5 | C6: 60000 | D6: =C6*10/100 -> 6000 | E6: =C6*7.5/100 -> 4500 | F6: =C6*15/100 -> 9000 | G6: =SUM(C6:F6) -> 79500 | H6: =F6/2 -> 4500 | I6: =H6/2 -> 2250 | J6: =SUM(H6:I6) -> 6750 | K6: =G6-J6 -> 72750 | L6: =G6*12 -> 954000 | M6: 25000 | N6: 40165
A7: E27 | B7: L8 | C7: 77000 | D7: =C7*10/100 -> 7700 | E7: =C7*7.5/100 -> 5775 | F7: =C7*15/100 -> 11550 | G7: =SUM(C7:F7) -> 102025 | H7: =F7/2 -> 5775 | I7: =H7/2 -> 2887.5 | J7: =SUM(H7:I7) -> 8662.5 | K7: =G7-J7 -> 93362.5 | L7: =G7*12 -> 1224300 | M7: 30000 | N7: 45286
A8: E36 | B8: L4 | C8: 45000 | D8: =C8*10/100 -> 4500 | E8: =C8*7.5/100 -> 3375 | F8: =C8*15/100 -> 6750 | G8: =SUM(C8:F8) -> 59625 | H8: =F8/2 -> 3375 | I8: =H8/2 -> 1687.5 | J8: =SUM(H8:I8) -> 5062.5 | K8: =G8-J8 -> 54562.5 | L8: =G8*12 -> 715500 | M8: 20000 | N8: 46317
A9: E38 | B9: L5 | C9: 60000 | D9: =C9*10/100 -> 6000 | E9: =C9*7.5/100 -> 4500 | F9: =C9*15/100 -> 9000 | G9: =SUM(C9:F9) -> 79500 | H9: =F9/2 -> 4500 | I9: =H9/2 -> 2250 | J9: =SUM(H9:I9) -> 6750 | K9: =G9-J9 -> 72750 | L9: =G9*12 -> 954000 | M9: 25000 | N9: 37504
A10: E53 | B10: L4 | C10: 45000 | D10: =C10*10/100 -> 4500 | E10: =C10*7.5/100 -> 3375 | F10: =C10*15/100 -> 6750 | G10: =SUM(C10:F10) -> 59625 | H10: =F10/2 -> 3375 | I10: =H10/2 -> 1687.5 | J10: =SUM(H10:I10) -> 5062.5 | K10: =G10-J10 -> 54562.5 | L10: =G10*12 -> 715500 | M10: 20000 | N10: 41411
A11: E56 | B11: L4 | C11: 45000 | D11: =C11*10/100 -> 4500 | E11: =C11*7.5/100 -> 3375 | F11: =C11*15/100 -> 6750 | G11: =SUM(C11:F11) -> 59625 | H11: =F11/2 -> 3375 | I11: =H11/2 -> 1687.5 | J11: =SUM(H11:I11) -> 5062.5 | K11: =G11-J11 -> 54562.5 | L11: =G11*12 -> 715500 | M11: 20000 | N11: 47458
A12: E62 | B12: L4 | C12: 45000 | D12: =C12*10/100 -> 4500 | E12: =C12*7.5/100 -> 3375 | F12: =C12*15/100 -> 6750 | G12: =SUM(C12:F12) -> 59625 | H12: =F12/2 -> 3375 | I12: =H12/2 -> 1687.5 | J12: =SUM(H12:I12) -> 5062.5 | K12: =G12-J12 -> 54562.5 | L12: =G12*12 -> 715500 | M12: 20000 | N12: 21900
A13: E63 | B13: L5 | C13: 60000 | D13: =C13*10/100 -> 6000 | E13: =C13*7.5/100 -> 4500 | F13: =C13*15/100 -> 9000 | G13: =SUM(C13:F13) -> 79500 | H13: =F13/2 -> 4500 | I13: =H13/2 -> 2250 | J13: =SUM(H13:I13) -> 6750 | K13: =G13-J13 -> 72750 | L13: =G13*12 -> 954000 | M13: 25000 | N13: 23721
... A45: E278 | B45: L3 | C45: 26000 | D45: =C45*10/100 -> 2600 | E45: =C45*7.5/100 -> 1950 | F45: =C45*15/100 -> 3900 | G45: =SUM(C45:F45) -> 34450 | H45: =F45/2 -> 1950 | I45: =H45/2 -> 975 | J45: =SUM(H45:I45) -> 2925 | K45: =G45-J45 -> 31525 | L45: =G45*12 -> 413400 | M45: 20000 | N45: 20370
A46: E283 | B46: L3 | C46: 26000 | D46: =C46*10/100 -> 2600 | E46: =C46*7.5/100 -> 1950 | F46: =C46*15/100 -> 3900 | G46: =SUM(C46:F46) -> 34450 | H46: =F46/2 -> 1950 | I46: =H46/2 -> 975 | J46: =SUM(H46:I46) -> 2925 | K46: =G46-J46 -> 31525 | L46: =G46*12 -> 413400 | M46: 20000
A47: E298 | B47: L3 | C47: 26000 | D47: =C47*10/100 -> 2600 | E47: =C47*7.5/100 -> 1950 | F47: =C47*15/100 -> 3900 | G47: =SUM(C47:F47) -> 34450 | H47: =F47/2 -> 1950 | I47: =H47/2 -> 975 | J47: =SUM(H47:I47) -> 2925 | K47: =G47-J47 -> 31525 | L47: =G47*12 -> 413400 | M47: 20000
A48: E307 | B48: L3 | C48: 30000 | D48: =C48*10/100 -> 3000 | E48: =C48*7.5/100 -> 2250 | F48: =C48*15/100 -> 4500 | G48: =SUM(C48:F48) -> 39750 | H48: =F48/2 -> 2250 | I48: =H48/2 -> 1125 | J48: =SUM(H48:I48) -> 3375 | K48: =G48-J48 -> 36375 | L48: =G48*12 -> 477000 | M48: 20000
A49: E308 | B49: L2 | C49: 25000 | D49: =C49*10/100 -> 2500 | E49: =C49*7.5/100 -> 1875 | F49: =C49*15/100 -> 3750 | G49: =SUM(C49:F49) -> 33125 | H49: =F49/2 -> 1875 | I49: =H49/2 -> 937.5 | J49: =SUM(H49:I49) -> 2812.5 | K49: =G49-J49 -> 30312.5 | L49: =G49*12 -> 397500 | M49: 15000
A50: E315 | B50: L1 | C50: 20000 | D50: =C50*10/100 -> 2000 | E50: =C50*7.5/100 -> 1500 | F50: =C50*15/100 -> 3000 | G50: =SUM(C50:F50) -> 26500 | H50: =F50/2 -> 1500 | I50: =H50/2 -> 750 | J50: =SUM(H50:I50) -> 2250 | K50: =G50-J50 -> 24250 | L50: =G50*12 -> 318000 | M50: 15000
A51: E323 | B51: L3 | C51: 30000 | D51: =C51*10/100 -> 3000 | E51: =C51*7.5/100 -> 2250 | F51: =C51*15/100 -> 4500 | G51: =SUM(C51:F51) -> 39750 | H51: =F51/2 -> 2250 | I51: =H51/2 -> 1125 | J51: =SUM(H51:I51) -> 3375 | K51: =G51-J51 -> 36375 | L51: =G51*12 -> 477000 | M51: 20000
A52: E324 | B52: L3 | C52: 30000 | D52: =C52*10/100 -> 3000 | E52: =C52*7.5/100 -> 2250 | F52: =C52*15/100 -> 4500 | G52: =SUM(C52:F52) -> 39750 | H52: =F52/2 -> 2250 | I52: =H52/2 -> 1125 | J52: =SUM(H52:I52) -> 3375 | K52: =G52-J52 -> 36375 | L52: =G52*12 -> 477000 | M52: 20000
A53: E329 | B53: L5 | C53: 50000 | D53: =C53*10/100 -> 5000 | E53: =C53*7.5/100 -> 3750 | F53: =C53*15/100 -> 7500 | G53: =SUM(C53:F53) -> 66250 | H53: =F53/2 -> 3750 | I53: =H53/2 -> 1875 | J53: =SUM(H53:I53) -> 5625 | K53: =G53-J53 -> 60625 | L53: =G53*12 -> 795000 | M53: 25000
A54: E333 | B54: L4 | C54: 40000 | D54: =C54*10/100 -> 4000 | E54: =C54*7.5/100 -> 3000 | F54: =C54*15/100 -> 6000 | G54: =SUM(C54:F54) -> 53000 | H54: =F54/2 -> 3000 | I54: =H54/2 -> 1500 | J54: =SUM(H54:I54) -> 4500 | K54: =G54-J54 -> 48500 | L54: =G54*12 -> 636000 | M54: 20000
A55: E335 | B55: L2 | C55: 25000 | D55: =C55*10/100 -> 2500 | E55: =C55*7.5/100 -> 1875 | F55: =C55*15/100 -> 3750 | G55: =SUM(C55:F55) -> 33125 | H55: =F55/2 -> 1875 | I55: =H55/2 -> 937.5 | J55: =SUM(H55:I55) -> 2812.5 | K55: =G55-J55 -> 30312.5 | L55: =G55*12 -> 397500 | M55: 15000
A56: E337 | B56: L3 | C56: 30000 | D56: =C56*10/100 -> 3000 | E56: =C56*7.5/100 -> 2250 | F56: =C56*15/100 -> 4500 | G56: =SUM(C56:F56) -> 39750 | H56: =F56/2 -> 2250 | I56: =H56/2 -> 1125 | J56: =SUM(H56:I56) -> 3375 | K56: =G56-J56 -> 36375 | L56: =G56*12 -> 477000 | M56: 20000
A57: E350 | B57: L3 | C57: 30000 | D57: =C57*10/100 -> 3000 | E57: =C57*7.5/100 -> 2250 | F57: =C57*15/100 -> 4500 | G57: =SUM(C57:F57) -> 39750 | H57: =F57/2 -> 2250 | I57: =H57/2 -> 1125 | J57: =SUM(H57:I57) -> 3375 | K57: =G57-J57 -> 36375 | L57: =G57*12 -> 477000 | M57: 20000
A58: E355 | B58: L2 | C58: 25000 | D58: =C58*10/100 -> 2500 | E58: =C58*7.5/100 -> 1875 | F58: =C58*15/100 -> 3750 | G58: =SUM(C58:F58) -> 33125 | H58: =F58/2 -> 1875 | I58: =H58/2 -> 937.5 | J58: =SUM(H58:I58) -> 2812.5 | K58: =G58-J58 -> 30312.5 | L58: =G58*12 -> 397500 | M58: 15000
A59: E362 | B59: L6 | C59: 60000 | D59: =C59*10/100 -> 6000 | E59: =C59*7.5/100 -> 4500 | F59: =C59*15/100 -> 9000 | G59: =SUM(C59:F59) -> 79500 | H59: =F59/2 -> 4500 | I59: =H59/2 -> 2250 | J59: =SUM(H59:I59) -> 6750 | K59: =G59-J59 -> 72750 | L59: =G59*12 -> 954000 | M59: 25000 | N59: =RANDBETWEEN(30000,50000) -> 47262
A60: E366 | B60: L2 | C60: 25000 | D60: =C60*10/100 -> 2500 | E60: =C60*7.5/100 -> 1875 | F60: =C60*15/100 -> 3750 | G60: =SUM(C60:F60) -> 33125 | H60: =F60/2 -> 1875 | I60: =H60/2 -> 937.5 | J60: =SUM(H60:I60) -> 2812.5 | K60: =G60-J60 -> 30312.5 | L60: =G60*12 -> 397500 | M60: 15000 | N60: 8872
A61: E371 | B61: L5 | C61: 50000 | D61: =C61*10/100 -> 5000 | E61: =C61*7.5/100 -> 3750 | F61: =C61*15/100 -> 7500 | G61: =SUM(C61:F61) -> 66250 | H61: =F61/2 -> 3750 | I61: =H61/2 -> 1875 | J61: =SUM(H61:I61) -> 5625 | K61: =G61-J61 -> 60625 | L61: =G61*12 -> 795000 | M61: 25000 | N61: =RANDBETWEEN(20000,30000) -> 20551
A62: E378 | B62: L3 | C62: 30000 | D62: =C62*10/100 -> 3000 | E62: =C62*7.5/100 -> 2250 | F62: =C62*15/100 -> 4500 | G62: =SUM(C62:F62) -> 39750 | H62: =F62/2 -> 2250 | I62: =H62/2 -> 1125 | J62: =SUM(H62:I62) -> 3375 | K62: =G62-J62 -> 36375 | L62: =G62*12 -> 477000 | M62: 20000 | N62: 12222
A63: E381 | B63: L5 | C63: 50000 | D63: =C63*10/100 -> 5000 | E63: =C63*7.5/100 -> 3750 | F63: =C63*15/100 -> 7500 | G63: =SUM(C63:F63) -> 66250 | H63: =F63/2 -> 3750 | I63: =H63/2 -> 1875 | J63: =SUM(H63:I63) -> 5625 | K63: =G63-J63 -> 60625 | L63: =G63*12 -> 795000 | M63: 25000 | N63: =RANDBETWEEN(20000,30000) -> 20832
A64: E393 | B64: L3 | C64: 30000 | D64: =C64*10/100 -> 3000 | E64: =C64*7.5/100 -> 2250 | F64: =C64*15/100 -> 4500 | G64: =SUM(C64:F64) -> 39750 | H64: =F64/2 -> 2250 | I64: =H64/2 -> 1125 | J64: =SUM(H64:I64) -> 3375 | K64: =G64-J64 -> 36375 | L64: =G64*12 -> 477000 | M64: 20000 | N64: 14666
A65: E403 | B65: L5 | C65: 50000 | D65: =C65*10/100 -> 5000 | E65: =C65*7.5/100 -> 3750 | F65: =C65*15/100 -> 7500 | G65: =SUM(C65:F65) -> 66250 | H65: =F65/2 -> 3750 | I65: =H65/2 -> 1875 | J65: =SUM(H65:I65) -> 5625 | K65: =G65-J65 -> 60625 | L65: =G65*12 -> 795000 | M65: 25000 | N65: =RANDBETWEEN(20000,30000) -> 26554
A66: E404 | B66: L3 | C66: 30000 | D66: =C66*10/100 -> 3000 | E66: =C66*7.5/100 -> 2250 | F66: =C66*15/100 -> 4500 | G66: =SUM(C66:F66) -> 39750 | H66: =F66/2 -> 2250 | I66: =H66/2 -> 1125 | J66: =SUM(H66:I66) -> 3375 | K66: =G66-J66 -> 36375 | L66: =G66*12 -> 477000 | M66: 20000 | N66: 11408
A67: E408 | B67: L3 | C67: 30000 | D67: =C67*10/100 -> 3000 | E67: =C67*7.5/100 -> 2250 | F67: =C67*15/100 -> 4500 | G67: =SUM(C67:F67) -> 39750 | H67: =F67/2 -> 2250 | I67: =H67/2 -> 1125 | J67: =SUM(H67:I67) -> 3375 | K67: =G67-J67 -> 36375 | L67: =G67*12 -> 477000 | M67: 20000 | N67: 18519
A68: E414 | B68: L4 | C68: 40000 | D68: =C68*10/100 -> 4000 | E68: =C68*7.5/100 -> 3000 | F68: =C68*15/100 -> 6000 | G68: =SUM(C68:F68) -> 53000 | H68: =F68/2 -> 3000 | I68: =H68/2 -> 1500 | J68: =SUM(H68:I68) -> 4500 | K68: =G68-J68 -> 48500 | L68: =G68*12 -> 636000 | M68: 20000 | N68: =RANDBETWEEN(20000,30000) -> 24640
A69: E415 | B69: L2 | C69: 25000 | D69: =C69*10/100 -> 2500 | E69: =C69*7.5/100 -> 1875 | F69: =C69*15/100 -> 3750 | G69: =SUM(C69:F69) -> 33125 | H69: =F69/2 -> 1875 | I69: =H69/2 -> 937.5 | J69: =SUM(H69:I69) -> 2812.5 | K69: =G69-J69 -> 30312.5 | L69: =G69*12 -> 397500 | M69: 15000 | N69: 12165
A70: E418 | B70: L3 | C70: 30000 | D70: =C70*10/100 -> 3000 | E70: =C70*7.5/100 -> 2250 | F70: =C70*15/100 -> 4500 | G70: =SUM(C70:F70) -> 39750 | H70: =F70/2 -> 2250 | I70: =H70/2 -> 1125 | J70: =SUM(H70:I70) -> 3375 | K70: =G70-J70 -> 36375 | L70: =G70*12 -> 477000 | M70: 20000 | N70: 12348
A71: E421 | B71: L4 | C71: 40000 | D71: =C71*10/100 -> 4000 | E71: =C71*7.5/100 -> 3000 | F71: =C71*15/100 -> 6000 | G71: =SUM(C71:F71) -> 53000 | H71: =F71/2 -> 3000 | I71: =H71/2 -> 1500 | J71: =SUM(H71:I71) -> 4500 | K71: =G71-J71 -> 48500 | L71: =G71*12 -> 636000 | M71: 20000 | N71: =RANDBETWEEN(20000,30000) -> 26899
A72: E426 | B72: L2 | C72: 25000 | D72: =C72*10/100 -> 2500 | E72: =C72*7.5/100 -> 1875 | F72: =C72*15/100 -> 3750 | G72: =SUM(C72:F72) -> 33125 | H72: =F72/2 -> 1875 | I72: =H72/2 -> 937.5 | J72: =SUM(H72:I72) -> 2812.5 | K72: =G72-J72 -> 30312.5 | L72: =G72*12 -> 397500 | M72: 15000 | N72: 8620
A73: E427 | B73: L2 | C73: 25000 | D73: =C73*10/100 -> 2500 | E73: =C73*7.5/100 -> 1875 | F73: =C73*15/100 -> 3750 | G73: =SUM(C73:F73) -> 33125 | H73: =F73/2 -> 1875 | I73: =H73/2 -> 937.5 | J73: =SUM(H73:I73) -> 2812.5 | K73: =G73-J73 -> 30312.5 | L73: =G73*12 -> 397500 | M73: 15000 | N73: 19983
A74: E429 | B74: L2 | C74: 25000 | D74: =C74*10/100 -> 2500 | E74: =C74*7.5/100 -> 1875 | F74: =C74*15/100 -> 3750 | G74: =SUM(C74:F74) -> 33125 | H74: =F74/2 -> 1875 | I74: =H74/2 -> 937.5 | J74: =SUM(H74:I74) -> 2812.5 | K74: =G74-J74 -> 30312.5 | L74: =G74*12 -> 397500 | M74: 15000 | N74: 12153
A75: E430 | B75: L2 | C75: 25000 | D75: =C75*10/100 -> 2500 | E75: =C75*7.5/100 -> 1875 | F75: =C75*15/100 -> 3750 | G75: =SUM(C75:F75) -> 33125 | H75: =F75/2 -> 1875 | I75: =H75/2 -> 937.5 | J75: =SUM(H75:I75) -> 2812.5 | K75: =G75-J75 -> 30312.5 | L75: =G75*12 -> 397500 | M75: 15000 | N75: 13995
A76: E438 | B76: L2 | C76: 25000 | D76: =C76*10/100 -> 2500 | E76: =C76*7.5/100 -> 1875 | F76: =C76*15/100 -> 3750 | G76: =SUM(C76:F76) -> 33125 | H76: =F76/2 -> 1875 | I76: =H76/2 -> 937.5 | J76: =SUM(H76:I76) -> 2812.5 | K76: =G76-J76 -> 30312.5 | L76: =G76*12 -> 397500 | M76: 15000 | N76: 12282
A77: E442 | B77: L3 | C77: 30000 | D77: =C77*10/100 -> 3000 | E77: =C77*7.5/100 -> 2250 | F77: =C77*15/100 -> 4500 | G77: =SUM(C77:F77) -> 39750 | H77: =F77/2 -> 2250 | I77: =H77/2 -> 1125 | J77: =SUM(H77:I77) -> 3375 | K77: =G77-J77 -> 36375 | L77: =G77*12 -> 477000 | M77: 20000 | N77: 9373
A78: E448 | B78: L2 | C78: 25000 | D78: =C78*10/100 -> 2500 | E78: =C78*7.5/100 -> 1875 | F78: =C78*15/100 -> 3750 | G78: =SUM(C78:F78) -> 33125 | H78: =F78/2 -> 1875 | I78: =H78/2 -> 937.5 | J78: =SUM(H78:I78) -> 2812.5 | K78: =G78-J78 -> 30312.5 | L78: =G78*12 -> 397500 | M78: 15000 | N78: 11172
A79: E454 | B79: L3 | C79: 30000 | D79: =C79*10/100 -> 3000 | E79: =C79*7.5/100 -> 2250 | F79: =C79*15/100 -> 4500 | G79: =SUM(C79:F79) -> 39750 | H79: =F79/2 -> 2250 | I79: =H79/2 -> 1125 | J79: =SUM(H79:I79) -> 3375 | K79: =G79-J79 -> 36375 | L79: =G79*12 -> 477000 | M79: 20000
A80: E456 | B80: L2 | C80: 25000 | D80: =C80*10/100 -> 2500 | E80: =C80*7.5/100 -> 1875 | F80: =C80*15/100 -> 3750 | G80: =SUM(C80:F80) -> 33125 | H80: =F80/2 -> 1875 | I80: =H80/2 -> 937.5 | J80: =SUM(H80:I80) -> 2812.5 | K80: =G80-J80 -> 30312.5 | L80: =G80*12 -> 397500 | M80: 15000
A81: E457 | B81: L3 | C81: 30000 | D81: =C81*10/100 -> 3000 | E81: =C81*7.5/100 -> 2250 | F81: =C81*15/100 -> 4500 | G81: =SUM(C81:F81) -> 39750 | H81: =F81/2 -> 2250 | I81: =H81/2 -> 1125 | J81: =SUM(H81:I81) -> 3375 | K81: =G81-J81 -> 36375 | L81: =G81*12 -> 477000 | M81: 20000
A82: E462 | B82: L5 | C82: 50000 | D82: =C82*10/100 -> 5000 | E82: =C82*7.5/100 -> 3750 | F82: =C82*15/100 -> 7500 | G82: =SUM(C82:F82) -> 66250 | H82: =F82/2 -> 3750 | I82: =H82/2 -> 1875 | J82: =SUM(H82:I82) -> 5625 | K82: =G82-J82 -> 60625 | L82: =G82*12 -> 795000 | M82: 25000
A83: E465 | B83: L3 | C83: 30000 | D83: =C83*10/100 -> 3000 | E83: =C83*7.5/100 -> 2250 | F83: =C83*15/100 -> 4500 | G83: =SUM(C83:F83) -> 39750 | H83: =F83/2 -> 2250 | I83: =H83/2 -> 1125 | J83: =SUM(H83:I83) -> 3375 | K83: =G83-J83 -> 36375 | L83: =G83*12 -> 477000 | M83: 20000
A84: E467 | B84: L3 | C84: 30000 | D84: =C84*10/100 -> 3000 | E84: =C84*7.5/100 -> 2250 | F84: =C84*15/100 -> 4500 | G84: =SUM(C84:F84) -> 39750 | H84: =F84/2 -> 2250 | I84: =H84/2 -> 1125 | J84: =SUM(H84:I84) -> 3375 | K84: =G84-J84 -> 36375 | L84: =G84*12 -> 477000 | M84: 20000
A85: E481 | B85: L5 | C85: 50000 | D85: =C85*10/100 -> 5000 | E85: =C85*7.5/100 -> 3750 | F85: =C85*15/100 -> 7500 | G85: =SUM(C85:F85) -> 66250 | H85: =F85/2 -> 3750 | I85: =H85/2 -> 1875 | J85: =SUM(H85:I85) -> 5625 | K85: =G85-J85 -> 60625 | L85: =G85*12 -> 795000 | M85: 25000
A86: E493 | B86: L2 | C86: 25000 | D86: =C86*10/100 -> 2500 | E86: =C86*7.5/100 -> 1875 | F86: =C86*15/100 -> 3750 | G86: =SUM(C86:F86) -> 33125 | H86: =F86/2 -> 1875 | I86: =H86/2 -> 937.5 | J86: =SUM(H86:I86) -> 2812.5 | K86: =G86-J86 -> 30312.5 | L86: =G86*12 -> 397500 | M86: 15000
A87: E495 | B87: L2 | C87: 25000 | D87: =C87*10/100 -> 2500 | E87: =C87*7.5/100 -> 1875 | F87: =C87*15/100 -> 3750 | G87: =SUM(C87:F87) -> 33125 | H87: =F87/2 -> 1875 | I87: =H87/2 -> 937.5 | J87: =SUM(H87:I87) -> 2812.5 | K87: =G87-J87 -> 30312.5 | L87: =G87*12 -> 397500 | M87: 15000
A88: E497 | B88: L3 | C88: 30000 | D88: =C88*10/100 -> 3000 | E88: =C88*7.5/100 -> 2250 | F88: =C88*15/100 -> 4500 | G88: =SUM(C88:F88) -> 39750 | H88: =F88/2 -> 2250 | I88: =H88/2 -> 1125 | J88: =SUM(H88:I88) -> 3375 | K88: =G88-J88 -> 36375 | L88: =G88*12 -> 477000 | M88: 20000
A89: E499 | B89: L4 | C89: 40000 | D89: =C89*10/100 -> 4000 | E89: =C89*7.5/100 -> 3000 | F89: =C89*15/100 -> 6000 | G89: =SUM(C89:F89) -> 53000 | H89: =F89/2 -> 3000 | I89: =H89/2 -> 1500 | J89: =SUM(H89:I89) -> 4500 | K89: =G89-J89 -> 48500 | L89: =G89*12 -> 636000 | M89: 20000
A90: E500 | B90: L4 | C90: 40000 | D90: =C90*10/100 -> 4000 | E90: =C90*7.5/100 -> 3000 | F90: =C90*15/100 -> 6000 | G90: =SUM(C90:F90) -> 53000 | H90: =F90/2 -> 3000 | I90: =H90/2 -> 1500 | J90: =SUM(H90:I90) -> 4500 | K90: =G90-J90 -> 48500 | L90: =G90*12 -> 636000 | M90: 20000
A91: E505 | B91: L2 | C91: 25000 | D91: =C91*10/100 -> 2500 | E91: =C91*7.5/100 -> 1875 | F91: =C91*15/100 -> 3750 | G91: =SUM(C91:F91) -> 33125 | H91: =F91/2 -> 1875 | I91: =H91/2 -> 937.5 | J91: =SUM(H91:I91) -> 2812.5 | K91: =G91-J91 -> 30312.5 | L91: =G91*12 -> 397500 | M91: 15000 | N91: 17731
A92: E508 | B92: L2 | C92: 25000 | D92: =C92*10/100 -> 2500 | E92: =C92*7.5/100 -> 1875 | F92: =C92*15/100 -> 3750 | G92: =SUM(C92:F92) -> 33125 | H92: =F92/2 -> 1875 | I92: =H92/2 -> 937.5 | J92: =SUM(H92:I92) -> 2812.5 | K92: =G92-J92 -> 30312.5 | L92: =G92*12 -> 397500 | M92: 15000 | N92: 17496
A93: E509 | B93: L3 | C93: 30000 | D93: =C93*10/100 -> 3000 | E93: =C93*7.5/100 -> 2250 | F93: =C93*15/100 -> 4500 | G93: =SUM(C93:F93) -> 39750 | H93: =F93/2 -> 2250 | I93: =H93/2 -> 1125 | J93: =SUM(H93:I93) -> 3375 | K93: =G93-J93 -> 36375 | L93: =G93*12 -> 477000 | M93: 20000 | N93: 10843
A94: E510 | B94: L2 | C94: 25000 | D94: =C94*10/100 -> 2500 | E94: =C94*7.5/100 -> 1875 | F94: =C94*15/100 -> 3750 | G94: =SUM(C94:F94) -> 33125 | H94: =F94/2 -> 1875 | I94: =H94/2 -> 937.5 | J94: =SUM(H94:I94) -> 2812.5 | K94: =G94-J94 -> 30312.5 | L94: =G94*12 -> 397500 | M94: 15000 | N94: 8022
A95: E511 | B95: L2 | C95: 25000 | D95: =C95*10/100 -> 2500 | E95: =C95*7.5/100 -> 1875 | F95: =C95*15/100 -> 3750 | G95: =SUM(C95:F95) -> 33125 | H95: =F95/2 -> 1875 | I95: =H95/2 -> 937.5 | J95: =SUM(H95:I95) -> 2812.5 | K95: =G95-J95 -> 30312.5 | L95: =G95*12 -> 397500 | M95: 15000 | N95: 19758
A96: E512 | B96: L1 | C96: 20000 | D96: =C96*10/100 -> 2000 | E96: =C96*7.5/100 -> 1500 | F96: =C96*15/100 -> 3000 | G96: =SUM(C96:F96) -> 26500 | H96: =F96/2 -> 1500 | I96: =H96/2 -> 750 | J96: =SUM(H96:I96) -> 2250 | K96: =G96-J96 -> 24250 | L96: =G96*12 -> 318000 | M96: 15000 | N96: 14311
A97: E514 | B97: L3 | C97: 30000 | D97: =C97*10/100 -> 3000 | E97: =C97*7.5/100 -> 2250 | F97: =C97*15/100 -> 4500 | G97: =SUM(C97:F97) -> 39750 | H97: =F97/2 -> 2250 | I97: =H97/2 -> 1125 | J97: =SUM(H97:I97) -> 3375 | K97: =G97-J97 -> 36375 | L97: =G97*12 -> 477000 | M97: 20000 | N97: 14906
A98: E515 | B98: L2 | C98: 25000 | D98: =C98*10/100 -> 2500 | E98: =C98*7.5/100 -> 1875 | F98: =C98*15/100 -> 3750 | G98: =SUM(C98:F98) -> 33125 | H98: =F98/2 -> 1875 | I98: =H98/2 -> 937.5 | J98: =SUM(H98:I98) -> 2812.5 | K98: =G98-J98 -> 30312.5 | L98: =G98*12 -> 397500 | M98: 15000 | N98: 9675
A99: E518 | B99: L2 | C99: 25000 | D99: =C99*10/100 -> 2500 | E99: =C99*7.5/100 -> 1875 | F99: =C99*15/100 -> 3750 | G99: =SUM(C99:F99) -> 33125 | H99: =F99/2 -> 1875 | I99: =H99/2 -> 937.5 | J99: =SUM(H99:I99) -> 2812.5 | K99: =G99-J99 -> 30312.5 | L99: =G99*12 -> 397500 | M99: 15000 | N99: 15027
A100: E521 | B100: L3 | C100: 30000 | D100: =C100*10/100 -> 3000 | E100: =C100*7.5/100 -> 2250 | F100: =C100*15/100 -> 4500 | G100: =SUM(C100:F100) -> 39750 | H100: =F100/2 -> 2250 | I100: =H100/2 -> 1125 | J100: =SUM(H100:I100) -> 3375 | K100: =G100-J100 -> 36375 | L100: =G100*12 -> 477000 | M100: 20000 | N100: 19754
A101: E523 | B101: L3 | C101: 30000 | D101: =C101*10/100 -> 3000 | E101: =C101*7.5/100 -> 2250 | F101: =C101*15/100 -> 4500 | G101: =SUM(C101:F101) -> 39750 | H101: =F101/2 -> 2250 | I101: =H101/2 -> 1125 | J101: =SUM(H101:I101) -> 3375 | K101: =G101-J101 -> 36375 | L101: =G101*12 -> 477000 | M101: 20000 | N101: 12952
A102: E525 | B102: L3 | C102: 30000 | D102: =C102*10/100 -> 3000 | E102: =C102*7.5/100 -> 2250 | F102: =C102*15/100 -> 4500 | G102: =SUM(C102:F102) -> 39750 | H102: =F102/2 -> 2250 | I102: =H102/2 -> 1125 | J102: =SUM(H102:I102) -> 3375 | K102: =G102-J102 -> 36375 | L102: =G102*12 -> 477000 | M102: 20000 | N102: 12028
... A105: E529 | B105: L3 | C105: 30000 | D105: =C105*10/100 -> 3000 | E105: =C105*7.5/100 -> 2250 | F105: =C105*15/100 -> 4500 | G105: =SUM(C105:F105) -> 39750 | H105: =F105/2 -> 2250 | I105: =H105/2 -> 1125 | J105: =SUM(H105:I105) -> 3375 | K105: =G105-J105 -> 36375 | L105: =G105*12 -> 477000 | M105: 20000 | N105: 13557
A106: E531 | B106: L3 | C106: 30000 | D106: =C106*10/100 -> 3000 | E106: =C106*7.5/100 -> 2250 | F106: =C106*15/100 -> 4500 | G106: =SUM(C106:F106) -> 39750 | H106: =F106/2 -> 2250 | I106: =H106/2 -> 1125 | J106: =SUM(H106:I106) -> 3375 | K106: =G106-J106 -> 36375 | L106: =G106*12 -> 477000 | M106: 20000
A107: E535 | B107: L2 | C107: 25000 | D107: =C107*10/100 -> 2500 | E107: =C107*7.5/100 -> 1875 | F107: =C107*15/100 -> 3750 | G107: =SUM(C107:F107) -> 33125 | H107: =F107/2 -> 1875 | I107: =H107/2 -> 937.5 | J107: =SUM(H107:I107) -> 2812.5 | K107: =G107-J107 -> 30312.5 | L107: =G107*12 -> 397500 | M107: 15000
A108: E538 | B108: L2 | C108: 25000 | D108: =C108*10/100 -> 2500 | E108: =C108*7.5/100 -> 1875 | F108: =C108*15/100 -> 3750 | G108: =SUM(C108:F108) -> 33125 | H108: =F108/2 -> 1875 | I108: =H108/2 -> 937.5 | J108: =SUM(H108:I108) -> 2812.5 | K108: =G108-J108 -> 30312.5 | L108: =G108*12 -> 397500 | M108: 15000
A109: E539 | B109: L2 | C109: 25000 | D109: =C109*10/100 -> 2500 | E109: =C109*7.5/100 -> 1875 | F109: =C109*15/100 -> 3750 | G109: =SUM(C109:F109) -> 33125 | H109: =F109/2 -> 1875 | I109: =H109/2 -> 937.5 | J109: =SUM(H109:I109) -> 2812.5 | K109: =G109-J109 -> 30312.5 | L109: =G109*12 -> 397500 | M109: 15000
A110: E541 | B110: L3 | C110: 30000 | D110: =C110*10/100 -> 3000 | E110: =C110*7.5/100 -> 2250 | F110: =C110*15/100 -> 4500 | G110: =SUM(C110:F110) -> 39750 | H110: =F110/2 -> 2250 | I110: =H110/2 -> 1125 | J110: =SUM(H110:I110) -> 3375 | K110: =G110-J110 -> 36375 | L110: =G110*12 -> 477000 | M110: 20000
A111: E544 | B111: L1 | C111: 20000 | D111: =C111*10/100 -> 2000 | E111: =C111*7.5/100 -> 1500 | F111: =C111*15/100 -> 3000 | G111: =SUM(C111:F111) -> 26500 | H111: =F111/2 -> 1500 | I111: =H111/2 -> 750 | J111: =SUM(H111:I111) -> 2250 | K111: =G111-J111 -> 24250 | L111: =G111*12 -> 318000 | M111: 15000
A112: E549 | B112: L1 | C112: 20000 | D112: =C112*10/100 -> 2000 | E112: =C112*7.5/100 -> 1500 | F112: =C112*15/100 -> 3000 | G112: =SUM(C112:F112) -> 26500 | H112: =F112/2 -> 1500 | I112: =H112/2 -> 750 | J112: =SUM(H112:I112) -> 2250 | K112: =G112-J112 -> 24250 | L112: =G112*12 -> 318000 | M112: 15000
A113: E550 | B113: L1 | C113: 20000 | D113: =C113*10/100 -> 2000 | E113: =C113*7.5/100 -> 1500 | F113: =C113*15/100 -> 3000 | G113: =SUM(C113:F113) -> 26500 | H113: =F113/2 -> 1500 | I113: =H113/2 -> 750 | J113: =SUM(H113:I113) -> 2250 | K113: =G113-J113 -> 24250 | L113: =G113*12 -> 318000 | M113: 15000
A114: E552 | B114: L1 | C114: 20000 | D114: =C114*10/100 -> 2000 | E114: =C114*7.5/100 -> 1500 | F114: =C114*15/100 -> 3000 | G114: =SUM(C114:F114) -> 26500 | H114: =F114/2 -> 1500 | I114: =H114/2 -> 750 | J114: =SUM(H114:I114) -> 2250 | K114: =G114-J114 -> 24250 | L114: =G114*12 -> 318000 | M114: 15000
A115: E553 | B115: L1 | C115: 20000 | D115: =C115*10/100 -> 2000 | E115: =C115*7.5/100 -> 1500 | F115: =C115*15/100 -> 3000 | G115: =SUM(C115:F115) -> 26500 | H115: =F115/2 -> 1500 | I115: =H115/2 -> 750 | J115: =SUM(H115:I115) -> 2250 | K115: =G115-J115 -> 24250 | L115: =G115*12 -> 318000 | M115: 15000
A116: E554 | B116: L1 | C116: 20000 | D116: =C116*10/100 -> 2000 | E116: =C116*7.5/100 -> 1500 | F116: =C116*15/100 -> 3000 | G116: =SUM(C116:F116) -> 26500 | H116: =F116/2 -> 1500 | I116: =H116/2 -> 750 | J116: =SUM(H116:I116) -> 2250 | K116: =G116-J116 -> 24250 | L116: =G116*12 -> 318000 | M116: 15000
A117: E555 | B117: L1 | C117: 20000 | D117: =C117*10/100 -> 2000 | E117: =C117*7.5/100 -> 1500 | F117: =C117*15/100 -> 3000 | G117: =SUM(C117:F117) -> 26500 | H117: =F117/2 -> 1500 | I117: =H117/2 -> 750 | J117: =SUM(H117:I117) -> 2250 | K117: =G117-J117 -> 24250 | L117: =G117*12 -> 318000 | M117: 15000
A118: E556 | B118: L1 | C118: 20000 | D118: =C118*10/100 -> 2000 | E118: =C118*7.5/100 -> 1500 | F118: =C118*15/100 -> 3000 | G118: =SUM(C118:F118) -> 26500 | H118: =F118/2 -> 1500 | I118: =H118/2 -> 750 | J118: =SUM(H118:I118) -> 2250 | K118: =G118-J118 -> 24250 | L118: =G118*12 -> 318000 | M118: 15000 | N118: 15157
A119: E557 | B119: L1 | C119: 20000 | D119: =C119*10/100 -> 2000 | E119: =C119*7.5/100 -> 1500 | F119: =C119*15/100 -> 3000 | G119: =SUM(C119:F119) -> 26500 | H119: =F119/2 -> 1500 | I119: =H119/2 -> 750 | J119: =SUM(H119:I119) -> 2250 | K119: =G119-J119 -> 24250 | L119: =G119*12 -> 318000 | M119: 15000 | N119: 13606
A120: E558 | B120: L2 | C120: 25000 | D120: =C120*10/100 -> 2500 | E120: =C120*7.5/100 -> 1875 | F120: =C120*15/100 -> 3750 | G120: =SUM(C120:F120) -> 33125 | H120: =F120/2 -> 1875 | I120: =H120/2 -> 937.5 | J120: =SUM(H120:I120) -> 2812.5 | K120: =G120-J120 -> 30312.5 | L120: =G120*12 -> 397500 | M120: 15000 | N120: 18771
A121: E559 | B121: L3 | C121: 30000 | D121: =C121*10/100 -> 3000 | E121: =C121*7.5/100 -> 2250 | F121: =C121*15/100 -> 4500 | G121: =SUM(C121:F121) -> 39750 | H121: =F121/2 -> 2250 | I121: =H121/2 -> 1125 | J121: =SUM(H121:I121) -> 3375 | K121: =G121-J121 -> 36375 | L121: =G121*12 -> 477000 | M121: 20000 | N121: 8918
A122: E560 | B122: L4 | C122: 40000 | D122: =C122*10/100 -> 4000 | E122: =C122*7.5/100 -> 3000 | F122: =C122*15/100 -> 6000 | G122: =SUM(C122:F122) -> 53000 | H122: =F122/2 -> 3000 | I122: =H122/2 -> 1500 | J122: =SUM(H122:I122) -> 4500 | K122: =G122-J122 -> 48500 | L122: =G122*12 -> 636000 | M122: 20000 | N122: =RANDBETWEEN(20000,30000) -> 21335
A123: E564 | B123: L2 | C123: 25000 | D123: =C123*10/100 -> 2500 | E123: =C123*7.5/100 -> 1875 | F123: =C123*15/100 -> 3750 | G123: =SUM(C123:F123) -> 33125 | H123: =F123/2 -> 1875 | I123: =H123/2 -> 937.5 | J123: =SUM(H123:I123) -> 2812.5 | K123: =G123-J123 -> 30312.5 | L123: =G123*12 -> 397500 | M123: 15000 | N123: 17146
A124: E565 | B124: L2 | C124: 25000 | D124: =C124*10/100 -> 2500 | E124: =C124*7.5/100 -> 1875 | F124: =C124*15/100 -> 3750 | G124: =SUM(C124:F124) -> 33125 | H124: =F124/2 -> 1875 | I124: =H124/2 -> 937.5 | J124: =SUM(H124:I124) -> 2812.5 | K124: =G124-J124 -> 30312.5 | L124: =G124*12 -> 397500 | M124: 15000 | N124: 11421
A125: E566 | B125: L2 | C125: 25000 | D125: =C125*10/100 -> 2500 | E125: =C125*7.5/100 -> 1875 | F125: =C125*15/100 -> 3750 | G125: =SUM(C125:F125) -> 33125 | H125: =F125/2 -> 1875 | I125: =H125/2 -> 937.5 | J125: =SUM(H125:I125) -> 2812.5 | K125: =G125-J125 -> 30312.5 | L125: =G125*12 -> 397500 | M125: 15000 | N125: 16220
A126: E568 | B126: L4 | C126: 40000 | D126: =C126*10/100 -> 4000 | E126: =C126*7.5/100 -> 3000 | F126: =C126*15/100 -> 6000 | G126: =SUM(C126:F126) -> 53000 | H126: =F126/2 -> 3000 | I126: =H126/2 -> 1500 | J126: =SUM(H126:I126) -> 4500 | K126: =G126-J126 -> 48500 | L126: =G126*12 -> 636000 | M126: 20000 | N126: =RANDBETWEEN(20000,30000) -> 20302
A127: E572 | B127: L2 | C127: 25000 | D127: =C127*10/100 -> 2500 | E127: =C127*7.5/100 -> 1875 | F127: =C127*15/100 -> 3750 | G127: =SUM(C127:F127) -> 33125 | H127: =F127/2 -> 1875 | I127: =H127/2 -> 937.5 | J127: =SUM(H127:I127) -> 2812.5 | K127: =G127-J127 -> 30312.5 | L127: =G127*12 -> 397500 | M127: 15000 | N127: 17939
A128: E579 | B128: L2 | C128: 25000 | D128: =C128*10/100 -> 2500 | E128: =C128*7.5/100 -> 1875 | F128: =C128*15/100 -> 3750 | G128: =SUM(C128:F128) -> 33125 | H128: =F128/2 -> 1875 | I128: =H128/2 -> 937.5 | J128: =SUM(H128:I128) -> 2812.5 | K128: =G128-J128 -> 30312.5 | L128: =G128*12 -> 397500 | M128: 15000 | N128: 9771
A129: E582 | B129: L2 | C129: 25000 | D129: =C129*10/100 -> 2500 | E129: =C129*7.5/100 -> 1875 | F129: =C129*15/100 -> 3750 | G129: =SUM(C129:F129) -> 33125 | H129: =F129/2 -> 1875 | I129: =H129/2 -> 937.5 | J129: =SUM(H129:I129) -> 2812.5 | K129: =G129-J129 -> 30312.5 | L129: =G129*12 -> 397500 | M129: 15000 | N129: 17548
A130: E583 | B130: L3 | C130: 30000 | D130: =C130*10/100 -> 3000 | E130: =C130*7.5/100 -> 2250 | F130: =C130*15/100 -> 4500 | G130: =SUM(C130:F130) -> 39750 | H130: =F130/2 -> 2250 | I130: =H130/2 -> 1125 | J130: =SUM(H130:I130) -> 3375 | K130: =G130-J130 -> 36375 | L130: =G130*12 -> 477000 | M130: 20000 | N130: 11308
A131: E588 | B131: L2 | C131: 25000 | D131: =C131*10/100 -> 2500 | E131: =C131*7.5/100 -> 1875 | F131: =C131*15/100 -> 3750 | G131: =SUM(C131:F131) -> 33125 | H131: =F131/2 -> 1875 | I131: =H131/2 -> 937.5 | J131: =SUM(H131:I131) -> 2812.5 | K131: =G131-J131 -> 30312.5 | L131: =G131*12 -> 397500 | M131: 15000 | N131: 11270
A132: E589 | B132: L3 | C132: 30000 | D132: =C132*10/100 -> 3000 | E132: =C132*7.5/100 -> 2250 | F132: =C132*15/100 -> 4500 | G132: =SUM(C132:F132) -> 39750 | H132: =F132/2 -> 2250 | I132: =H132/2 -> 1125 | J132: =SUM(H132:I132) -> 3375 | K132: =G132-J132 -> 36375 | L132: =G132*12 -> 477000 | M132: 20000 | N132: 17062
A133: E591 | B133: L2 | C133: 25000 | D133: =C133*10/100 -> 2500 | E133: =C133*7.5/100 -> 1875 | F133: =C133*15/100 -> 3750 | G133: =SUM(C133:F133) -> 33125 | H133: =F133/2 -> 1875 | I133: =H133/2 -> 937.5 | J133: =SUM(H133:I133) -> 2812.5 | K133: =G133-J133 -> 30312.5 | L133: =G133*12 -> 397500 | M133: 15000
...

Sheet Offer Acceptance
A1: application_id | B1: candidate_name | C1: offer_date | D1: Department | E1: Source | F1: offer_status | G1: Joined Status
A2: 1 | B2: Eadie | C2: 44274 | D2: BI | E2: Referrals | F2: Offer Rejected
A3: 2 | B3: Mel | C3: 44247 | D3: BI | E3: Social media | F3: On Hold
A4: 3 | B4: Tilda | C4: 44583 | D4: BI | E4: Career Fairs | F4: Offer Accepted | G4: Joined
A5: 4 | B5: Elyn | C5: 44445 | D5: BI | E5: Career Fairs | F5: Not Offered
A6: 5 | B6: Wildon | C6: 44284 | D6: BI | E6: Referrals | F6: Counteroffer
A7: 6 | B7: Hakim | C7: 44447 | D7: BI | E7: Referrals | F7: Counteroffer
A8: 7 | B8: Evered | C8: 44586 | D8: BI | E8: Referrals | F8: On Hold
A9: 8 | B9: Walden | C9: 43847 | D9: BI | E9: Referrals | F9: Offer Rejected
A10: 9 | B10: Thaddeus | C10: 44248 | D10: BI | E10: Referrals | F10: Not Offered
A11: 10 | B11: Cynthea | C11: 44240 | D11: BI | E11: Referrals | F11: On Hold
A12: 11 | B12: Seymour | C12: 44564 | D12: BI | E12: Referrals | F12: Offer Accepted | G12: Joined
A13: 12 | B13: Savina | C13: 43837 | D13: BI | E13: Referrals | F13: Offer Accepted | G13: Joined
A14: 13 | B14: Abran | C14: 43919 | D14: BI | E14: Referrals | F14: Counteroffer
A15: 14 | B15: Paige | C15: 44233 | D15: BI | E15: Social media | F15: Offer Accepted | G15: Joined
A16: 15 | B16: Gusta | C16: 44591 | D16: BI | E16: Social media | F16: On Hold
A17: 16 | B17: Helen | C17: 44376 | D17: BI | E17: Social media | F17: Counteroffer
A18: 17 | B18: Marti | C18: 44412 | D18: BI | E18: Social media | F18: Offer Accepted | G18: Joined
A19: 18 | B19: Rip | C19: 43898 | D19: BI | E19: Social media | F19: Offer Accepted | G19: Not Joined
A20: 19 | B20: Allyson | C20: 44612 | D20: BI | E20: Social media | F20: Offer Accepted | G20: Not Joined
A21: 20 | B21: Ado | C21: 43843 | D21: BI | E21: Social media | F21: Not Offered
A22: 21 | B22: Sibylle | C22: 44462 | D22: BI | E22: Social media | F22: On Hold
A23: 22 | B23: Timothea | C23: 44579 | D23: BI | E23: Social media | F23: Offer Accepted | G23: Not Joined
A24: 23 | B24: Wilden | C24: 43899 | D24: BI | E24: Social media | F24: Counteroffer
A25: 24 | B25: Carter | C25: 44440 | D25: BI | E25: Social media | F25: Offer Accepted | G25: Not Joined
A26: 25 | B26: Shanan | C26: 44575 | D26: BI | E26: Social media | F26: Offer Rejected
A27: 26 | B27: Alanah | C27: 44563 | D27: BI | E27: Social media | F27: Counteroffer
A28: 27 | B28: Faye | C28: 43917 | D28: BI | E28: Social media | F28: Offer Rejected
A29: 28 | B29: Sansone | C29: 44476 | D29: BI | E29: Career Fairs | F29: On Hold
A30: 29 | B30: Enrica | C30: 44623 | D30: Sales | E30: Career Fairs | F30: On Hold
A31: 30 | B31: Hank | C31: 44246 | D31: Sales | E31: Career Fairs | F31: Offer Accepted | G31: Not Joined
A32: 31 | B32: Timotheus | C32: 44602 | D32: Sales | E32: Career Fairs | F32: Counteroffer
A33: 32 | B33: Shae | C33: 44642 | D33: Sales | E33: Career Fairs | F33: On Hold
A34: 33 | B34: Tabina | C34: 44517 | D34: Sales | E34: Career Fairs | F34: Counteroffer
A35: 34 | B35: Ambrose | C35: 44646 | D35: Sales | E35: Career Fairs | F35: On Hold
A36: 35 | B36: Jermaine | C36: 44326 | D36: Sales | E36: Career Fairs | F36: Offer Rejected
A37: 36 | B37: Adriaens | C37: 43831 | D37: Sales | E37: Career Fairs | F37: Offer Accepted | G37: Not Joined
A38: 37 | B38: Sal | C38: 44498 | D38: Sales | E38: Career Fairs | F38: Counteroffer
A39: 38 | B39: Ree | C39: 44636 | D39: Sales | E39: Career Fairs | F39: Not Offered
A40: 39 | B40: Jolynn | C40: 44361 | D40: Sales | E40: Career Fairs | F40: Offer Accepted | G40: Not Joined
A41: 40 | B41: Christyna | C41: 44078 | D41: Sales | E41: Career Fairs | F41: Offer Rejected
A42: 41 | B42: Sandro | C42: 44474 | D42: Sales | E42: Career Fairs | F42: Not Offered
A43: 42 | B43: Debor | C43: 44502 | D43: Sales | E43: Career Fairs | F43: On Hold
A44: 43 | B44: Winnie | C44: 43911 | D44: Sales | E44: Career Fairs | F44: Not Offered
A45: 44 | B45: Joyous | C45: 44332 | D45: Sales | E45: Career Fairs | F45: Not Offered
A46: 45 | B46: Eleen | C46: 44612 | D46: Sales | E46: Career Fairs | F46: Offer Accepted | G46: Joined
A47: 46 | B47: Hortensia | C47: 44366 | D47: Sales | E47: Career Fairs | F47: Offer Accepted | G47: Joined
A48: 47 | B48: Nicol | C48: 44572 | D48: Sales | E48: Career Fairs | F48: Counteroffer
A49: 48 | B49: Maryjane | C49: 43898 | D49: Sales | E49: Career Fairs | F49: Offer Rejected
A50: 49 | B50: Birgit | C50: 43857 | D50: Sales | E50: Career Fairs | F50: Not Offered
A51: 50 | B51: Henri | C51: 44244 | D51: Sales | E51: Career Fairs | F51: Offer Accepted | G51: Joined
A52: 51 | B52: Isadore | C52: 44359 | D52: Sales | E52: Career Fairs | F52: Not Offered
A53: 52 | B53: Alvira | C53: 44598 | D53: Sales | E53: Career Fairs | F53: Not Offered
A54: 53 | B54: Faunie | C54: 44571 | D54: Sales | E54: Career Fairs | F54: Offer Rejected
A55: 54 | B55: Raeann | C55: 44516 | D55: Sales | E55: Career Fairs | F55: Offer Accepted | G55: Joined
A56: 55 | B56: Chance | C56: 43846 | D56: Sales | E56: Career Fairs | F56: Offer Accepted | G56: Joined
A57: 56 | B57: Berkie | C57: 44328 | D57: Sales | E57: Career Fairs | F57: Counteroffer
A58: 57 | B58: Dougie | C58: 44638 | D58: Sales | E58: Career Fairs | F58: Offer Rejected
A59: 58 | B59: Hildegarde | C59: 44582 | D59: Sales | E59: Career Fairs | F59: On Hold
A60: 59 | B60: Andi | C60: 44620 | D60: Sales | E60: Referrals | F60: Not Offered
A61: 60 | B61: Aila | C61: 44091 | D61: Sales | E61: Referrals | F61: On Hold
A62: 61 | B62: Gay | C62: 44598 | D62: Sales | E62: Referrals | F62: Offer Rejected
A63: 62 | B63: Mata | C63: 44473 | D63: Sales | E63: Referrals | F63: Counteroffer
A64: 63 | B64: Grant | C64: 43905 | D64: Sales | E64: Referrals | F64: Offer Rejected
A65: 64 | B65: Hamnet | C65: 44648 | D65: Sales | E65: Referrals | F65: On Hold
A66: 65 | B66: Candra | C66: 44648 | D66: Sales | E66: Referrals | F66: Offer Rejected
A67: 66 | B67: Pauli | C67: 44642 | D67: Sales | E67: Referrals | F67: Not Offered
A68: 67 | B68: Hewet | C68: 44338 | D68: Sales | E68: Referrals | F68: Counteroffer
... A82: 81 | B82: Andrea | C82: 44613 | D82: QA & QC | E82: Social media | F82: On Hold
A83: 82 | B83: Itch | C83: 44483 | D83: QA & QC | E83: job boards | F83: Offer Accepted | G83: Joined
A84: 83 | B84: Mona | C84: 44593 | D84: QA & QC | E84: Social media | F84: Offer Rejected
A85: 84 | B85: Roosevelt | C85: 44245 | D85: QA & QC | E85: job boards | F85: Offer Accepted | G85: Joined
A86: 85 | B86: Ivor | C86: 44240 | D86: QA & QC | E86: Social media | F86: On Hold
A87: 86 | B87: Ulrich | C87: 44491 | D87: QA & QC | E87: Social media | F87: Not Offered
A88: 87 | B88: Crichton | C88: 44582 | D88: QA & QC | E88: Social media | F88: Counteroffer
A89: 88 | B89: Elton | C89: 44100 | D89: QA & QC | E89: Social media | F89: On Hold
A90: 89 | B90: Truman | C90: 44597 | D90: QA & QC | E90: job boards | F90: Offer Accepted | G90: Joined
A91: 90 | B91: Fara | C91: 44590 | D91: QA & QC | E91: job boards | F91: Offer Accepted | G91: Joined
A92: 91 | B92: Cesya | C92: 44592 | D92: QA & QC | E92: Career Fairs | F92: Offer Accepted | G92: Joined
A93: 92 | B93: Jorgan | C93: 44494 | D93: QA & QC | E93: Career Fairs | F93: Not Offered
A94: 93 | B94: Dean | C94: 43896 | D94: QA & QC | E94: Career Fairs | F94: On Hold
A95: 94 | B95: Barnett | C95: 44246 | D95: QA & QC | E95: Career Fairs | F95: On Hold
A96: 95 | B96: Sonny | C96: 44613 | D96: QA & QC | E96: Career Fairs | F96: Offer Rejected
A97: 96 | B97: Juditha | C97: 44623 | D97: QA & QC | E97: Career Fairs | F97: Not Offered
A98: 97 | B98: Rayna | C98: 44076 | D98: QA & QC | E98: Career Fairs | F98: Not Offered
A99: 98 | B99: Anna-maria | C99: 44096 | D99: QA & QC | E99: Career Fairs | F99: Counteroffer
A100: 99 | B100: Wylma | C100: 43906 | D100: QA & QC | E100: Career Fairs | F100: Offer Accepted | G100: Joined
A101: 100 | B101: Gawen | C101: 44104 | D101: QA & QC | E101: Career Fairs | F101: Offer Rejected
A102: 101 | B102: Field | C102: 44644 | D102: QA & QC | E102: Career Fairs | F102: Counteroffer
A103: 102 | B103: Lucinda | C103: 44349 | D103: QA & QC | E103: Career Fairs | F103: Offer Accepted | G103: Joined
A104: 103 | B104: Barrie | C104: 44095 | D104: QA & QC | E104: Career Fairs | F104: Offer Rejected
A105: 104 | B105: Dav | C105: 43858 | D105: QA & QC | E105: Career Fairs | F105: Not Offered
A106: 105 | B106: Kakalina | C106: 44377 | D106: QA & QC | E106: Career Fairs | F106: Offer Rejected
A107: 106 | B107: Clevie | C107: 44625 | D107: QA & QC | E107: Career Fairs | F107: Not Offered
A108: 107 | B108: Marylin | C108: 44481 | D108: QA & QC | E108: Career Fairs | F108: Offer Rejected
A109: 108 | B109: Garnet | C109: 44346 | D109: QA & QC | E109: Career Fairs | F109: Not Offered
A110: 109 | B110: Leeann | C110: 43906 | D110: QA & QC | E110: Career Fairs | F110: Counteroffer
A111: 110 | B111: Amity | C111: 43861 | D111: QA & QC | E111: Career Fairs | F111: Counteroffer
A112: 111 | B112: Ricoriki | C112: 44617 | D112: QA & QC | E112: Career Fairs | F112: Offer Rejected
A113: 112 | B113: Claudian | C113: 44341 | D113: QA & QC | E113: Career Fairs | F113: Not Offered
...

Sheet Leave  Prediction
A1: Joining_Date | B1: Start_Date | C1: End_Date | D1: EMP_ID | E1: Reason_for_Leave | F1: Type_of_Leave | G1: Planned/Unplanned | H1: Status | I1: No_of_Leave | J1: Gap
A2: =VLOOKUP(D2,Transaction!$A$2:$C$477,3,0) -> 42725 | B2: 42830 | C2: 42830 | D2: E7 | E2: Family function | F2: Casual Leave | G2: Planned | H2: Approved | I2: =(C2-B2)+1 -> 1 | J2: =B2-A2 -> 105
A3: =VLOOKUP(D3,Transaction!$A$2:$C$477,3,0) -> 42726 | B3: 42831 | C3: 42831 | D3: E12 | E3: Sick Leave | F3: Sick Leave | G3: Unplanned | H3: Rejected | I3: =(C3-B3)+1 -> 1 | J3: =B3-A3 -> 105
A4: =VLOOKUP(D4,Transaction!$A$2:$C$477,3,0) -> 42728 | B4: 42837 | C4: 42839 | D4: E15 | E4: Sick Leave | F4: Sick Leave | G4: Planned | H4: Approved | I4: =(C4-B4)+1 -> 3 | J4: =B4-A4 -> 109
A5: =VLOOKUP(D5,Transaction!$A$2:$C$477,3,0) -> 42767 | B5: 42840 | C5: 42840 | D5: E24 | E5: Documentation Work | F5: Paid Leave | G5: Planned | H5: Rejected | I5: =(C5-B5)+1 -> 1 | J5: =B5-A5 -> 73
A6: =VLOOKUP(D6,Transaction!$A$2:$C$477,3,0) -> 42727 | B6: 42845 | C6: 42847 | D6: E14 | E6: Family Outing | F6: Casual Leave | G6: Unplanned | H6: Approved | I6: =(C6-B6)+1 -> 3 | J6: =B6-A6 -> 118
A7: =VLOOKUP(D7,Transaction!$A$2:$C$477,3,0) -> 42691 | B7: 42850 | C7: 42853 | D7: E100 | E7: Personal Reason | F7: Casual Leave | G7: Planned | H7: Approved | I7: =(C7-B7)+1 -> 4 | J7: =B7-A7 -> 159
A8: =VLOOKUP(D8,Transaction!$A$2:$C$477,3,0) -> 42725 | B8: 42874 | C8: 42874 | D8: E7 | E8: Sick Leave | F8: Sick Leave | G8: Unplanned | H8: Approved | I8: =(C8-B8)+1 -> 1 | J8: =B8-B2 -> 44
A9: =VLOOKUP(D9,Transaction!$A$2:$C$477,3,0) -> 42726 | B9: 42876 | C9: 42876 | D9: E12 | E9: Family function | F9: Casual Leave | G9: Planned | H9: Approved | I9: =(C9-B9)+1 -> 1 | J9: =B9-B3 -> 45
A10: =VLOOKUP(D10,Transaction!$A$2:$C$477,3,0) -> 42727 | B10: 42876 | C10: 42876 | D10: E14 | E10: Sick Leave | F10: Sick Leave | G10: Unplanned | H10: Rejected | I10: =(C10-B10)+1 -> 1 | J10: =B10-B6 -> 31
A11: =VLOOKUP(D11,Transaction!$A$2:$C$477,3,0) -> 42728 | B11: 42879 | C11: 42879 | D11: E15 | E11: Personal Reason | F11: Casual Leave | G11: Unplanned | H11: Approved | I11: =(C11-B11)+1 -> 1 | J11: =B11-B4 -> 42
A12: =VLOOKUP(D12,Transaction!$A$2:$C$477,3,0) -> 42767 | B12: 42883 | C12: 42883 | D12: E24 | E12: Family Outing | F12: Paid Leave | G12: Planned | H12: Approved | I12: =(C12-B12)+1 -> 1 | J12: =B12-B5 -> 43
A13: =VLOOKUP(D13,Transaction!$A$2:$C$477,3,0) -> 42725 | B13: 42914 | C13: 42914 | D13: E7 | E13: Sick Leave | F13: Sick Leave | G13: Unplanned | H13: Rejected | I13: =(C13-B13)+1 -> 1 | J13: =B13-B8 -> 40
A14: =VLOOKUP(D14,Transaction!$A$2:$C$477,3,0) -> 42726 | B14: 42887 | C14: 42887 | D14: E12 | E14: Documentation Work | F14: Paid Leave | G14: Unplanned | H14: Rejected | I14: =(C14-B14)+1 -> 1 | J14: =B14-B9 -> 11
A15: =VLOOKUP(D15,Transaction!$A$2:$C$477,3,0) -> 42727 | B15: 42892 | C15: 42893 | D15: E14 | E15: Family function | F15: Casual Leave | G15: Planned | H15: Approved | I15: =(C15-B15)+1 -> 2 | J15: =B15-B10 -> 16
A16: =VLOOKUP(D16,Transaction!$A$2:$C$477,3,0) -> 42728 | B16: 42899 | C16: 42905 | D16: E15 | E16: Family Outing | F16: Casual Leave | G16: Planned | H16: Approved | I16: =(C16-B16)+1 -> 7 | J16: =B16-B11 -> 20
A17: =VLOOKUP(D17,Transaction!$A$2:$C$477,3,0) -> 42767 | B17: 42902 | C17: 42902 | D17: E24 | E17: Sick Leave | F17: Sick Leave | G17: Unplanned | H17: Rejected | I17: =(C17-B17)+1 -> 1 | J17: =B17-B12 -> 19
A18: =VLOOKUP(D18,Transaction!$A$2:$C$477,3,0) -> 42725 | B18: 42948 | C18: 42948 | D18: E7 | E18: Documentation Work | F18: Casual Leave | G18: Planned | H18: Approved | I18: =(C18-B18)+1 -> 1 | J18: =B18-B13 -> 34
A19: =VLOOKUP(D19,Transaction!$A$2:$C$477,3,0) -> 42726 | B19: 42957 | C19: 42957 | D19: E12 | E19: Documentation Work | F19: Casual Leave | G19: Planned | H19: Rejected | I19: =(C19-B19)+1 -> 1 | J19: =B19-B14 -> 70
A20: =VLOOKUP(D20,Transaction!$A$2:$C$477,3,0) -> 42727 | B20: 42960 | C20: 42960 | D20: E14 | E20: Sick Leave | F20: Sick Leave | G20: Unplanned | H20: Approved | I20: =(C20-B20)+1 -> 1 | J20: =B20-B15 -> 68
A21: =VLOOKUP(D21,Transaction!$A$2:$C$477,3,0) -> 42728 | B21: 42962 | C21: 42962 | D21: E15 | E21: Family function | F21: Casual Leave | G21: Planned | H21: Rejected | I21: =(C21-B21)+1 -> 1 | J21: =B21-B16 -> 63
A22: =VLOOKUP(D22,Transaction!$A$2:$C$477,3,0) -> 42767 | B22: 42973 | C22: 42973 | D22: E24 | E22: Sick Leave | F22: Sick Leave | G22: Unplanned | H22: Rejected | I22: =(C22-B22)+1 -> 1 | J22: =B22-B17 -> 71
A23: =VLOOKUP(D23,Transaction!$A$2:$C$477,3,0) -> 42816 | B23: 42975 | C23: 42975 | D23: E307 | E23: Sick Leave | F23: Sick Leave | G23: Unplanned | H23: Rejected | I23: =(C23-B23)+1 -> 1 | J23: =B23-A23 -> 159
A24: =VLOOKUP(D24,Transaction!$A$2:$C$477,3,0) -> 42828 | B24: 42979 | C24: 42981 | D24: E308 | E24: Family Outing | F24: Casual Leave | G24: Planned | H24: Approved | I24: =(C24-B24)+1 -> 3 | J24: =B24-A24 -> 151
A25: =VLOOKUP(D25,Transaction!$A$2:$C$477,3,0) -> 42725 | B25: 42981 | C25: 42985 | D25: E7 | E25: Family Outing | F25: Casual Leave | G25: Unplanned | H25: Rejected | I25: =(C25-B25)+1 -> 5 | J25: =B25-B18 -> 33
A26: =VLOOKUP(D26,Transaction!$A$2:$C$477,3,0) -> 42726 | B26: 42987 | C26: 42987 | D26: E12 | E26: Sick Leave | F26: Sick Leave | G26: Unplanned | H26: Approved | I26: =(C26-B26)+1 -> 1 | J26: =B26-B19 -> 30
A27: =VLOOKUP(D27,Transaction!$A$2:$C$477,3,0) -> 42727 | B27: 42992 | C27: 42996 | D27: E14 | E27: Personal Reason | F27: Leave Without Pay | G27: Unplanned | H27: Approved | I27: =(C27-B27)+1 -> 5 | J27: =B27-B20 -> 32
A28: =VLOOKUP(D28,Transaction!$A$2:$C$477,3,0) -> 42728 | B28: 42995 | C28: 42997 | D28: E15 | E28: Family function | F28: Leave Without Pay | G28: Planned | H28: Approved | I28: =(C28-B28)+1 -> 3 | J28: =B28-B21 -> 33
A29: =VLOOKUP(D29,Transaction!$A$2:$C$477,3,0) -> 42767 | B29: 42999 | C29: 42999 | D29: E24 | E29: Documentation Work | F29: Leave Without Pay | G29: Planned | H29: Rejected | I29: =(C29-B29)+1 -> 1 | J29: =B29-B22 -> 26
A30: =VLOOKUP(D30,Transaction!$A$2:$C$477,3,0) -> 42725 | B30: 43020 | C30: 43022 | D30: E7 | E30: Family Outing | F30: Paid Leave | G30: Planned | H30: Approved | I30: =(C30-B30)+1 -> 3 | J30: =B30-B25 -> 39
A31: =VLOOKUP(D31,Transaction!$A$2:$C$477,3,0) -> 42726 | B31: 43028 | C31: 43028 | D31: E12 | E31: Documentation Work | F31: Casual Leave | G31: Planned | H31: Rejected | I31: =(C31-B31)+1 -> 1 | J31: =B31-B26 -> 41
A32: =VLOOKUP(D32,Transaction!$A$2:$C$477,3,0) -> 42727 | B32: 43040 | C32: 43040 | D32: E14 | E32: Documentation Work | F32: Casual Leave | G32: Planned | H32: Approved | I32: =(C32-B32)+1 -> 1 | J32: =B32-B27 -> 48
A33: =VLOOKUP(D33,Transaction!$A$2:$C$477,3,0) -> 42728 | B33: 43043 | C33: 43043 | D33: E15 | E33: Personal Reason | F33: Leave Without Pay | G33: Unplanned | H33: Rejected | I33: =(C33-B33)+1 -> 1 | J33: =B33-B28 -> 48
A34: =VLOOKUP(D34,Transaction!$A$2:$C$477,3,0) -> 42767 | B34: 43048 | C34: 43051 | D34: E24 | E34: Sick Leave | F34: Sick Leave | G34: Unplanned | H34: Approved | I34: =(C34-B34)+1 -> 4 | J34: =B34-B29 -> 49
A35: =VLOOKUP(D35,Transaction!$A$2:$C$477,3,0) -> 42725 | B35: 43052 | C35: 43053 | D35: E7 | E35: Family Outing | F35: Paid Leave | G35: Planned | H35: Approved | I35: =(C35-B35)+1 -> 2 | J35: =B35-B30 -> 32
A36: =VLOOKUP(D36,Transaction!$A$2:$C$477,3,0) -> 42726 | B36: 43054 | C36: 43054 | D36: E12 | E36: Personal Reason | F36: Leave Without Pay | G36: Unplanned | H36: Rejected | I36: =(C36-B36)+1 -> 1 | J36: =B36-B31 -> 26
A37: =VLOOKUP(D37,Transaction!$A$2:$C$477,3,0) -> 42727 | B37: 43055 | C37: 43059 | D37: E14 | E37: Family function | F37: Casual Leave | G37: Planned | H37: Approved | I37: =(C37-B37)+1 -> 5 | J37: =B37-B32 -> 15
A38: =VLOOKUP(D38,Transaction!$A$2:$C$477,3,0) -> 42728 | B38: 43056 | C38: 43059 | D38: E15 | E38: Family function | F38: Paid Leave | G38: Planned | H38: Approved | I38: =(C38-B38)+1 -> 4 | J38: =B38-B33 -> 13
A39: =VLOOKUP(D39,Transaction!$A$2:$C$477,3,0) -> 42767 | B39: 43060 | C39: 43061 | D39: E24 | E39: Family Outing | F39: Leave Without Pay | G39: Planned | H39: Approved | I39: =(C39-B39)+1 -> 2 | J39: =B39-B34 -> 12
A40: =VLOOKUP(D40,Transaction!$A$2:$C$477,3,0) -> 42725 | B40: 43083 | C40: 43083 | D40: E7 | E40: Family Outing | F40: Paid Leave | G40: Planned | H40: Approved | I40: =(C40-B40)+1 -> 1 | J40: =B40-B35 -> 31
A41: =VLOOKUP(D41,Transaction!$A$2:$C$477,3,0) -> 42726 | B41: 43084 | C41: 43084 | D41: E12 | E41: Documentation Work | F41: Paid Leave | G41: Unplanned | H41: Approved | I41: =(C41-B41)+1 -> 1 | J41: =B41-B36 -> 30
... A44: =VLOOKUP(D44,Transaction!$A$2:$C$477,3,0) -> 42767 | B44: 43096 | C44: 43096 | D44: E24 | E44: Sick Leave | F44: Sick Leave | G44: Unplanned | H44: Approved | I44: =(C44-B44)+1 -> 1 | J44: =B44-B39 -> 36
A45: =VLOOKUP(D45,Transaction!$A$2:$C$477,3,0) -> 42691 | B45: 43097 | C45: 43097 | D45: E100 | E45: Sick Leave | F45: Sick Leave | G45: Unplanned | H45: Approved | I45: =(C45-B45)+1 -> 1 | J45: =B45-B7 -> 247
A46: =VLOOKUP(D46,Transaction!$A$2:$C$477,3,0) -> 42816 | B46: 43098 | C46: 43100 | D46: E307 | E46: Family function | F46: Casual Leave | G46: Planned | H46: Approved | I46: =(C46-B46)+1 -> 3 | J46: =B46-B23 -> 123
A47: =VLOOKUP(D47,Transaction!$A$2:$C$477,3,0) -> 42828 | B47: 43098 | C47: 43098 | D47: E308 | E47: Sick Leave | F47: Sick Leave | G47: Unplanned | H47: Rejected | I47: =(C47-B47)+1 -> 1 | J47: =B47-B24 -> 119
A48: =VLOOKUP(D48,Transaction!$A$2:$C$477,3,0) -> 42725 | B48: 43100 | C48: 43100 | D48: E7 | E48: Family function | F48: Casual Leave | G48: Unplanned | H48: Rejected | I48: =(C48-B48)+1 -> 1 | J48: =B48-B40 -> 17
A49: =VLOOKUP(D49,Transaction!$A$2:$C$477,3,0) -> 42726 | B49: 43101 | C49: 43101 | D49: E12 | E49: Sick Leave | F49: Sick Leave | G49: Unplanned | H49: Approved | I49: =(C49-B49)+1 -> 1 | J49: =B49-B41 -> 17
A50: =VLOOKUP(D50,Transaction!$A$2:$C$477,3,0) -> 42727 | B50: 43112 | C50: 43112 | D50: E14 | E50: Sick Leave | F50: Sick Leave | G50: Unplanned | H50: Approved | I50: =(C50-B50)+1 -> 1 | J50: =B50-B42 -> 23
A51: =VLOOKUP(D51,Transaction!$A$2:$C$477,3,0) -> 43108 | B51: 43112 | C51: 43112 | D51: E339 | E51: Sick Leave | F51: Sick Leave | G51: Unplanned | H51: Approved | I51: =(C51-B51)+1 -> 1 | J51: =B51-A51 -> 4
A52: =VLOOKUP(D52,Transaction!$A$2:$C$477,3,0) -> 42728 | B52: 43113 | C52: 43113 | D52: E15 | E52: Personal Reason | F52: Leave Without Pay | G52: Unplanned | H52: Rejected | I52: =(C52-B52)+1 -> 1 | J52: =B52-B43 -> 21
A53: =VLOOKUP(D53,Transaction!$A$2:$C$477,3,0) -> 42767 | B53: 43124 | C53: 43124 | D53: E24 | E53: Documentation Work | F53: Paid Leave | G53: Planned | H53: Approved | I53: =(C53-B53)+1 -> 1 | J53: =B53-B44 -> 28
A54: =VLOOKUP(D54,Transaction!$A$2:$C$477,3,0) -> 42725 | B54: 43146 | C54: 43146 | D54: E7 | E54: Sick Leave | F54: Sick Leave | G54: Unplanned | H54: Approved | I54: =(C54-B54)+1 -> 1 | J54: =B54-B48 -> 46
A55: =VLOOKUP(D55,Transaction!$A$2:$C$477,3,0) -> 42726 | B55: 43151 | C55: 43151 | D55: E12 | E55: Sick Leave | F55: Sick Leave | G55: Unplanned | H55: Rejected | I55: =(C55-B55)+1 -> 1 | J55: =B55-B49 -> 50
A56: =VLOOKUP(D56,Transaction!$A$2:$C$477,3,0) -> 42727 | B56: 43161 | C56: 43161 | D56: E14 | E56: Documentation Work | F56: Leave Without Pay | G56: Unplanned | H56: Approved | I56: =(C56-B56)+1 -> 1 | J56: =B56-B50 -> 49
A57: =VLOOKUP(D57,Transaction!$A$2:$C$477,3,0) -> 42728 | B57: 43173 | C57: 43173 | D57: E15 | E57: Documentation Work | F57: Leave Without Pay | G57: Unplanned | H57: Approved | I57: =(C57-B57)+1 -> 1 | J57: =B57-B52 -> 60
A58: =VLOOKUP(D58,Transaction!$A$2:$C$477,3,0) -> 42767 | B58: 43184 | C58: 43188 | D58: E24 | E58: Personal Reason | F58: Paid Leave | G58: Planned | H58: Approved | I58: =(C58-B58)+1 -> 5 | J58: =B58-B53 -> 60
A59: =VLOOKUP(D59,Transaction!$A$2:$C$477,3,0) -> 42725 | B59: 43195 | C59: 43196 | D59: E7 | E59: Family function | F59: Paid Leave | G59: Planned | H59: Approved | I59: =(C59-B59)+1 -> 2 | J59: =B59-B54 -> 49
A60: =VLOOKUP(D60,Transaction!$A$2:$C$477,3,0) -> 42726 | B60: 43197 | C60: 43197 | D60: E12 | E60: Sick Leave | F60: Sick Leave | G60: Unplanned | H60: Rejected | I60: =(C60-B60)+1 -> 1 | J60: =B60-B55 -> 46
A61: =VLOOKUP(D61,Transaction!$A$2:$C$477,3,0) -> 42727 | B61: 43198 | C61: 43198 | D61: E14 | E61: Documentation Work | F61: Paid Leave | G61: Unplanned | H61: Rejected | I61: =(C61-B61)+1 -> 1 | J61: =B61-B56 -> 37
A62: =VLOOKUP(D62,Transaction!$A$2:$C$477,3,0) -> 42728 | B62: 43204 | C62: 43204 | D62: E15 | E62: Personal Reason | F62: Paid Leave | G62: Planned | H62: Approved | I62: =(C62-B62)+1 -> 1 | J62: =B62-B57 -> 31
A63: =VLOOKUP(D63,Transaction!$A$2:$C$477,3,0) -> 42767 | B63: 43207 | C63: 43209 | D63: E24 | E63: Sick Leave | F63: Sick Leave | G63: Unplanned | H63: Approved | I63: =(C63-B63)+1 -> 3 | J63: =B63-B58 -> 23
A64: =VLOOKUP(D64,Transaction!$A$2:$C$477,3,0) -> 42691 | B64: 43208 | C64: 43211 | D64: E100 | E64: Family Outing | F64: Casual Leave | G64: Planned | H64: Approved | I64: =(C64-B64)+1 -> 4 | J64: =B64-B45 -> 111
A65: =VLOOKUP(D65,Transaction!$A$2:$C$477,3,0) -> 42725 | B65: 43212 | C65: 43212 | D65: E7 | E65: Sick Leave | F65: Sick Leave | G65: Unplanned | H65: Rejected | I65: =(C65-B65)+1 -> 1 | J65: =B65-B59 -> 17
A66: =VLOOKUP(D66,Transaction!$A$2:$C$477,3,0) -> 42726 | B66: 43217 | C66: 43217 | D66: E12 | E66: Family function | F66: Casual Leave | G66: Planned | H66: Approved | I66: =(C66-B66)+1 -> 1 | J66: =B66-B60 -> 20
A67: =VLOOKUP(D67,Transaction!$A$2:$C$477,3,0) -> 42727 | B67: 43241 | C67: 43241 | D67: E14 | E67: Family Outing | F67: Paid Leave | G67: Planned | H67: Approved | I67: =(C67-B67)+1 -> 1 | J67: =B67-B61 -> 43
A68: =VLOOKUP(D68,Transaction!$A$2:$C$477,3,0) -> 42728 | B68: 43243 | C68: 43243 | D68: E15 | E68: Personal Reason | F68: Casual Leave | G68: Planned | H68: Approved | I68: =(C68-B68)+1 -> 1 | J68: =B68-B62 -> 39
A69: =VLOOKUP(D69,Transaction!$A$2:$C$477,3,0) -> 42767 | B69: 43243 | C69: 43243 | D69: E24 | E69: Sick Leave | F69: Sick Leave | G69: Unplanned | H69: Approved | I69: =(C69-B69)+1 -> 1 | J69: =B69-B63 -> 36
A70: =VLOOKUP(D70,Transaction!$A$2:$C$477,3,0) -> 43150 | B70: 43243 | C70: 43243 | D70: E355 | E70: Family function | F70: Casual Leave | G70: Planned | H70: Approved | I70: =(C70-B70)+1 -> 1 | J70: =B70-A70 -> 93
A71: =VLOOKUP(D71,Transaction!$A$2:$C$477,3,0) -> 42816 | B71: 43244 | C71: 43244 | D71: E307 | E71: Documentation Work | F71: Paid Leave | G71: Unplanned | H71: Rejected | I71: =(C71-B71)+1 -> 1 | J71: =B71-B46 -> 146
A72: =VLOOKUP(D72,Transaction!$A$2:$C$477,3,0) -> 42828 | B72: 43245 | C72: 43245 | D72: E308 | E72: Documentation Work | F72: Leave Without Pay | G72: Planned | H72: Approved | I72: =(C72-B72)+1 -> 1 | J72: =B72-B47 -> 147
A73: =VLOOKUP(D73,Transaction!$A$2:$C$477,3,0) -> 42725 | B73: 43246 | C73: 43246 | D73: E7 | E73: Sick Leave | F73: Sick Leave | G73: Unplanned | H73: Approved | I73: =(C73-B73)+1 -> 1 | J73: =B73-B65 -> 34
A74: =VLOOKUP(D74,Transaction!$A$2:$C$477,3,0) -> 42726 | B74: 43250 | C74: 43250 | D74: E12 | E74: Sick Leave | F74: Sick Leave | G74: Unplanned | H74: Approved | I74: =(C74-B74)+1 -> 1 | J74: =B74-B66 -> 33
A75: =VLOOKUP(D75,Transaction!$A$2:$C$477,3,0) -> 42727 | B75: 43250 | C75: 43250 | D75: E14 | E75: Personal Reason | F75: Leave Without Pay | G75: Unplanned | H75: Approved | I75: =(C75-B75)+1 -> 1 | J75: =B75-B67 -> 9
A76: =VLOOKUP(D76,Transaction!$A$2:$C$477,3,0) -> 42728 | B76: 43254 | C76: 43254 | D76: E15 | E76: Documentation Work | F76: Paid Leave | G76: Unplanned | H76: Rejected | I76: =(C76-B76)+1 -> 1 | J76: =B76-B68 -> 11
A77: =VLOOKUP(D77,Transaction!$A$2:$C$477,3,0) -> 42767 | B77: 43259 | C77: 43259 | D77: E24 | E77: Documentation Work | F77: Casual Leave | G77: Planned | H77: Approved | I77: =(C77-B77)+1 -> 1 | J77: =B77-B69 -> 16
A78: =VLOOKUP(D78,Transaction!$A$2:$C$477,3,0) -> 42725 | B78: 43266 | C78: 43266 | D78: E7 | E78: Documentation Work | F78: Paid Leave | G78: Planned | H78: Approved | I78: =(C78-B78)+1 -> 1 | J78: =B78-B73 -> 20
A79: =VLOOKUP(D79,Transaction!$A$2:$C$477,3,0) -> 42726 | B79: 43269 | C79: 43270 | D79: E12 | E79: Family Outing | F79: Paid Leave | G79: Planned | H79: Approved | I79: =(C79-B79)+1 -> 2 | J79: =B79-B74 -> 19
A80: =VLOOKUP(D80,Transaction!$A$2:$C$477,3,0) -> 42727 | B80: 43276 | C80: 43276 | D80: E14 | E80: Personal Reason | F80: Leave Without Pay | G80: Planned | H80: Rejected | I80: =(C80-B80)+1 -> 1 | J80: =B80-B75 -> 26
A81: =VLOOKUP(D81,Transaction!$A$2:$C$477,3,0) -> 42728 | B81: 43315 | C81: 43319 | D81: E15 | E81: Personal Reason | F81: Paid Leave | G81: Unplanned | H81: Approved | I81: =(C81-B81)+1 -> 5 | J81: =B81-B76 -> 61
A82: =VLOOKUP(D82,Transaction!$A$2:$C$477,3,0) -> 42767 | B82: 43324 | C82: 43324 | D82: E24 | E82: Personal Reason | F82: Leave Without Pay | G82: Planned | H82: Approved | I82: =(C82-B82)+1 -> 1 | J82: =B82-B77 -> 65
A83: =VLOOKUP(D83,Transaction!$A$2:$C$477,3,0) -> 43150 | B83: 43325 | C83: 43325 | D83: E355 | E83: Sick Leave | F83: Sick Leave | G83: Unplanned | H83: Approved | I83: =(C83-B83)+1 -> 1 | J83: =B83-B70 -> 82
A84: =VLOOKUP(D84,Transaction!$A$2:$C$477,3,0) -> 42816 | B84: 43326 | C84: 43326 | D84: E307 | E84: Personal Reason | F84: Casual Leave | G84: Planned | H84: Approved | I84: =(C84-B84)+1 -> 1 | J84: =B84-B71 -> 82
A85: =VLOOKUP(D85,Transaction!$A$2:$C$477,3,0) -> 42828 | B85: 43327 | C85: 43327 | D85: E308 | E85: Sick Leave | F85: Sick Leave | G85: Unplanned | H85: Approved | I85: =(C85-B85)+1 -> 1 | J85: =B85-B72 -> 82
A86: =VLOOKUP(D86,Transaction!$A$2:$C$477,3,0) -> 42725 | B86: 43327 | C86: 43329 | D86: E7 | E86: Family Outing | F86: Paid Leave | G86: Unplanned | H86: Rejected | I86: =(C86-B86)+1 -> 3 | J86: =B86-B78 -> 61
A87: =VLOOKUP(D87,Transaction!$A$2:$C$477,3,0) -> 42726 | B87: 43329 | C87: 43329 | D87: E12 | E87: Family Function | F87: Paid Leave | G87: Planned | H87: Approved | I87: =(C87-B87)+1 -> 1 | J87: =B87-B79 -> 60
A88: =VLOOKUP(D88,Transaction!$A$2:$C$477,3,0) -> 42727 | B88: 43340 | C88: 43340 | D88: E14 | E88: Documentation Work | F88: Leave Without Pay | G88: Planned | H88: Approved | I88: =(C88-B88)+1 -> 1 | J88: =B88-B80 -> 64
A89: =VLOOKUP(D89,Transaction!$A$2:$C$477,3,0) -> 43108 | B89: 43340 | C89: 43341 | D89: E339 | E89: Family function | F89: Casual Leave | G89: Planned | H89: Approved | I89: =(C89-B89)+1 -> 2 | J89: =B89-B51 -> 228
A90: =VLOOKUP(D90,Transaction!$A$2:$C$477,3,0) -> 42728 | B90: 43348 | C90: 43348 | D90: E15 | E90: Personal Reason | F90: Leave Without Pay | G90: Planned | H90: Rejected | I90: =(C90-B90)+1 -> 1 | J90: =B90-B81 -> 33
A91: =VLOOKUP(D91,Transaction!$A$2:$C$477,3,0) -> 42767 | B91: 43354 | C91: 43354 | D91: E24 | E91: Family Outing | F91: Leave Without Pay | G91: Planned | H91: Approved | I91: =(C91-B91)+1 -> 1 | J91: =B91-B82 -> 30
A92: =VLOOKUP(D92,Transaction!$A$2:$C$477,3,0) -> 42725 | B92: 43359 | C92: 43359 | D92: E7 | E92: Personal Reason | F92: Leave Without Pay | G92: Planned | H92: Approved | I92: =(C92-B92)+1 -> 1 | J92: =B92-B86 -> 32
A93: =VLOOKUP(D93,Transaction!$A$2:$C$477,3,0) -> 42726 | B93: 43362 | C93: 43362 | D93: E12 | E93: Documentation Work | F93: Casual Leave | G93: Unplanned | H93: Approved | I93: =(C93-B93)+1 -> 1 | J93: =B93-B87 -> 33
A94: =VLOOKUP(D94,Transaction!$A$2:$C$477,3,0) -> 42727 | B94: 43366 | C94: 43366 | D94: E14 | E94: Sick Leave | F94: Sick Leave | G94: Unplanned | H94: Rejected | I94: =(C94-B94)+1 -> 1 | J94: =B94-B88 -> 26
A95: =VLOOKUP(D95,Transaction!$A$2:$C$477,3,0) -> 43164 | B95: 43366 | C95: 43366 | D95: E362 | E95: Personal Reason | F95: Casual Leave | G95: Planned | H95: Approved | I95: =(C95-B95)+1 -> 1 | J95: =B95-A95 -> 202
A96: =VLOOKUP(D96,Transaction!$A$2:$C$477,3,0) -> 42728 | B96: 43387 | C96: 43388 | D96: E15 | E96: Family Outing | F96: Paid Leave | G96: Unplanned | H96: Rejected | I96: =(C96-B96)+1 -> 2 | J96: =B96-B90 -> 39
A97: =VLOOKUP(D97,Transaction!$A$2:$C$477,3,0) -> 42767 | B97: 43395 | C97: 43396 | D97: E24 | E97: Family Function | F97: Leave Without Pay | G97: Planned | H97: Approved | I97: =(C97-B97)+1 -> 2 | J97: =B97-B91 -> 41
A98: =VLOOKUP(D98,Transaction!$A$2:$C$477,3,0) -> 42725 | B98: 43407 | C98: 43407 | D98: E7 | E98: Family Outing | F98: Paid Leave | G98: Planned | H98: Approved | I98: =(C98-B98)+1 -> 1 | J98: =B98-B92 -> 48
A99: =VLOOKUP(D99,Transaction!$A$2:$C$477,3,0) -> 42726 | B99: 43410 | C99: 43410 | D99: E12 | E99: Personal Reason | F99: Leave Without Pay | G99: Planned | H99: Approved | I99: =(C99-B99)+1 -> 1 | J99: =B99-B93 -> 48
A100: =VLOOKUP(D100,Transaction!$A$2:$C$477,3,0) -> 42727 | B100: 43415 | C100: 43415 | D100: E14 | E100: Family Outing | F100: Casual Leave | G100: Unplanned | H100: Rejected | I100: =(C100-B100)+1 -> 1 | J100: =B100-B94 -> 49
A101: =VLOOKUP(D101,Transaction!$A$2:$C$477,3,0) -> 42728 | B101: 43419 | C101: 43419 | D101: E15 | E101: Sick Leave | F101: Sick Leave | G101: Unplanned | H101: Rejected | I101: =(C101-B101)+1 -> 1 | J101: =B101-B96 -> 32
A102: =VLOOKUP(D102,Transaction!$A$2:$C$477,3,0) -> 42767 | B102: 43421 | C102: 43421 | D102: E24 | E102: Family Function | F102: Leave Without Pay | G102: Unplanned | H102: Rejected | I102: =(C102-B102)+1 -> 1 | J102: =B102-B97 -> 26
...

Sheet Leave 
A1: Date | B1: EMP ID | C1: Reason for Leave | D1: Type of Leave | E1: Planned/Unplanned | F1: Status | G1: No of Leave
A2: 44287 | B2: E7 | C2: Sick Leave | D2: Sick Leave | E2: Unplanned | F2: Rejected | G2: 1
A3: 44287 | B3: E12 | C3: Family Outing | D3: Casual Leave | E3: Planned | F3: Rejected | G3: 1
A4: 44287 | B4: E14 | C4: Family Outing | D4: Casual Leave | E4: Planned | F4: Rejected | G4: 1
A5: 44287 | B5: E15 | C5: Family Outing | D5: Casual Leave | E5: Planned | F5: Rejected | G5: 1
A6: 44287 | B6: E24 | C6: Sick Leave | D6: Sick Leave | E6: Unplanned | F6: Rejected | G6: 1
A7: 44287 | B7: E27 | C7: Documentation Work | D7: Leave Without Pay | E7: Planned | F7: Rejected | G7: 1
A8: 44287 | B8: E36 | C8: Documentation Work | D8: Leave Without Pay | E8: Planned | F8: Rejected | G8: 1
A9: 44287 | B9: E38 | C9: Family Outing | D9: Paid Leave | E9: Planned | F9: Rejected | G9: 1
A10: 44287 | B10: E53 | C10: Family Outing | D10: Paid Leave | E10: Planned | F10: Rejected | G10: 1
A11: 44287 | B11: E56 | C11: Personal Reason | D11: Leave Without Pay | E11: Planned | F11: Rejected | G11: 1
A12: 44294 | B12: E62 | C12: Family Outing | D12: Casual Leave | E12: Planned | F12: Rejected | G12: 1
A13: 44294 | B13: E63 | C13: Sick Leave | D13: Sick Leave | E13: Unplanned | F13: Rejected | G13: 1
... A547: 44692 | B547: E549 | C547: Documentation Work | D547: Casual Leave | E547: Planned | F547: Approved | G547: 1

Sheet Leave  (3)
A1: Date | B1: EMP ID | C1: Reason for Leave | D1: Type of Leave | E1: Planned/Unplanned | F1: Status | G1: No of Leave | H1: gap
A2: 42830 | B2: E7 | C2: Family function | D2: Casual Leave | E2: Planned | F2: Approved | G2: 1 | H2: =IF(A3="","",A3-A2) -> 44
A3: 42874 | B3: E7 | C3: Sick Leave | D3: Sick Leave | E3: Unplanned | F3: Approved | G3: 1 | H3: =IF(A4="","",A4-A3) -> 40
A4: 42914 | B4: E7 | C4: Sick Leave | D4: Sick Leave | E4: Unplanned | F4: Rejected | G4: 1 | H4: =IF(A5="","",A5-A4) -> 34
A5: 42948 | B5: E7 | C5: Documentation Work | D5: Casual Leave | E5: Planned | F5: Approved | G5: 1 | H5: =IF(A6="","",A6-A5) -> 53
A6: 43001 | B6: E7 | C6: Family Outing | D6: Casual Leave | E6: Unplanned | F6: Rejected | G6: 1 | H6: =IF(A7="","",A7-A6) -> 50
A7: 43051 | B7: E7 | C7: Family Outing | D7: Paid Leave | E7: Planned | F7: Approved | G7: 1 | H7: =IF(A8="","",A8-A7) -> 1
A8: 43052 | B8: E7 | C8: Family Outing | D8: Paid Leave | E8: Planned | F8: Approved | G8: 1 | H8: =IF(A9="","",A9-A8) -> 1
A9: 43053 | B9: E7 | C9: Family Outing | D9: Paid Leave | E9: Planned | F9: Approved | G9: 1 | H9: =IF(A10="","",A10-A9) -> 47
A10: 43100 | B10: E7 | C10: Family function | D10: Casual Leave | E10: Unplanned | F10: Rejected | G10: 1 | H10: =IF(A11="","",A11-A10) -> 12
A11: 43112 | B11: E7 | C11: Sick Leave | D11: Paid Leave | E11: Unplanned | F11: Approved | G11: 1 | H11: =IF(A12="","",A12-A11) -> 83
A12: 43195 | B12: E7 | C12: Family function | D12: Casual Leave | E12: Planned | F12: Approved | G12: 1 | H12: =IF(A13="","",A13-A12) -> 26
A13: 43221 | B13: E7 | C13: Sick Leave | D13: Sick Leave | E13: Unplanned | F13: Rejected | G13: 1 | H13: =IF(A14="","",A14-A13) -> 81
... A41: 44239 | B41: E7 | C41: Sick Leave | D41: Paid Leave | E41: Unplanned | F41: Rejected | G41: 1 | H41: =IF(A42="","",A42-A41)

Sheet Claim
A1: Date | B1: Emp ID | C1: Marrage | D1: Travel | E1: Travel Cost | F1: Food | G1: Food Cost | H1: Special Allowance | I1: Special Allowance Cost | J1: Children Education | K1: Children Education Cost | L1: Internet/Phone Bills | M1: Internet/Phone Bills cost | N1: Medical Reimbursement | O1: Medical Reimbursement cost
A2: 44316 | B2: E7 | C2: Married | D2: Yes | E2: 3687 | F2: Yes | G2: 2555 | H2: Yes | I2: 2296 | J2: Yes | K2: 1881 | L2: No | M2: 0 | N2: Yes | O2: 4493
A3: 44316 | B3: E12 | C3: Married | D3: Yes | E3: 3111 | F3: Yes | G3: 2810 | H3: Yes | I3: 2375 | J3: Yes | K3: 1498 | L3: Yes | M3: 3208 | N3: Yes | O3: 3566
A4: 44316 | B4: E14 | C4: Unmarried | D4: Yes | E4: 3842 | F4: Yes | G4: 2846 | H4: Yes | I4: 2416 | J4: No | K4: 0 | L4: No | M4: 0 | N4: Yes | O4: 4991
A5: 44316 | B5: E15 | C5: Unmarried | D5: Yes | E5: 4332 | F5: Yes | G5: 2977 | H5: Yes | I5: 2276 | J5: No | K5: 0 | L5: No | M5: 0 | N5: Yes | O5: 4423
A6: 44316 | B6: E24 | C6: Unmarried | D6: Yes | E6: 3734 | F6: Yes | G6: 2370 | H6: No | I6: 0 | J6: No | K6: 0 | L6: No | M6: 0 | N6: Yes | O6: 3828
A7: 44316 | B7: E27 | C7: Married | D7: Yes | E7: 3875 | F7: Yes | G7: 2131 | H7: Yes | I7: 2147 | J7: Yes | K7: 1775 | L7: Yes | M7: 3433 | N7: Yes | O7: 5808
A8: 44316 | B8: E36 | C8: Married | D8: Yes | E8: 4726 | F8: Yes | G8: 2540 | H8: Yes | I8: 2527 | J8: Yes | K8: 1803 | L8: No | M8: 0 | N8: Yes | O8: 4548
A9: 44316 | B9: E38 | C9: Married | D9: Yes | E9: 3149 | F9: Yes | G9: 2973 | H9: Yes | I9: 2383 | J9: Yes | K9: 1986 | L9: Yes | M9: 3001 | N9: Yes | O9: 5878
A10: 44316 | B10: E53 | C10: Unmarried | D10: Yes | E10: 3265 | F10: Yes | G10: 2803 | H10: Yes | I10: 2020 | J10: No | K10: 0 | L10: No | M10: 0 | N10: Yes | O10: 3718
A11: 44316 | B11: E56 | C11: Unmarried | D11: Yes | E11: 4976 | F11: Yes | G11: 2583 | H11: No | I11: 0 | J11: No | K11: 0 | L11: No | M11: 0 | N11: Yes | O11: 5028
A12: 44316 | B12: E62 | C12: Unmarried | D12: Yes | E12: 3599 | F12: Yes | G12: 2197 | H12: No | I12: 0 | J12: No | K12: 0 | L12: No | M12: 0 | N12: Yes | O12: 3714
A13: 44316 | B13: E63 | C13: Married | D13: Yes | E13: 3895 | F13: Yes | G13: 2632 | H13: No | I13: 0 | J13: Yes | K13: 1812 | L13: No | M13: 0 | N13: Yes | O13: 4098
... A7393: 44926 | B7393: E2001 | C7393: Married | D7393: No | E7393: 0 | F7393: Yes | G7393: 2074 | H7393: Yes | I7393: 2606 | J7393: Yes | K7393: 1524 | L7393: Yes | M7393: 3205 | N7393: Yes | O7393: 4082

Sheet Claim2
A1: Date | B1: Emp ID | C1: Level | D1: Claim Type | E1: Cost
A2: 44316 | B2: E7 | C2: L8 | D2: Travel | E2: 3763
A3: 44316 | B3: E7 | C3: L8 | D3: Food | E3: 4182
A4: 44316 | B4: E7 | C4: L8 | D4: Special Allowance | E4: 3296
A5: 44316 | B5: E7 | C5: L8 | D5: Internet/Phone Bills | E5: 3623
A6: 44316 | B6: E7 | C6: L8 | D6: Medical Reimbursement | E6: 5276
A7: 44316 | B7: E12 | C7: L8 | D7: Food | E7: 2347
A8: 44316 | B8: E12 | C8: L8 | D8: Travel | E8: 3727
A9: 44316 | B9: E12 | C9: L8 | D9: Special Allowance | E9: 3106
A10: 44316 | B10: E12 | C10: L8 | D10: Internet/Phone Bills | E10: 3507
A11: 44316 | B11: E12 | C11: L8 | D11: Medical Reimbursement | E11: 5268
A12: 44316 | B12: E14 | C12: L8 | D12: Travel | E12: 4297
A13: 44316 | B13: E14 | C13: L8 | D13: Food | E13: 2329
... A7299: 44712 | B7299: E935 | C7299: L1 | D7299: Travel | E7299: 3705

Sheet Outing
A1: Date | B1: Department | C1: Emp Code | D1: Outing Place
A2: 44301 | B2: BI | C2: E7 | D2: Imagicaa Water Park
A3: 44301 | B3: BI | C3: E12 | D3: Imagicaa Water Park
A4: 44301 | B4: BI | C4: E14 | D4: Imagicaa Water Park
A5: 44301 | B5: BI | C5: E15 | D5: Imagicaa Water Park
A6: 44301 | B6: BI | C6: E24 | D6: Imagicaa Water Park
A7: 44301 | B7: BI | C7: E27 | D7: Imagicaa Water Park
A8: 44301 | B8: BI | C8: E38 | D8: Imagicaa Water Park
A9: 44301 | B9: BI | C9: E53 | D9: Imagicaa Water Park
A10: 44301 | B10: BI | C10: E56 | D10: Imagicaa Water Park
A11: 44301 | B11: BI | C11: E62 | D11: Imagicaa Water Park
A12: 44301 | B12: BI | C12: E63 | D12: Imagicaa Water Park
A13: 44301 | B13: BI | C13: E64 | D13: Imagicaa Water Park
... A369: 44513 | B369: Support | C369: E857 | D369: Sunny's World, Pune

Sheet Award & Recognition
A1: Date | B1: Quater | C1: Emp_Code | D1: Award Type | E1: Recognition Type
A2: 44012 | B2: 20-21 Q1 | C2: E7 | D2: The Brainiac
A3: 44012 | B3: 20-21 Q1 | C3: E12 | D3: The Brainiac
A4: 44012 | B4: 20-21 Q1 | C4: E672 | D4: Best Team Player
A5: 44012 | B5: 20-21 Q1 | C5: E674 | D5: Best Team Player
A6: 44012 | B6: 20-21 Q1 | C6: E38 | D6: The Brainiac
A7: 44012 | B7: 20-21 Q1 | C7: E683 | D7: The Brainiac
A8: 44012 | B8: 20-21 Q1 | C8: E684 | D8: The Brainiac
A9: 44012 | B9: 20-21 Q1 | C9: E24 | D9: Stand Out Performer | E9: Recognition
A10: 44012 | B10: 20-21 Q1 | C10: E138 | D10: Stand Out Performer | E10: Recognition
A11: 44012 | B11: 20-21 Q1 | C11: E329 | D11: Stand Out Performer
A12: 44012 | B12: 20-21 Q1 | C12: E371 | D12: Stand Out Performer
A13: 44012 | B13: 20-21 Q1 | C13: E481 | D13: Mountain Mover
A14: 44012 | B14: 20-21 Q1 | C14: E676 | D14: Star of the Quater | E14: Recognition
A15: 44012 | B15: 20-21 Q1 | C15: E150 | E15: Recognition
A16: 44012 | B16: 20-21 Q1 | C16: E192 | E16: Recognition
A17: 44012 | B17: 20-21 Q1 | C17: E208 | E17: Recognition
A18: 44012 | B18: 20-21 Q1 | C18: E283 | E18: Recognition
A19: 44012 | B19: 20-21 Q1 | C19: E308 | E19: Recognition
A20: 44012 | B20: 20-21 Q1 | C20: E335 | E20: Recognition
A21: 44012 | B21: 20-21 Q1 | C21: E350 | E21: Recognition
A22: 44104 | B22: 20-21 Q2 | C22: E418 | D22: Best Team Player
A23: 44104 | B23: 20-21 Q2 | C23: E426 | D23: Best Team Player
A24: 44104 | B24: 20-21 Q2 | C24: E429 | D24: Best Team Player
A25: 44104 | B25: 20-21 Q2 | C25: E430 | D25: Stand Out Performer
A26: 44104 | B26: 20-21 Q2 | C26: E467 | D26: Stand Out Performer
A27: 44104 | B27: 20-21 Q2 | C27: E497 | D27: Star of the Quater
A28: 44104 | B28: 20-21 Q2 | C28: E36 | D28: Mountain Mover
A29: 44104 | B29: 20-21 Q2 | C29: E499 | D29: Mountain Mover
A30: 44104 | B30: 20-21 Q2 | C30: E635 | D30: Mountain Mover
A31: 44104 | B31: 20-21 Q2 | C31: E735 | D31: The Brainiac
A32: 44104 | B32: 20-21 Q2 | C32: E594 | D32: The Brainiac
A33: 44104 | B33: 20-21 Q2 | C33: E684 | D33: Best Customer Centricity
A34: 44104 | B34: 20-21 Q2 | C34: E38 | D34: Best Customer Centricity
A35: 44104 | B35: 20-21 Q2 | C35: E403 | E35: Recognition
A36: 44104 | B36: 20-21 Q2 | C36: E601 | E36: Recognition
A37: 44104 | B37: 20-21 Q2 | C37: E683 | E37: Recognition
A38: 44104 | B38: 20-21 Q2 | C38: E526 | E38: Recognition
A39: 44104 | B39: 20-21 Q2 | C39: E564 | E39: Recognition
A40: 44104 | B40: 20-21 Q2 | C40: E565 | E40: Recognition
A41: 44104 | B41: 20-21 Q2 | C41: E582 | E41: Recognition
A42: 44104 | B42: 20-21 Q2 | C42: E682 | E42: Recognition
A43: 44104 | B43: 20-21 Q2 | C43: E696 | E43: Recognition
A44: 44104 | B44: 20-21 Q2 | C44: E697 | E44: Recognition
A45: 44196 | B45: 20-21 Q3 | C45: E672 | D45: Best Team Player
A46: 44196 | B46: 20-21 Q3 | C46: E676 | D46: Best Team Player
A47: 44196 | B47: 20-21 Q3 | C47: E36 | D47: Best Team Player
A48: 44196 | B48: 20-21 Q3 | C48: E499 | D48: Best Team Player
A49: 44196 | B49: 20-21 Q3 | C49: E594 | D49: Best Team Player
A50: 44196 | B50: 20-21 Q3 | C50: E735 | D50: Best Customer Centricity
A51: 44196 | B51: 20-21 Q3 | C51: E756 | D51: Best Customer Centricity
A52: 44196 | B52: 20-21 Q3 | C52: E646 | D52: Best Customer Centricity
A53: 44196 | B53: 20-21 Q3 | C53: E560 | D53: The Brainiac
A54: 44196 | B54: 20-21 Q3 | C54: E594 | D54: The Brainiac
A55: 44196 | B55: 20-21 Q3 | C55: E683 | D55: The Brainiac
A56: 44196 | B56: 20-21 Q3 | C56: E403 | D56: Star of the Quater
A57: 44196 | B57: 20-21 Q3 | C57: E601 | D57: Star of the Quater | E57: Recognition
A58: 44196 | B58: 20-21 Q3 | C58: E684 | D58: Stand Out Performer
A59: 44196 | B59: 20-21 Q3 | C59: E145 | D59: Stand Out Performer
A60: 44196 | B60: 20-21 Q3 | C60: E559 | D60: Stand Out Performer
A61: 44196 | B61: 20-21 Q3 | C61: E794 | D61: Stand Out Performer
A62: 44196 | B62: 20-21 Q3 | C62: E801 | D62: Stand Out Performer | E62: Recognition
A63: 44196 | B63: 20-21 Q3 | C63: E404 | E63: Recognition
A64: 44196 | B64: 20-21 Q3 | C64: E521 | E64: Recognition
A65: 44196 | B65: 20-21 Q3 | C65: E559 | E65: Recognition
A66: 44196 | B66: 20-21 Q3 | C66: E607 | E66: Recognition
A67: 44196 | B67: 20-21 Q3 | C67: E731 | E67: Recognition
A68: 44196 | B68: 20-21 Q3 | C68: E747 | E68: Recognition
A69: 44196 | B69: 20-21 Q3 | C69: E802 | E69: Recognition
A70: 44196 | B70: 20-21 Q3 | C70: E810 | E70: Recognition
A71: 44286 | B71: 20-21 Q4 | C71: E38 | D71: Best Team Player
A72: 44286 | B72: 20-21 Q4 | C72: E403 | D72: Best Team Player
A73: 44286 | B73: 20-21 Q4 | C73: E601 | D73: Best Team Player
A74: 44286 | B74: 20-21 Q4 | C74: E684 | D74: Best Team Player
A75: 44286 | B75: 20-21 Q4 | C75: E12 | D75: Best Team Player
A76: 44286 | B76: 20-21 Q4 | C76: E329 | D76: Star of the Quater
A77: 44286 | B77: 20-21 Q4 | C77: E381 | D77: Star of the Quater
A78: 44286 | B78: 20-21 Q4 | C78: E462 | D78: The Brainiac
A79: 44286 | B79: 20-21 Q4 | C79: E481 | D79: The Brainiac
A80: 44286 | B80: 20-21 Q4 | C80: E63 | D80: Star of the Quater | E80: Recognition
A81: 44286 | B81: 20-21 Q4 | C81: E100 | D81: Star of the Quater | E81: Recognition
A82: 44286 | B82: 20-21 Q4 | C82: E115 | D82: Best Customer Centricity | E82: Recognition
A83: 44286 | B83: 20-21 Q4 | C83: E135 | D83: Best Customer Centricity | E83: Recognition
A84: 44286 | B84: 20-21 Q4 | C84: E500 | D84: Best Customer Centricity
A85: 44286 | B85: 20-21 Q4 | C85: E559 | D85: Best Team Player
A86: 44286 | B86: 20-21 Q4 | C86: E560 | D86: Best Team Player
A87: 44286 | B87: 20-21 Q4 | C87: E646 | D87: Best Team Player
A88: 44286 | B88: 20-21 Q4 | C88: E262 | D88: Stand Out Performer | E88: Recognition
A89: 44286 | B89: 20-21 Q4 | C89: E526 | D89: Stand Out Performer | E89: Recognition
A90: 44286 | B90: 20-21 Q4 | C90: E539 | E90: Recognition
A91: 44286 | B91: 20-21 Q4 | C91: E565 | E91: Recognition
A92: 44286 | B92: 20-21 Q4 | C92: E572 | E92: Recognition
A93: 44286 | B93: 20-21 Q4 | C93: E579 | E93: Recognition
A94: 44286 | B94: 20-21 Q4 | C94: E582 | E94: Recognition
A95: 44286 | B95: 20-21 Q4 | C95: E592 | E95: Recognition
A96: 44377 | B96: 21-22 Q1 | C96: E7 | D96: The Brainiac
A97: 44377 | B97: 21-22 Q1 | C97: E12 | D97: The Brainiac
A98: 44377 | B98: 21-22 Q1 | C98: E14 | D98: The Brainiac
A99: 44377 | B99: 21-22 Q1 | C99: E672 | D99: Best Team Player
A100: 44377 | B100: 21-22 Q1 | C100: E674 | D100: Best Team Player
...

Sheet Hiring Management 1
A1: Department | B1: Count of Emp req. | C1: Month and Year | D1: Count of Emp Leaving
A2: BI | B2: 2 | C2: 43922 | D2: 2
A3: Support | B3: 3 | C3: 43922 | D3: 3
A4: Sales | B4: 3 | C4: 43922 | D4: 3
A5: Cloud | B5: 2 | C5: 43922 | D5: 2
A6: Cloud | B6: 1 | C6: 43952 | D6: 1
A7: QA & QC | B7: 3 | C7: 44013 | D7: 3
A8: BI | B8: 1 | C8: 44013 | D8: 1
A9: Support | B9: 1 | C9: 44013 | D9: 1
A10: Sales | B10: 3 | C10: 44013 | D10: 3
A11: BI | B11: 8 | C11: 44044 | D11: 8
A12: Support | B12: 3 | C12: 44075 | D12: 3
A13: Sales | B13: 5 | C13: 44075 | D13: 5
... A120: BI | B120: 5 | C120: 45108 | D120: 5

Sheet Hiring Management 2
A1: Department | B1: Skill | C1: Level | D1: Experience | E1: Technology | F1: Date | G1: who's leaving | H1: Location | I1: Salary
A2: BI | B2: Python Engineer, Data science and ETL | C2: L3 | E2: Qlik | F2: 43922
A3: Support | B3: SAP Controls Transformation | C3: L2 | E3: SuperOps PSA | F3: 43922
A4: Sales | B4: Communication+SMS+CMR | C4: L2 | E4: CRM | F4: 43922
A5: Cloud | B5: Cloud Computing | C5: L2 | E5: AWS | F5: 43922
A6: Cloud | B6: .net Developer / C Sharp | C6: L3 | E6: AWS | F6: 43952
A7: QA & QC | B7: ITGC | C7: L3 | E7: MasterControl | F7: 44013
A8: BI | B8: Python Engineer, Data science and ETL | C8: L2 | E8: Qlik | F8: 44013
A9: Support | B9: Data Engineering | C9: L1 | E9: SuperOps PSA | F9: 44013
A10: Sales | B10: Communication+SMS+CMR | C10: L2 | E10: CRM | F10: 44013
A11: BI | B11: Python Engineer, Data science and ETL | C11: L2 | E11: Qlik | F11: 44044
A12: Support | B12: ITGC | C12: L3 | E12: SuperOps PSA | F12: 44075
A13: Sales | B13: Communication+SMS+CMR | C13: L1 | E13: CRM | F13: 44075
... A120: BI | B120: Python Engineer, Data science and ETL | C120: L3 | E120: Power BI | F120: 45108

Sheet Formulas
A1: Table | B1: column | C1: formula
A2: Leave prediction | B2: Leave type | C2: IF(E66="Sick Leave","Sick Leave",IF(E66="Family Function",CHOOSE(RANDBETWEEN(1,3),"Casual Leave","Leave Without Pay","Paid Leave"),IF(E66="Personal Reason",CHOOSE(RANDBETWEEN(1,3),"Casual Leave","Leave Without Pay","Paid Leave"),IF(E66="Documentation Work",CHOOSE(RANDBETWEEN(1,3),"Casual Leave","Leave Without Pay","Paid Leave"),CHOOSE(RANDBETWEEN(1,3),"Casual Leave","Leave Without Pay","Paid Leave")))))
A3: Leave prediction | B3: Reason for Leave | C3: CHOOSE(RANDBETWEEN(1,5),"Sick Leave","Family Outing","Family Function","Documentation Work","Personal Work")
